Workbook

Sheet Лист1

Sheet Биаксплен Новосибирск
A1: =T37 -> 194710.51
A2: ="Отчет по хранению товара за " & TEXT(B5,"ММММ ГГГГ") -> Отчет по хранению товара за Июль 2026
A3: № | B3: дата | D3: Выгрузка кол-во | E3: Загрузка кол-во | F3: Хранение | G3: Резервирование 70 т | H3: Мин. Суточный резерв 0 т | I3: переконсолидация (тонн) | J3: Паллетирование | K3: Ночная загруска выгрузка | L3: стоимость ночной загруски | M3: стоимость выгрузки | N3: стоимость загрузки | O3: стоимость хранения | P3: Стоимость резервирования | Q3: Стоимость мин.суточной бработки | R3: стоимость переконс. | S3: Стоимость паллетирования | T3: итого
A5: 1 | B5: 46204 | F5: 0 | G5: =IF(OR(B5="",NOT(ISERROR(SEARCH("KPI",$A$2))),NOT(ISERROR(SEARCH("Полиом",$A$2)))),0,IF(70-F5<=0,0,70-F5)) -> 70 | L5: =SUM(K5*240) -> 0 | M5: =SUM(D5*120) -> 0 | N5: =SUM(E5*120) -> 0 | O5: =SUM(F5*54) -> 0 | P5: =SUM(G5*54) -> 3780 | Q5: =SUM(H5*120) -> 0 | R5: =SUM(I5*1000) -> 0 | S5: =SUM(J5*140) -> 0 | T5: =SUM(L5:S5) -> 3780
A6: 2 | B6: 46205 | F6: =F5-E6+D6 -> 0 | G6: =IF(OR(B6="",NOT(ISERROR(SEARCH("KPI",$A$2))),NOT(ISERROR(SEARCH("Полиом",$A$2)))),0,IF(70-F6<=0,0,70-F6)) -> 70 | L6: =SUM(K6*240) -> 0 | M6: =SUM(D6*120) -> 0 | N6: =SUM(E6*120) -> 0 | O6: =SUM(F6*54) -> 0 | P6: =SUM(G6*54) -> 3780 | Q6: =SUM(H6*120) -> 0 | R6: =SUM(I6*1000) -> 0 | S6: =SUM(J6*140) -> 0 | T6: =SUM(L6:S6) -> 3780
A7: 3 | B7: 46206 | F7: =F6-E7+D7 -> 0 | G7: =IF(OR(B7="",NOT(ISERROR(SEARCH("KPI",$A$2))),NOT(ISERROR(SEARCH("Полиом",$A$2)))),0,IF(70-F7<=0,0,70-F7)) -> 70 | L7: =SUM(K7*240) -> 0 | M7: =SUM(D7*120) -> 0 | N7: =SUM(E7*120) -> 0 | O7: =SUM(F7*54) -> 0 | P7: =SUM(G7*54) -> 3780 | Q7: =SUM(H7*120) -> 0 | R7: =SUM(I7*1000) -> 0 | S7: =SUM(J7*140) -> 0 | T7: =SUM(L7:S7) -> 3780
A8: 4 | B8: 46207 | F8: =F7-E8+D8 -> 0 | G8: =IF(OR(B8="",NOT(ISERROR(SEARCH("KPI",$A$2))),NOT(ISERROR(SEARCH("Полиом",$A$2)))),0,IF(70-F8<=0,0,70-F8)) -> 70 | L8: =SUM(K8*240) -> 0 | M8: =SUM(D8*120) -> 0 | N8: =SUM(E8*120) -> 0 | O8: =SUM(F8*54) -> 0 | P8: =SUM(G8*54) -> 3780 | Q8: =SUM(H8*120) -> 0 | R8: =SUM(I8*1000) -> 0 | S8: =SUM(J8*140) -> 0 | T8: =SUM(L8:S8) -> 3780
A9: 5 | B9: 46208 | F9: =F8-E9+D9 -> 0 | G9: =IF(OR(B9="",NOT(ISERROR(SEARCH("KPI",$A$2))),NOT(ISERROR(SEARCH("Полиом",$A$2)))),0,IF(70-F9<=0,0,70-F9)) -> 70 | L9: =SUM(K9*240) -> 0 | M9: =SUM(D9*120) -> 0 | N9: =SUM(E9*120) -> 0 | O9: =SUM(F9*54) -> 0 | P9: =SUM(G9*54) -> 3780 | Q9: =SUM(H9*120) -> 0 | R9: =SUM(I9*1000) -> 0 | S9: =SUM(J9*140) -> 0 | T9: =SUM(L9:S9) -> 3780
A10: 6 | B10: 46209 | F10: =F9-E10+D10 -> 0 | G10: =IF(OR(B10="",NOT(ISERROR(SEARCH("KPI",$A$2))),NOT(ISERROR(SEARCH("Полиом",$A$2)))),0,IF(70-F10<=0,0,70-F10)) -> 70 | L10: =SUM(K10*240) -> 0 | M10: =SUM(D10*120) -> 0 | N10: =SUM(E10*120) -> 0 | O10: =SUM(F10*54) -> 0 | P10: =SUM(G10*54) -> 3780 | Q10: =SUM(H10*120) -> 0 | R10: =SUM(I10*1000) -> 0 | S10: =SUM(J10*140) -> 0 | T10: =SUM(L10:S10) -> 3780
A11: 7 | B11: 46210 | F11: =F10-E11+D11 -> 0 | G11: =IF(OR(B11="",NOT(ISERROR(SEARCH("KPI",$A$2))),NOT(ISERROR(SEARCH("Полиом",$A$2)))),0,IF(70-F11<=0,0,70-F11)) -> 70 | L11: =SUM(K11*240) -> 0 | M11: =SUM(D11*120) -> 0 | N11: =SUM(E11*120) -> 0 | O11: =SUM(F11*54) -> 0 | P11: =SUM(G11*54) -> 3780 | Q11: =SUM(H11*120) -> 0 | R11: =SUM(I11*1000) -> 0 | S11: =SUM(J11*140) -> 0 | T11: =SUM(L11:S11) -> 3780
A12: 8 | B12: 46211 | F12: =F11-E12+D12 -> 0 | G12: =IF(OR(B12="",NOT(ISERROR(SEARCH("KPI",$A$2))),NOT(ISERROR(SEARCH("Полиом",$A$2)))),0,IF(70-F12<=0,0,70-F12)) -> 70 | L12: =SUM(K12*240) -> 0 | M12: =SUM(D12*120) -> 0 | N12: =SUM(E12*120) -> 0 | O12: =SUM(F12*54) -> 0 | P12: =SUM(G12*54) -> 3780 | Q12: =SUM(H12*120) -> 0 | R12: =SUM(I12*1000) -> 0 | S12: =SUM(J12*140) -> 0 | T12: =SUM(L12:S12) -> 3780
A13: 9 | B13: 46212 | F13: =F12-E13+D13 -> 0 | G13: =IF(OR(B13="",NOT(ISERROR(SEARCH("KPI",$A$2))),NOT(ISERROR(SEARCH("Полиом",$A$2)))),0,IF(70-F13<=0,0,70-F13)) -> 70 | L13: =SUM(K13*240) -> 0 | M13: =SUM(D13*120) -> 0 | N13: =SUM(E13*120) -> 0 | O13: =SUM(F13*54) -> 0 | P13: =SUM(G13*54) -> 3780 | Q13: =SUM(H13*120) -> 0 | R13: =SUM(I13*1000) -> 0 | S13: =SUM(J13*140) -> 0 | T13: =SUM(L13:S13) -> 3780
A14: 10 | B14: 46213 | F14: =F13-E14+D14 -> 0 | G14: =IF(OR(B14="",NOT(ISERROR(SEARCH("KPI",$A$2))),NOT(ISERROR(SEARCH("Полиом",$A$2)))),0,IF(70-F14<=0,0,70-F14)) -> 70 | L14: =SUM(K14*240) -> 0 | M14: =SUM(D14*120) -> 0 | N14: =SUM(E14*120) -> 0 | O14: =SUM(F14*54) -> 0 | P14: =SUM(G14*54) -> 3780 | Q14: =SUM(H14*120) -> 0 | R14: =SUM(I14*1000) -> 0 | S14: =SUM(J14*140) -> 0 | T14: =SUM(L14:S14) -> 3780
A15: 11 | B15: 46214 | F15: =F14-E15+D15 -> 0 | G15: =IF(OR(B15="",NOT(ISERROR(SEARCH("KPI",$A$2))),NOT(ISERROR(SEARCH("Полиом",$A$2)))),0,IF(70-F15<=0,0,70-F15)) -> 70 | L15: =SUM(K15*240) -> 0 | M15: =SUM(D15*120) -> 0 | N15: =SUM(E15*120) -> 0 | O15: =SUM(F15*54) -> 0 | P15: =SUM(G15*54) -> 3780 | Q15: =SUM(H15*120) -> 0 | R15: =SUM(I15*1000) -> 0 | S15: =SUM(J15*140) -> 0 | T15: =SUM(L15:S15) -> 3780
A16: 12 | B16: 46215 | F16: =F15-E16+D16 -> 0 | G16: =IF(OR(B16="",NOT(ISERROR(SEARCH("KPI",$A$2))),NOT(ISERROR(SEARCH("Полиом",$A$2)))),0,IF(70-F16<=0,0,70-F16)) -> 70 | L16: =SUM(K16*240) -> 0 | M16: =SUM(D16*120) -> 0 | N16: =SUM(E16*120) -> 0 | O16: =SUM(F16*54) -> 0 | P16: =SUM(G16*54) -> 3780 | Q16: =SUM(H16*120) -> 0 | R16: =SUM(I16*1000) -> 0 | S16: =SUM(J16*140) -> 0 | T16: =SUM(L16:S16) -> 3780
A17: 13 | B17: 46216 | F17: =F16-E17+D17 -> 0 | G17: =IF(OR(B17="",NOT(ISERROR(SEARCH("KPI",$A$2))),NOT(ISERROR(SEARCH("Полиом",$A$2)))),0,IF(70-F17<=0,0,70-F17)) -> 70 | L17: =SUM(K17*240) -> 0 | M17: =SUM(D17*120) -> 0 | N17: =SUM(E17*120) -> 0 | O17: =SUM(F17*54) -> 0 | P17: =SUM(G17*54) -> 3780 | Q17: =SUM(H17*120) -> 0 | R17: =SUM(I17*1000) -> 0 | S17: =SUM(J17*140) -> 0 | T17: =SUM(L17:S17) -> 3780
... A24: 20 | B24: 46223 | F24: =F23-E24+D24 -> 0 | G24: =IF(OR(B24="",NOT(ISERROR(SEARCH("KPI",$A$2))),NOT(ISERROR(SEARCH("Полиом",$A$2)))),0,IF(70-F24<=0,0,70-F24)) -> 70 | L24: =SUM(K24*240) -> 0 | M24: =SUM(D24*120) -> 0 | N24: =SUM(E24*120) -> 0 | O24: =SUM(F24*54) -> 0 | P24: =SUM(G24*54) -> 3780 | Q24: =SUM(H24*120) -> 0 | R24: =SUM(I24*1000) -> 0 | S24: =SUM(J24*140) -> 0 | T24: =SUM(L24:S24) -> 3780
A25: 21 | B25: 46224 | D25: 35.0864 | F25: =F24-E25+D25 -> 35.0864 | G25: =IF(OR(B25="",NOT(ISERROR(SEARCH("KPI",$A$2))),NOT(ISERROR(SEARCH("Полиом",$A$2)))),0,IF(70-F25<=0,0,70-F25)) -> 34.9136 | L25: =SUM(K25*240) -> 0 | M25: =SUM(D25*120) -> 4210.368 | N25: =SUM(E25*120) -> 0 | O25: =SUM(F25*54) -> 1894.6656 | P25: =SUM(G25*54) -> 1885.3344 | Q25: =SUM(H25*120) -> 0 | R25: =SUM(I25*1000) -> 0 | S25: =SUM(J25*140) -> 0 | T25: =SUM(L25:S25) -> 7990.368
A26: 22 | B26: 46225 | D26: 36.2845 | F26: =F25-E26+D26 -> 71.3709 | G26: =IF(OR(B26="",NOT(ISERROR(SEARCH("KPI",$A$2))),NOT(ISERROR(SEARCH("Полиом",$A$2)))),0,IF(70-F26<=0,0,70-F26)) -> 0 | L26: =SUM(K26*240) -> 0 | M26: =SUM(D26*120) -> 4354.14 | N26: =SUM(E26*120) -> 0 | O26: =SUM(F26*54) -> 3854.0286 | P26: =SUM(G26*54) -> 0 | Q26: =SUM(H26*120) -> 0 | R26: =SUM(I26*1000) -> 0 | S26: =SUM(J26*140) -> 0 | T26: =SUM(L26:S26) -> 8208.1686
A27: 23 | B27: 46226 | E27: 14.0867 | F27: =F26-E27+D27 -> 57.2842 | G27: =IF(OR(B27="",NOT(ISERROR(SEARCH("KPI",$A$2))),NOT(ISERROR(SEARCH("Полиом",$A$2)))),0,IF(70-F27<=0,0,70-F27)) -> 12.7158 | L27: =SUM(K27*240) -> 0 | M27: =SUM(D27*120) -> 0 | N27: =SUM(E27*120) -> 1690.404 | O27: =SUM(F27*54) -> 3093.3468 | P27: =SUM(G27*54) -> 686.6532 | Q27: =SUM(H27*120) -> 0 | R27: =SUM(I27*1000) -> 0 | S27: =SUM(J27*140) -> 0 | T27: =SUM(L27:S27) -> 5470.404
A28: 24 | B28: 46227 | F28: =F27-E28+D28 -> 57.2842 | G28: =IF(OR(B28="",NOT(ISERROR(SEARCH("KPI",$A$2))),NOT(ISERROR(SEARCH("Полиом",$A$2)))),0,IF(70-F28<=0,0,70-F28)) -> 12.7158 | L28: =SUM(K28*240) -> 0 | M28: =SUM(D28*120) -> 0 | N28: =SUM(E28*120) -> 0 | O28: =SUM(F28*54) -> 3093.3468 | P28: =SUM(G28*54) -> 686.6532 | Q28: =SUM(H28*120) -> 0 | R28: =SUM(I28*1000) -> 0 | S28: =SUM(J28*140) -> 0 | T28: =SUM(L28:S28) -> 3780
A29: 25 | B29: 46228 | F29: =F28-E29+D29 -> 57.2842 | G29: =IF(OR(B29="",NOT(ISERROR(SEARCH("KPI",$A$2))),NOT(ISERROR(SEARCH("Полиом",$A$2)))),0,IF(70-F29<=0,0,70-F29)) -> 12.7158 | L29: =SUM(K29*240) -> 0 | M29: =SUM(D29*120) -> 0 | N29: =SUM(E29*120) -> 0 | O29: =SUM(F29*54) -> 3093.3468 | P29: =SUM(G29*54) -> 686.6532 | Q29: =SUM(H29*120) -> 0 | R29: =SUM(I29*1000) -> 0 | S29: =SUM(J29*140) -> 0 | T29: =SUM(L29:S29) -> 3780
A30: 26 | B30: 46229 | F30: =F29-E30+D30 -> 57.2842 | G30: =IF(OR(B30="",NOT(ISERROR(SEARCH("KPI",$A$2))),NOT(ISERROR(SEARCH("Полиом",$A$2)))),0,IF(70-F30<=0,0,70-F30)) -> 12.7158 | L30: =SUM(K30*240) -> 0 | M30: =SUM(D30*120) -> 0 | N30: =SUM(E30*120) -> 0 | O30: =SUM(F30*54) -> 3093.3468 | P30: =SUM(G30*54) -> 686.6532 | Q30: =SUM(H30*120) -> 0 | R30: =SUM(I30*1000) -> 0 | S30: =SUM(J30*140) -> 0 | T30: =SUM(L30:S30) -> 3780
A31: 27 | B31: 46230 | D31: 36.0562 | F31: =F30-E31+D31 -> 93.3404 | G31: =IF(OR(B31="",NOT(ISERROR(SEARCH("KPI",$A$2))),NOT(ISERROR(SEARCH("Полиом",$A$2)))),0,IF(70-F31<=0,0,70-F31)) -> 0 | L31: =SUM(K31*240) -> 0 | M31: =SUM(D31*120) -> 4326.744 | N31: =SUM(E31*120) -> 0 | O31: =SUM(F31*54) -> 5040.3816 | P31: =SUM(G31*54) -> 0 | Q31: =SUM(H31*120) -> 0 | R31: =SUM(I31*1000) -> 0 | S31: =SUM(J31*140) -> 0 | T31: =SUM(L31:S31) -> 9367.1256
A32: 28 | B32: 46231 | D32: 35.7391 | F32: =F31-E32+D32 -> 129.0795 | G32: =IF(OR(B32="",NOT(ISERROR(SEARCH("KPI",$A$2))),NOT(ISERROR(SEARCH("Полиом",$A$2)))),0,IF(70-F32<=0,0,70-F32)) -> 0 | L32: =SUM(K32*240) -> 0 | M32: =SUM(D32*120) -> 4288.692 | N32: =SUM(E32*120) -> 0 | O32: =SUM(F32*54) -> 6970.293 | P32: =SUM(G32*54) -> 0 | Q32: =SUM(H32*120) -> 0 | R32: =SUM(I32*1000) -> 0 | S32: =SUM(J32*140) -> 0 | T32: =SUM(L32:S32) -> 11258.985
A33: 29 | B33: 46232 | F33: =F32-E33+D33 -> 129.0795 | G33: =IF(OR(B33="",NOT(ISERROR(SEARCH("KPI",$A$2))),NOT(ISERROR(SEARCH("Полиом",$A$2)))),0,IF(70-F33<=0,0,70-F33)) -> 0 | L33: =SUM(K33*240) -> 0 | M33: =SUM(D33*120) -> 0 | N33: =SUM(E33*120) -> 0 | O33: =SUM(F33*54) -> 6970.293 | P33: =SUM(G33*54) -> 0 | Q33: =SUM(H33*120) -> 0 | R33: =SUM(I33*1000) -> 0 | S33: =SUM(J33*140) -> 0 | T33: =SUM(L33:S33) -> 6970.293
A34: 30 | B34: 46233 | F34: =F33-E34+D34 -> 129.0795 | G34: =IF(OR(B34="",NOT(ISERROR(SEARCH("KPI",$A$2))),NOT(ISERROR(SEARCH("Полиом",$A$2)))),0,IF(70-F34<=0,0,70-F34)) -> 0 | L34: =SUM(K34*240) -> 0 | M34: =SUM(D34*120) -> 0 | N34: =SUM(E34*120) -> 0 | O34: =SUM(F34*54) -> 6970.293 | P34: =SUM(G34*54) -> 0 | Q34: =SUM(H34*120) -> 0 | R34: =SUM(I34*1000) -> 0 | S34: =SUM(J34*140) -> 0 | T34: =SUM(L34:S34) -> 6970.293
B35: 46234 | D35: 51.1505 | E35: 8.3736 | F35: =F34-E35+D35 -> 171.8564 | G35: =IF(OR(B35="",NOT(ISERROR(SEARCH("KPI",$A$2))),NOT(ISERROR(SEARCH("Полиом",$A$2)))),0,IF(70-F35<=0,0,70-F35)) -> 0 | L35: =SUM(K35*240) -> 0 | M35: =SUM(D35*120) -> 6138.06 | N35: =SUM(E35*120) -> 1004.832 | O35: =SUM(F35*54) -> 9280.2456 | P35: =SUM(G35*54) -> 0 | Q35: =SUM(H35*120) -> 0 | R35: =SUM(I35*1000) -> 0 | S35: =SUM(J35*140) -> 0 | T35: =SUM(L35:S35) -> 16423.138
F36: =SUM(F5:F35) -> 988.0294 | G36: =SUM(G5:G35) -> 1485.7768 | H36: =SUM(H5:H35) -> 0 | I36: =SUM(I5:I35) -> 0 | J36: =SUM(J5:J35) -> 0 | K36: =SUM(K5:K35) -> 0 | L36: =SUM(L5:L35) -> 0 | M36: =SUM(M5:M35) -> 23318.004 | ... T36: =SUM(T5:T35) -> 159598.77
T37: =T36*1.22 -> 194710.51

Sheet ИТОГО
A1: =G16 -> 1.4708465e+08
I2: ТОП
A3: Склад | B3: Сибур | C3: Завод | D3: Русвинил | E3: Клиенты сибура | F3: Остальные | G3: Итого | I3: Казань_Автосервисная | J3: 23143268
A4: Баумана | B4: =INDEX($M$45:$M$54,MATCH(A4,$A$45:$A$54,0),1) -> 7960861.4 | C4: 0 | D4: =INDEX($B$57:$B$73,MATCH(A4,$A$57:$A$73,0),1) -> 0 | E4: =SUMIF($F$19:$F$42,A4,$G$19:$G$42) -> 1138316.7 | F4: =SUMIF($B$19:$B$27,A4,$C$19:$C$27) -> 184417 | G4: =SUM(B4:F4) -> 9283595.1 | I4: Нижнекамск завод | J4: 19482962
A5: Новикова-Прибоя | B5: =INDEX($M$45:$M$54,MATCH(A5,$A$45:$A$54,0),1) -> 10570080 | C5: 0 | D5: =INDEX($B$57:$B$73,MATCH(A5,$A$57:$A$73,0),1) -> 0 | E5: =SUMIF($F$19:$F$42,A5,$G$19:$G$42) -> 179523 | F5: =SUMIF($B$19:$B$27,A5,$C$19:$C$27) -> 0 | G5: =SUM(B5:F5) -> 10749603 | I5: Новикова-Прибоя | J5: 14483152
A6: Екатеринбург | B6: =INDEX($M$45:$M$54,MATCH(A6,$A$45:$A$54,0),1) -> 11713975 | C6: 0 | D6: =INDEX($B$57:$B$73,MATCH(A6,$A$57:$A$73,0),1) -> 0 | E6: =SUMIF($F$19:$F$42,A6,$G$19:$G$42) -> 0 | F6: =SUMIF($B$19:$B$27,A6,$C$19:$C$27) -> 0 | G6: =SUM(B6:F6) -> 11713975 | I6: Екатеринбург | J6: 11908609
A7: Новосибирск | B7: =INDEX($M$45:$M$54,MATCH(A7,$A$45:$A$54,0),1) -> 5953601.8 | C7: 0 | D7: =INDEX($B$57:$B$73,MATCH(A7,$A$57:$A$73,0),1) -> 0 | E7: =SUMIF($F$19:$F$42,A7,$G$19:$G$42) -> 194710.51 | F7: =SUMIF($B$19:$B$27,A7,$C$19:$C$27) -> 0 | G7: =SUM(B7:F7) -> 6148312.3 | I7: Баумана | J7: 11544503
A8: Новосибирск_Пасечная | B8: =INDEX($M$45:$M$54,MATCH(A8,$A$45:$A$54,0),1) -> 5686668.2 | C8: 0 | D8: =INDEX($B$57:$B$73,MATCH(A8,$A$57:$A$73,0),1) -> 0 | E8: =SUMIF($F$19:$F$42,A8,$G$19:$G$42) -> 0 | F8: =SUMIF($B$19:$B$27,A8,$C$19:$C$27) -> 0 | G8: =SUM(B8:F8) -> 5686668.2
A9: Казань_Автосервисная | B9: =INDEX($M$45:$M$54,MATCH(A9,$A$45:$A$54,0),1) -> 18503047 | C9: 0 | D9: =INDEX($B$57:$B$73,MATCH(A9,$A$57:$A$73,0),1) -> 0 | E9: =SUMIF($F$19:$F$42,A9,$G$19:$G$42) -> 0 | F9: =SUMIF($B$19:$B$27,A9,$C$19:$C$27) -> 0 | G9: =SUM(B9:F9) -> 18503047 | I9: Казань_Приволжская | J9: 9900926.9
A10: Казань_Приволжская | B10: =INDEX($M$45:$M$54,MATCH(A10,$A$45:$A$54,0),1) -> 9749437.5 | C10: 0 | D10: =INDEX($B$57:$B$73,MATCH(A10,$A$57:$A$73,0),1) -> 0 | E10: =SUMIF($F$19:$F$42,A10,$G$19:$G$42) -> 0 | F10: =SUMIF($B$19:$B$27,A10,$C$19:$C$27) -> 0 | G10: =SUM(B10:F10) -> 9749437.5 | I10: Зеленодольск | J10: 9082789.1
A11: Зеленодольск | B11: =INDEX($M$45:$M$54,MATCH(A11,$A$45:$A$54,0),1) -> 8115504.1 | C11: 0 | D11: =INDEX($B$57:$B$73,MATCH(A11,$A$57:$A$73,0),1) -> 0 | E11: =SUMIF($F$19:$F$42,A11,$G$19:$G$42) -> 86302.8 | F11: =SUMIF($B$19:$B$27,A11,$C$19:$C$27) -> 0 | G11: =SUM(B11:F11) -> 8201806.9 | I11: Новосибирск | J11: 7932975.6
A12: Нижнекамск | B12: =INDEX($M$45:$M$54,MATCH(A12,$A$45:$A$54,0),1) -> 0 | C12: 0 | D12: =INDEX($B$57:$B$73,MATCH(A12,$A$57:$A$73,0),1) -> 0 | E12: =SUMIF($F$19:$F$42,A12,$G$19:$G$42) -> 0 | F12: =SUMIF($B$19:$B$27,A12,$C$19:$C$27) -> 0 | G12: =SUM(B12:F12) -> 0 | I12: Нижнекамск | J12: 7580244.6
A13: Нижнекамск завод | B13: 0 | C13: =C29+C37 -> 53285555 | D13: =INDEX($B$57:$B$73,MATCH(A13,$A$57:$A$73,0),1) -> 0 | E13: =SUMIF($F$19:$F$42,A13,$G$19:$G$42) -> 0 | F13: =SUMIF($B$19:$B$27,A13,$C$19:$C$27) -> 0 | G13: =SUM(B13:F13) -> 53285555 | I13: ГАЗ | J13: 6720000
A14: ЕкатеринбургЧкаловский | B14: =INDEX($M$45:$M$54,MATCH(A14,$A$45:$A$54,0),1) -> 11372374 | C14: 0 | D14: =INDEX($B$57:$B$73,MATCH(A14,$A$57:$A$73,0),1) -> 0 | E14: =SUMIF($F$19:$F$42,A14,$G$19:$G$42) -> 0 | F14: =SUMIF($B$19:$B$27,A14,$C$19:$C$27) -> 0 | G14: =SUM(B14:F14) -> 11372374 | I14: Монастырка | J14: 2464921.6
A15: Завод "Посуда" | B15: 0 | C15: 0 | D15: 0 | E15: =SUMIF($F$19:$F$42,A15,$G$19:$G$42) -> 0 | F15: 2390273 | G15: =SUM(B15:F15) -> 2390273
B16: =SUM(B4:B15) -> 89625549 | C16: =SUM(C4:C15) -> 53285555 | D16: =SUM(D4:D15) -> 0 | E16: =SUM(E4:E15) -> 1598853 | F16: =SUM(F4:F15) -> 2574690 | G16: =SUM(G4:G15) -> 1.4708465e+08
A18: Остальные клиенты | C18: =SUM(C19:C27) -> 184417 | E18: Клиенты сибура | G18: =SUM(G19:G41) -> 1598853
A19: Стройтех | B19: Баумана | C19: {=IFERROR(INDIRECT("'" & A19 & "'!A1"),)} -> 55733 | E19: Приоритет | F19: Баумана | G19: {=IFERROR(INDIRECT("'" & E19 & " " & F19 & "'!A1"),0)} -> 122207.4
A20: Ергарда | B20: Баумана | C20: {=IFERROR(INDIRECT("'" & A20 & "'!A1"),)} -> 7812 | E20: Фармпласт | F20: Баумана | G20: {=IFERROR(INDIRECT("'" & E20 & " " & F20 & "'!A1"),0)} -> 416008.41
A21: Литейные решения | B21: Баумана | C21: {=IFERROR(INDIRECT("'" & A21 & "'!A1"),)} -> 102164 | E21: Юг Полимер | F21: Баумана | G21: {=IFERROR(INDIRECT("'" & E21 & " " & F21 & "'!A1"),0)} -> 337898.52
A22: Сандекс | B22: Баумана | C22: {=IFERROR(INDIRECT("'" & A22 & "'!A1"),)} -> 17102.4 | E22: Центрополимер | F22: Екатеринбург | G22: {=IFERROR(INDIRECT("'" & E22 & " " & F22 & "'!A1"),0)} -> 0
A23: ЛС-Техномет | B23: Баумана | C23: {=IFERROR(INDIRECT("'" & A23 & "'!A1"),)} -> 1605.6 | E23: Приоритет | F23: Екатеринбург | G23: {=IFERROR(INDIRECT("'" & E23 & " " & F23 & "'!A1"),0)} -> 0
A24: РусДжам | B24: ГАЗ | C24: {=IFERROR(INDIRECT("'" & A24 & "'!A1"),)} -> 0 | E24: Фармпласт | F24: Екатеринбург | G24: {=IFERROR(INDIRECT("'" & E24 & " " & F24 & "'!A1"),0)} -> 0
A25: Виго | B25: Новикова-Прибоя | C25: {=IFERROR(INDIRECT("'" & A25 & "'!A1"),)} -> 0 | E25: Приоритет | F25: Зеленодольск | G25: {=IFERROR(INDIRECT("'" & E25 & " " & F25 & "'!A1"),0)} -> 0
A26: Доктор Франк | B26: Новикова-Прибоя | C26: {=IFERROR(INDIRECT("'" & A26 & "'!A1"),)} -> 0 | E26: Данафлекс | F26: Зеленодольск | G26: {=IFERROR(INDIRECT("'" & E26 & " " & F26 & "'!t37"),0)} -> 0
A27: Нефтезол | B27: Новикова-Прибоя | C27: {=IFERROR(INDIRECT("'" & A27 & "'!A1"),)} -> 0 | E27: ИП Ксендз | F27: Нижнекамск | G27: {=IFERROR(INDIRECT("'" & E27 & " " & F27 & "'!A1"),0)} -> 0
E28: Фармпласт | F28: Новикова-Прибоя | G28: {=IFERROR(INDIRECT("'" & E28 & " " & F28 & "'!A1"),0)} -> 102937.5
A29: Нижнекамск завод | C29: =SUM(C30:C35) -> 44423720 | E29: Центрополимер | F29: Новикова-Прибоя | G29: {=IFERROR(INDIRECT("'" & E29 & " " & F29 & "'!A1"),0)} -> 0
A30: ПРР | C30: {=INDIRECT("'" & A29 & "'!F17")} -> 15827299 | E30: Юг Полимер | F30: Новикова-Прибоя | G30: {=IFERROR(INDIRECT("'" & E30 & " " & F30 & "'!A1"),0)} -> 0
A31: Кладовки | C31: {=INDIRECT("'" & A29 & "'!F16")} -> 0 | E31: Приоритет | F31: Новикова-Прибоя | G31: {=IFERROR(INDIRECT("'" & E31 & " " & F31 & "'!A1"),0)} -> 76585.5
A32: Стропальщики | C32: {=INDIRECT("'" & A29 & "'!F18")} -> 786900 | E32: Биаксплен | F32: Новосибирск | G32: {=IFERROR(INDIRECT("'" & E32 & " " & F32 & "'!A1"),0)} -> 194710.51
A33: Мойка контейнеров | C33: {=INDIRECT("'" & A29 & "'!F19")} -> 1879800 | E33: Центрополимер | F33: Новосибирск | G33: {=IFERROR(INDIRECT("'" & E33 & " " & F33 & "'!A1"),0)} -> 0
A34: МТО | C34: {=INDIRECT("'" & A29 & "'!F20")} -> 20584666 | E34: Фармпласт | F34: Новосибирск | G34: {=IFERROR(INDIRECT("'" & E34 & " " & F34 & "'!A1"),0)} -> 0
A35: МТО 2520 | C35: {=INDIRECT("'" & A29 & "'!F21")} -> 5345055 | E35: Центрополимер | F35: Зеленодольск | G35: {=IFERROR(INDIRECT("'" & E35 & " " & F35 & "'!A1"),0)} -> 86302.8
E36: Юг Полимер | F36: Зеленодольск | G36: {=IFERROR(INDIRECT("'" & E36 & " " & F36 & "'!A1"),0)} -> 0
A37: Контейнерные площадки | C37: =SUM(C38:C42) -> 8861835 | E37: Фармпласт | F37: Казань_Автосервисная | G37: {=IFERROR(INDIRECT("'" & E37 & " " & F37 & "'!A1"),0)} -> 0
A38: КОС | C38: 1797615 | E38: Приоритет | F38: Казань_Приволжская | G38: {=IFERROR(INDIRECT("'" & E38 & " " & F38 & "'!A1"),0)} -> 0
A39: Нижнекамск | C39: 7064220 | E39: Центрополимер | F39: Баумана | G39: {=IFERROR(INDIRECT("'" & E39 & " " & F39 & "'!A1"),0)} -> 262202.4
E40: Приоритет | F40: Казань_Автосервисная | G40: {=IFERROR(INDIRECT("'" & E40 & " " & F40 & "'!A1"),0)} -> 0
E41: Оникс | F41: Нижнекамск | G41: {=IFERROR(INDIRECT("'" & E41 & " " & F41 & "'!A1"),0)} -> 0
A43: СИБУР | K43: =SUM(M45:M54) -> 89625549
B44: KPI | C44: Полиом | D44: Полимеры | E44: Каучук | F44: ПСОН | G44: Данафлекс | H44: СБС | I44: Порошок | J44: НПЭГ | K44: Экспорт | L44: Доп услуги | M44: ИТОГО
A45: Баумана | B45: {=IFERROR(INDIRECT("'" & $A45 & " " & B$44 & "'!T37"),)} -> 1518.02 | C45: {=IFERROR(INDIRECT("'" & $A45 & " " & C$44 & "'!T37"),)} -> 290063.38 | D45: {=IFERROR(INDIRECT("'" & $A45 & " " & D$44 & "'!T37"),)} -> 7669280 | E45: {=IFERROR(INDIRECT("'" & $A45 & " " & E$44 & "'!T37"),)} -> 0 | F45: {=IFERROR(INDIRECT("'" & $A45 & " " & F$44 & "'!T37"),)} -> 0 | G45: {=IFERROR(INDIRECT("'" & $A45 & " " & G$44 & "'!T37"),)} -> 0 | H45: {=IFERROR(INDIRECT("'" & $A45 & " " & H$44 & "'!T37"),)} -> 0 | I45: {=IFERROR(INDIRECT("'" & $A45 & " " & I$44 & "'!T37"),)} -> 0 | J45: {=IFERROR(INDIRECT("'" & $A45 & " " & J$44 & "'!T37"),)} -> 0 | K45: {=IFERROR(INDIRECT("'" & $A45 & " " & K$44 & "'!G12"),)} -> 0 | L45: {=IFERROR(INDIRECT("'" & $A45 & " " & L$44 & "'!F14"),)} -> 0 | M45: =SUM(B45:L45) -> 7960861.4
A46: Новикова-Прибоя | B46: {=IFERROR(INDIRECT("'" & $A46 & " " & B$44 & "'!T37"),)} -> 18899.09 | C46: {=IFERROR(INDIRECT("'" & $A46 & " " & C$44 & "'!T37"),)} -> 614712.13 | D46: {=IFERROR(INDIRECT("'" & $A46 & " " & D$44 & "'!T37"),)} -> 9936468.8 | E46: {=IFERROR(INDIRECT("'" & $A46 & " " & E$44 & "'!T37"),)} -> 0 | F46: {=IFERROR(INDIRECT("'" & $A46 & " " & F$44 & "'!T37"),)} -> 0 | G46: {=IFERROR(INDIRECT("'" & $A46 & " " & G$44 & "'!T37"),)} -> 0 | H46: {=IFERROR(INDIRECT("'" & $A46 & " " & H$44 & "'!T37"),)} -> 0 | I46: {=IFERROR(INDIRECT("'" & $A46 & " " & I$44 & "'!T37"),)} -> 0 | J46: {=IFERROR(INDIRECT("'" & $A46 & " " & J$44 & "'!T37"),)} -> 0 | K46: {=IFERROR(INDIRECT("'" & $A46 & " " & K$44 & "'!G12"),)} -> 0 | L46: {=IFERROR(INDIRECT("'" & $A46 & " " & L$44 & "'!F14"),)} -> 0 | M46: =SUM(B46:L46) -> 10570080
A47: Екатеринбург | B47: {=IFERROR(INDIRECT("'" & $A47 & " " & B$44 & "'!T37"),)} -> 285691.12 | C47: {=IFERROR(INDIRECT("'" & $A47 & " " & C$44 & "'!T37"),)} -> 450359.75 | D47: {=IFERROR(INDIRECT("'" & $A47 & " " & D$44 & "'!T37"),)} -> 10841726 | E47: {=IFERROR(INDIRECT("'" & $A47 & " " & E$44 & "'!T37"),)} -> 0 | F47: {=IFERROR(INDIRECT("'" & $A47 & " " & F$44 & "'!T37"),)} -> 0 | G47: {=IFERROR(INDIRECT("'" & $A47 & " " & G$44 & "'!T37"),)} -> 0 | H47: {=IFERROR(INDIRECT("'" & $A47 & " " & H$44 & "'!T37"),)} -> 0 | I47: {=IFERROR(INDIRECT("'" & $A47 & " " & I$44 & "'!T37"),)} -> 0 | J47: {=IFERROR(INDIRECT("'" & $A47 & " " & J$44 & "'!T37"),)} -> 121557.99 | K47: {=IFERROR(INDIRECT("'" & $A47 & " " & K$44 & "'!G12"),)} -> 14640 | L47: {=IFERROR(INDIRECT("'" & $A47 & " " & L$44 & "'!F14"),)} -> 0 | M47: =SUM(B47:L47) -> 11713975
A48: Новосибирск | B48: {=IFERROR(INDIRECT("'" & $A48 & " " & B$44 & "'!T37"),)} -> 1031.88 | C48: {=IFERROR(INDIRECT("'" & $A48 & " " & C$44 & "'!T37"),)} -> 89197.91 | D48: {=IFERROR(INDIRECT("'" & $A48 & " " & D$44 & "'!T37"),)} -> 4263673.8 | E48: {=IFERROR(INDIRECT("'" & $A48 & " " & E$44 & "'!T37"),)} -> 0 | F48: {=IFERROR(INDIRECT("'" & $A48 & " " & F$44 & "'!T37"),)} -> 0 | G48: {=IFERROR(INDIRECT("'" & $A48 & " " & G$44 & "'!T37"),)} -> 0 | H48: {=IFERROR(INDIRECT("'" & $A48 & " " & H$44 & "'!T37"),)} -> 0 | I48: {=IFERROR(INDIRECT("'" & $A48 & " " & I$44 & "'!T37"),)} -> 1599698.2 | J48: {=IFERROR(INDIRECT("'" & $A48 & " " & J$44 & "'!T37"),)} -> 0 | K48: {=IFERROR(INDIRECT("'" & $A48 & " " & K$44 & "'!G12"),)} -> 0 | L48: {=IFERROR(INDIRECT("'" & $A48 & " " & L$44 & "'!F14"),)} -> 0 | M48: =SUM(B48:L48) -> 5953601.8
A49: Новосибирск_Пасечная | B49: {=IFERROR(INDIRECT("'" & $A49 & " " & B$44 & "'!T37"),)} -> 0 | C49: {=IFERROR(INDIRECT("'" & $A49 & " " & C$44 & "'!T37"),)} -> 0 | D49: {=IFERROR(INDIRECT("'" & $A49 & " " & D$44 & "'!T37"),)} -> 0 | E49: {=IFERROR(INDIRECT("'" & $A49 & " " & E$44 & "'!T37"),)} -> 0 | F49: {=IFERROR(INDIRECT("'" & $A49 & " " & F$44 & "'!T37"),)} -> 0 | G49: {=IFERROR(INDIRECT("'" & $A49 & " " & G$44 & "'!T37"),)} -> 0 | H49: {=IFERROR(INDIRECT("'" & $A49 & " " & H$44 & "'!T37"),)} -> 0 | I49: {=IFERROR(INDIRECT("'" & $A49 & " " & I$44 & "'!T37"),)} -> 5686668.2 | J49: {=IFERROR(INDIRECT("'" & $A49 & " " & J$44 & "'!T37"),)} -> 0 | K49: {=IFERROR(INDIRECT("'" & $A49 & " " & K$44 & "'!G12"),)} -> 0 | L49: {=IFERROR(INDIRECT("'" & $A49 & " " & L$44 & "'!F14"),)} -> 0 | M49: =SUM(B49:L49) -> 5686668.2
A50: Казань_Автосервисная | B50: {=IFERROR(INDIRECT("'" & $A50 & " " & B$44 & "'!T37"),)} -> 0 | C50: {=IFERROR(INDIRECT("'" & $A50 & " " & C$44 & "'!T37"),)} -> 210532.3 | D50: {=IFERROR(INDIRECT("'" & $A50 & " " & D$44 & "'!T37"),)} -> 18243715 | E50: {=IFERROR(INDIRECT("'" & $A50 & " " & E$44 & "'!T37"),)} -> 0 | F50: {=IFERROR(INDIRECT("'" & $A50 & " " & F$44 & "'!T37"),)} -> 0 | G50: {=IFERROR(INDIRECT("'" & $A50 & " " & G$44 & "'!T37"),)} -> 0 | H50: {=IFERROR(INDIRECT("'" & $A50 & " " & H$44 & "'!T37"),)} -> 0 | I50: {=IFERROR(INDIRECT("'" & $A50 & " " & I$44 & "'!T37"),)} -> 0 | J50: {=IFERROR(INDIRECT("'" & $A50 & " " & J$44 & "'!T37"),)} -> 0 | K50: {=IFERROR(INDIRECT("'" & $A50 & " " & K$44 & "'!G12"),)} -> 48800 | L50: {=IFERROR(INDIRECT("'" & $A50 & " " & L$44 & "'!F14"),)} -> 0 | M50: =SUM(B50:L50) -> 18503047
A51: Казань_Приволжская | B51: {=IFERROR(INDIRECT("'" & $A51 & " " & B$44 & "'!T37"),)} -> 0 | C51: {=IFERROR(INDIRECT("'" & $A51 & " " & C$44 & "'!T37"),)} -> 0 | D51: {=IFERROR(INDIRECT("'" & $A51 & " " & D$44 & "'!T37"),)} -> 9749437.5 | E51: {=IFERROR(INDIRECT("'" & $A51 & " " & E$44 & "'!T37"),)} -> 0 | F51: {=IFERROR(INDIRECT("'" & $A51 & " " & F$44 & "'!T37"),)} -> 0 | G51: {=IFERROR(INDIRECT("'" & $A51 & " " & G$44 & "'!T37"),)} -> 0 | H51: {=IFERROR(INDIRECT("'" & $A51 & " " & H$44 & "'!T37"),)} -> 0 | I51: {=IFERROR(INDIRECT("'" & $A51 & " " & I$44 & "'!T37"),)} -> 0 | J51: {=IFERROR(INDIRECT("'" & $A51 & " " & J$44 & "'!T37"),)} -> 0 | K51: {=IFERROR(INDIRECT("'" & $A51 & " " & K$44 & "'!G12"),)} -> 0 | L51: {=IFERROR(INDIRECT("'" & $A51 & " " & L$44 & "'!F14"),)} -> 0 | M51: =SUM(B51:L51) -> 9749437.5
A52: Зеленодольск | B52: {=IFERROR(INDIRECT("'" & $A52 & " " & B$44 & "'!T37"),)} -> 0 | C52: {=IFERROR(INDIRECT("'" & $A52 & " " & C$44 & "'!T37"),)} -> 92735.82 | D52: {=IFERROR(INDIRECT("'" & $A52 & " " & D$44 & "'!T37"),)} -> 7340148.4 | E52: {=IFERROR(INDIRECT("'" & $A52 & " " & E$44 & "'!T37"),)} -> 0 | F52: {=IFERROR(INDIRECT("'" & $A52 & " " & F$44 & "'!T37"),)} -> 0 | G52: {=IFERROR(INDIRECT("'" & $A52 & " " & G$44 & "'!T37"),)} -> 677739.87 | H52: {=IFERROR(INDIRECT("'" & $A52 & " " & H$44 & "'!T37"),)} -> 0 | I52: {=IFERROR(INDIRECT("'" & $A52 & " " & I$44 & "'!T37"),)} -> 0 | J52: {=IFERROR(INDIRECT("'" & $A52 & " " & J$44 & "'!T37"),)} -> 0 | K52: {=IFERROR(INDIRECT("'" & $A52 & " " & K$44 & "'!G12"),)} -> 4880 | L52: {=IFERROR(INDIRECT("'" & $A52 & " " & L$44 & "'!F14"),)} -> 0 | M52: =SUM(B52:L52) -> 8115504.1
A53: Нижнекамск | B53: {=IFERROR(INDIRECT("'" & $A53 & " " & B$44 & "'!T37"),)} -> 0 | C53: {=IFERROR(INDIRECT("'" & $A53 & " " & C$44 & "'!T37"),)} -> 0 | D53: {=IFERROR(INDIRECT("'" & $A53 & " " & D$44 & "'!T37"),)} -> 0 | E53: {=IFERROR(INDIRECT("'" & $A53 & " " & E$44 & "'!T37"),)} -> 0 | F53: {=IFERROR(INDIRECT("'" & $A53 & " " & F$44 & "'!T37"),)} -> 0 | G53: {=IFERROR(INDIRECT("'" & $A53 & " " & G$44 & "'!T37"),)} -> 0 | H53: {=IFERROR(INDIRECT("'" & $A53 & " " & H$44 & "'!T37"),)} -> 0 | I53: {=IFERROR(INDIRECT("'" & $A53 & " " & I$44 & "'!T37"),)} -> 0 | J53: {=IFERROR(INDIRECT("'" & $A53 & " " & J$44 & "'!T37"),)} -> 0 | K53: {=IFERROR(INDIRECT("'" & $A53 & " " & K$44 & "'!G12"),)} -> 0 | L53: {=IFERROR(INDIRECT("'" & $A53 & " " & L$44 & "'!F14"),)} -> 0 | M53: =SUM(B53:L53) -> 0
A54: ЕкатеринбургЧкаловский | B54: {=IFERROR(INDIRECT("'" & $A54 & " " & B$44 & "'!T37"),)} -> 137485.33 | C54: {=IFERROR(INDIRECT("'" & $A54 & " " & C$44 & "'!T37"),)} -> 1581168.4 | D54: {=IFERROR(INDIRECT("'" & $A54 & " " & D$44 & "'!T37"),)} -> 9653720.3 | E54: {=IFERROR(INDIRECT("'" & $A54 & " " & E$44 & "'!T37"),)} -> 0 | F54: {=IFERROR(INDIRECT("'" & $A54 & " " & F$44 & "'!T37"),)} -> 0 | G54: {=IFERROR(INDIRECT("'" & $A54 & " " & G$44 & "'!T37"),)} -> 0 | H54: {=IFERROR(INDIRECT("'" & $A54 & " " & H$44 & "'!T37"),)} -> 0 | I54: {=IFERROR(INDIRECT("'" & $A54 & " " & I$44 & "'!T37"),)} -> 0 | J54: {=IFERROR(INDIRECT("'" & $A54 & " " & J$44 & "'!T37"),)} -> 0 | K54: {=IFERROR(INDIRECT("'" & $A54 & " " & K$44 & "'!G12"),)} -> 0 | L54: {=IFERROR(INDIRECT("'" & $A54 & " " & L$44 & "'!F14"),)} -> 0 | M54: =SUM(B54:L54) -> 11372374
A56: Русвинил | B56: =SUM(B57:B67) -> 0
A57: Баумана | B57: {=IFERROR(INDIRECT("'РВ " & A57 & "'!O38"),0)} -> 0
A58: Новикова-Прибоя | B58: {=IFERROR(INDIRECT("'РВ " & A58 & "'!O38"),0)} -> 0
A59: ЕкатеринбургЧкаловский | B59: {=IFERROR(INDIRECT("'РВ " & A59 & "'!O38"),0)} -> 0
A60: Екатеринбург | B60: {=IFERROR(INDIRECT("'РВ " & A60 & "'!O38"),0)} -> 0
A61: Новосибирск | B61: {=IFERROR(INDIRECT("'РВ " & A61 & "'!O38"),0)} -> 0
A62: Казань_Приволжская | B62: {=IFERROR(INDIRECT("'РВ " & A62 & "'!O38"),0)} -> 0
A63: Казань_Автосервисная | B63: {=IFERROR(INDIRECT("'РВ " & A63 & "'!O38"),0)} -> 0
A64: Зеленодольск | B64: {=IFERROR(INDIRECT("'РВ " & A64 & "'!O38"),0)} -> 0
A65: Нижнекамск | B65: {=IFERROR(INDIRECT("'РВ " & A65 & "'!O38"),0)} -> 0
A66: Нижнекамск завод | B66: {=IFERROR(INDIRECT("'РВ " & A66 & "'!O38"),0)} -> 0
A67: Березовая Пойма | B67: {=IFERROR(INDIRECT("'РВ " & A67 & "'!O38"),0)+IFERROR(INDIRECT("Резерв!i38"),0)} -> 0
A68: Новосибирск_Пасечная | B68: {=IFERROR(INDIRECT("'РВ " & A68 & "'!O38"),0)} -> 0

Sheet Другое

Sheet Нижнекамск завод
A9: № | B9: Наименование услуг (работ) | C9: Ед. изм. | D9: Количество | E9: Цена | F9: Сумма
A14: Итого: | F14: =SUM(F10:F13) -> 0
A15: Без налога (НДС) | F15: =SUM(F14) -> 0
A16: Всего (с учетом НДС) | F16: =SUM(F15)*1.2 -> 0
A17: Вышеперечисленные услуги (работы) выполнены полностью. | E17: ПРР | F17: =13740173+2087126 -> 15827299
A18: ПОКЛАЖЕДАТЕЛЬ претензий по объему, качеству и срокам оказания услуг претензий не имеет. | E18: Стропальщики | F18: 786900
E19: Контейнеры | F19: 1879800
E20: МТО | F20: 20584666
E21: МТО 2520 | F21: 5345055
A22: ООО "ДТМ" | D22: ПАО "Нижнекамскнефтехим"
A24: ____________________Молькова Т.Ю. | B24: Расстегаев Д.О. | D24: ____________________

Sheet Сводка
A1: KPI | B1: Баумана | C1: =INDEX(INDIRECT("ИТОГО!$B$45:$L$54"),MATCH(Сводка!B1,INDIRECT("ИТОГО!$A$45:$A$54"),0),MATCH(Сводка!A1,INDIRECT("ИТОГО!$B$44:$L$44"),0)) -> 1518.02
A2: Полиом | B2: Баумана | C2: =INDEX(INDIRECT("ИТОГО!$B$45:$L$54"),MATCH(Сводка!B2,INDIRECT("ИТОГО!$A$45:$A$54"),0),MATCH(Сводка!A2,INDIRECT("ИТОГО!$B$44:$L$44"),0)) -> 290063.38
A3: Полимеры | B3: Баумана | C3: =INDEX(INDIRECT("ИТОГО!$B$45:$L$54"),MATCH(Сводка!B3,INDIRECT("ИТОГО!$A$45:$A$54"),0),MATCH(Сводка!A3,INDIRECT("ИТОГО!$B$44:$L$44"),0)) -> 7669280
A4: Каучук | B4: Баумана | C4: =INDEX(INDIRECT("ИТОГО!$B$45:$L$54"),MATCH(Сводка!B4,INDIRECT("ИТОГО!$A$45:$A$54"),0),MATCH(Сводка!A4,INDIRECT("ИТОГО!$B$44:$L$44"),0)) -> 0
A5: ПСОН | B5: Баумана | C5: =INDEX(INDIRECT("ИТОГО!$B$45:$L$54"),MATCH(Сводка!B5,INDIRECT("ИТОГО!$A$45:$A$54"),0),MATCH(Сводка!A5,INDIRECT("ИТОГО!$B$44:$L$44"),0)) -> 0
A6: Данафлекс | B6: Баумана | C6: =INDEX(INDIRECT("ИТОГО!$B$45:$L$54"),MATCH(Сводка!B6,INDIRECT("ИТОГО!$A$45:$A$54"),0),MATCH(Сводка!A6,INDIRECT("ИТОГО!$B$44:$L$44"),0)) -> 0
A7: СБС | B7: Баумана | C7: =INDEX(INDIRECT("ИТОГО!$B$45:$L$54"),MATCH(Сводка!B7,INDIRECT("ИТОГО!$A$45:$A$54"),0),MATCH(Сводка!A7,INDIRECT("ИТОГО!$B$44:$L$44"),0)) -> 0
A8: Порошок | B8: Баумана | C8: =INDEX(INDIRECT("ИТОГО!$B$45:$L$54"),MATCH(Сводка!B8,INDIRECT("ИТОГО!$A$45:$A$54"),0),MATCH(Сводка!A8,INDIRECT("ИТОГО!$B$44:$L$44"),0)) -> 0
A9: НПЭГ | B9: Баумана | C9: =INDEX(INDIRECT("ИТОГО!$B$45:$L$54"),MATCH(Сводка!B9,INDIRECT("ИТОГО!$A$45:$A$54"),0),MATCH(Сводка!A9,INDIRECT("ИТОГО!$B$44:$L$44"),0)) -> 0
A10: Экспорт | B10: Баумана | C10: =INDEX(INDIRECT("ИТОГО!$B$45:$L$54"),MATCH(Сводка!B10,INDIRECT("ИТОГО!$A$45:$A$54"),0),MATCH(Сводка!A10,INDIRECT("ИТОГО!$B$44:$L$44"),0)) -> 0
A11: Доп услуги | B11: Баумана | C11: =INDEX(INDIRECT("ИТОГО!$B$45:$L$54"),MATCH(Сводка!B11,INDIRECT("ИТОГО!$A$45:$A$54"),0),MATCH(Сводка!A11,INDIRECT("ИТОГО!$B$44:$L$44"),0)) -> 0
A12: KPI | B12: Новикова-Прибоя | C12: =INDEX(INDIRECT("ИТОГО!$B$45:$L$54"),MATCH(Сводка!B12,INDIRECT("ИТОГО!$A$45:$A$54"),0),MATCH(Сводка!A12,INDIRECT("ИТОГО!$B$44:$L$44"),0)) -> 18899.09
... A99: Доп услуги | B99: Казань_Приволжская | C99: =INDEX(INDIRECT("ИТОГО!$B$45:$L$54"),MATCH(Сводка!B99,INDIRECT("ИТОГО!$A$45:$A$54"),0),MATCH(Сводка!A99,INDIRECT("ИТОГО!$B$44:$L$44"),0)) -> 0
A100: Русвинил | B100: Баумана | C100: {=INDIRECT("ИТОГО!B57")} -> 0
A101: Русвинил | B101: Новикова-Прибоя | C101: {=INDIRECT("ИТОГО!B58")} -> 0
A102: Русвинил | B102: Березовая Пойма | C102: {=INDIRECT("ИТОГО!B67")} -> 0
A103: ПРР | B103: Нижнекамск завод | C103: {=INDIRECT("ИТОГО!C30")} -> 15827299
A104: Кладовки | B104: Нижнекамск завод | C104: {=INDIRECT("ИТОГО!C31")} -> 0
A105: Стропальщики | B105: Нижнекамск завод | C105: {=INDIRECT("ИТОГО!C32")} -> 786900
A106: Мойка контейнеров | B106: Нижнекамск завод | C106: {=INDIRECT("ИТОГО!C33")} -> 1879800
A107: МТО | B107: Нижнекамск завод | C107: {=INDIRECT("ИТОГО!C34")} -> 20584666
A108: МТО 2520 | B108: Нижнекамск завод | C108: {=INDIRECT("ИТОГО!C35")} -> 5345055
A109: КП КОС | B109: Нижнекамск завод | C109: {=INDIRECT("ИТОГО!C38")} -> 1797615
A110: КП Нижнекамск | B110: Нижнекамск завод | C110: {=INDIRECT("ИТОГО!C39")} -> 7064220
A111: Стройтех | B111: Баумана | C111: {=INDIRECT("ИТОГО!C19")} -> 55733
A112: Ергарда | B112: Баумана | C112: {=INDIRECT("ИТОГО!C20")} -> 7812
A113: Литейные решения | B113: Баумана | C113: {=INDIRECT("ИТОГО!C21")} -> 102164
A114: Сандекс | B114: Баумана | C114: {=INDIRECT("ИТОГО!C22")} -> 17102.4
A115: ЛС-Техномет | B115: Баумана | C115: {=INDIRECT("ИТОГО!C23")} -> 1605.6
A116: Приоритет | B116: Баумана | C116: {=INDIRECT("ИТОГО!G19")} -> 122207.4
A117: Фармпласт | B117: Баумана | C117: {=INDIRECT("ИТОГО!G20")} -> 416008.41
A118: Юг Полимер | B118: Баумана | C118: {=INDIRECT("ИТОГО!G21")} -> 337898.52
A119: Центрополимер | B119: Екатеринбург | C119: {=INDIRECT("ИТОГО!G22")} -> 0
A120: Приоритет | B120: Екатеринбург | C120: {=INDIRECT("ИТОГО!G23")} -> 0
A121: Фармпласт | B121: Екатеринбург | C121: {=INDIRECT("ИТОГО!G24")} -> 0
A122: Приоритет | B122: Зеленодольск | C122: {=INDIRECT("ИТОГО!G25")} -> 0
A123: Данафлекс | B123: Зеленодольск | C123: {=INDIRECT("ИТОГО!G26")} -> 0
A124: ИП Ксендз | B124: Нижнекамск | C124: {=INDIRECT("ИТОГО!G27")} -> 0
A125: Фармпласт | B125: Новикова-Прибоя | C125: {=INDIRECT("ИТОГО!G28")} -> 102937.5
A126: Центрополимер | B126: Новикова-Прибоя | C126: {=INDIRECT("ИТОГО!G29")} -> 0
A127: Юг Полимер | B127: Новикова-Прибоя | C127: {=INDIRECT("ИТОГО!G30")} -> 0
A128: Приоритет | B128: Новикова-Прибоя | C128: {=INDIRECT("ИТОГО!G31")} -> 76585.5
A129: Биаксплен | B129: Новосибирск | C129: {=INDIRECT("ИТОГО!G32")} -> 194710.51
A130: Центрополимер | B130: Новосибирск | C130: {=INDIRECT("ИТОГО!G33")} -> 0
A131: Фармпласт | B131: Новосибирск | C131: {=INDIRECT("ИТОГО!G34")} -> 0
A132: Юг Полимер | B132: Зеленодольск | C132: {=INDIRECT("ИТОГО!G36")} -> 0
A133: Фармпласт | B133: Казань_Автосервисная | C133: {=INDIRECT("ИТОГО!G37")} -> 0
A134: Приоритет | B134: Казань_Приволжская | C134: {=INDIRECT("ИТОГО!G38")} -> 0
A135: Центрополимер | B135: Баумана | C135: {=INDIRECT("ИТОГО!G39")} -> 262202.4
A136: Приоритет | B136: Казань_Автосервисная | C136: {=INDIRECT("ИТОГО!G40")} -> 0
A137: Оникс | B137: Нижнекамск | C137: {=INDIRECT("ИТОГО!G41")} -> 0
A138: Центрополимер | B138: Зеленодольск | C138: =[1]ИТОГО!G35 -> 0
A139: KPI | B139: ЕкатеринбургЧкаловский | C139: =INDEX(INDIRECT("ИТОГО!$B$45:$L$54"),MATCH(Сводка!B139,INDIRECT("ИТОГО!$A$45:$A$54"),0),MATCH(Сводка!A139,INDIRECT("ИТОГО!$B$44:$L$44"),0)) -> 137485.33
A140: Полиом | B140: ЕкатеринбургЧкаловский | C140: =INDEX(INDIRECT("ИТОГО!$B$45:$L$54"),MATCH(Сводка!B140,INDIRECT("ИТОГО!$A$45:$A$54"),0),MATCH(Сводка!A140,INDIRECT("ИТОГО!$B$44:$L$44"),0)) -> 1581168.4
A141: Полимеры | B141: ЕкатеринбургЧкаловский | C141: =INDEX(INDIRECT("ИТОГО!$B$45:$L$54"),MATCH(Сводка!B141,INDIRECT("ИТОГО!$A$45:$A$54"),0),MATCH(Сводка!A141,INDIRECT("ИТОГО!$B$44:$L$44"),0)) -> 9653720.3
A142: Каучук | B142: ЕкатеринбургЧкаловский | C142: =INDEX(INDIRECT("ИТОГО!$B$45:$L$54"),MATCH(Сводка!B142,INDIRECT("ИТОГО!$A$45:$A$54"),0),MATCH(Сводка!A142,INDIRECT("ИТОГО!$B$44:$L$44"),0)) -> 0
A143: ПСОН | B143: ЕкатеринбургЧкаловский | C143: =INDEX(INDIRECT("ИТОГО!$B$45:$L$54"),MATCH(Сводка!B143,INDIRECT("ИТОГО!$A$45:$A$54"),0),MATCH(Сводка!A143,INDIRECT("ИТОГО!$B$44:$L$44"),0)) -> 0
A144: Данафлекс | B144: ЕкатеринбургЧкаловский | C144: =INDEX(INDIRECT("ИТОГО!$B$45:$L$54"),MATCH(Сводка!B144,INDIRECT("ИТОГО!$A$45:$A$54"),0),MATCH(Сводка!A144,INDIRECT("ИТОГО!$B$44:$L$44"),0)) -> 0
A145: СБС | B145: ЕкатеринбургЧкаловский | C145: =INDEX(INDIRECT("ИТОГО!$B$45:$L$54"),MATCH(Сводка!B145,INDIRECT("ИТОГО!$A$45:$A$54"),0),MATCH(Сводка!A145,INDIRECT("ИТОГО!$B$44:$L$44"),0)) -> 0
A146: Порошок | B146: ЕкатеринбургЧкаловский | C146: =INDEX(INDIRECT("ИТОГО!$B$45:$L$54"),MATCH(Сводка!B146,INDIRECT("ИТОГО!$A$45:$A$54"),0),MATCH(Сводка!A146,INDIRECT("ИТОГО!$B$44:$L$44"),0)) -> 0
A147: НПЭГ | B147: ЕкатеринбургЧкаловский | C147: =INDEX(INDIRECT("ИТОГО!$B$45:$L$54"),MATCH(Сводка!B147,INDIRECT("ИТОГО!$A$45:$A$54"),0),MATCH(Сводка!A147,INDIRECT("ИТОГО!$B$44:$L$44"),0)) -> 0
A148: Экспорт | B148: ЕкатеринбургЧкаловский | C148: =INDEX(INDIRECT("ИТОГО!$B$45:$L$54"),MATCH(Сводка!B148,INDIRECT("ИТОГО!$A$45:$A$54"),0),MATCH(Сводка!A148,INDIRECT("ИТОГО!$B$44:$L$44"),0)) -> 0
A149: Доп услуги | B149: ЕкатеринбургЧкаловский | C149: =INDEX(INDIRECT("ИТОГО!$B$45:$L$54"),MATCH(Сводка!B149,INDIRECT("ИТОГО!$A$45:$A$54"),0),MATCH(Сводка!A149,INDIRECT("ИТОГО!$B$44:$L$44"),0)) -> 0

Sheet Центрополимер Зеленодольск
A1: =N37 -> 86302.8
A2: ="Отчет по хранению товара за " & TEXT(B5,"ММММ ГГГГ") -> Отчет по хранению товара за Июль 2026
A3: № | B3: дата | D3: Выгрузка кол-во | E3: Загрузка кол-во | F3: Хранение | G3: переконсолидация (тонн) | H3: Паллетирование | I3: стоимость выгрузки | J3: стоимость загрузки | K3: стоимость хранения | L3: стоимость переконс. | M3: Стоимость паллетирования | N3: итого | Q3: Цены
Q4: Выгрузка | R4: 180
A5: 1 | B5: 46204 | F5: =112.5 -> 112.5 | G5: 0 | H5: 0 | I5: =SUM(D5*$R$4) -> 0 | J5: =SUM(E5*$R$5) -> 0 | K5: =F5*$R$6 -> 2700 | L5: =SUM(G5*$R$7) -> 0 | M5: =SUM(H5*$R$8) -> 0 | N5: =SUM(I5:M5) -> 2700 | Q5: Загрузка | R5: 180
A6: 2 | B6: 46205 | F6: =F5-E5+D6 -> 112.5 | G6: 0 | H6: 0 | I6: =SUM(D6*$R$4) -> 0 | J6: =SUM(E6*$R$5) -> 0 | K6: =F6*$R$6 -> 2700 | L6: =SUM(G6*$R$7) -> 0 | M6: =SUM(H6*$R$8) -> 0 | N6: =SUM(I6:M6) -> 2700 | Q6: Хранение | R6: 24
A7: 3 | B7: 46206 | F7: =F6-E6+D7 -> 112.5 | G7: 0 | H7: 0 | I7: =SUM(D7*$R$4) -> 0 | J7: =SUM(E7*$R$5) -> 0 | K7: =F7*$R$6 -> 2700 | L7: =SUM(G7*$R$7) -> 0 | M7: =SUM(H7*$R$8) -> 0 | N7: =SUM(I7:M7) -> 2700 | Q7: Переконсолидация | R7: 1200
A8: 4 | B8: 46207 | F8: =F7-E7+D8 -> 112.5 | G8: 0 | H8: 0 | I8: =SUM(D8*$R$4) -> 0 | J8: =SUM(E8*$R$5) -> 0 | K8: =F8*$R$6 -> 2700 | L8: =SUM(G8*$R$7) -> 0 | M8: =SUM(H8*$R$8) -> 0 | N8: =SUM(I8:M8) -> 2700 | Q8: Паллетирование | R8: 240
A9: 5 | B9: 46208 | F9: =F8-E8+D9 -> 112.5 | G9: 0 | H9: 0 | I9: =SUM(D9*$R$4) -> 0 | J9: =SUM(E9*$R$5) -> 0 | K9: =F9*$R$6 -> 2700 | L9: =SUM(G9*$R$7) -> 0 | M9: =SUM(H9*$R$8) -> 0 | N9: =SUM(I9:M9) -> 2700
A10: 6 | B10: 46209 | F10: =F9-E9+D10 -> 112.5 | G10: 0 | H10: 0 | I10: =SUM(D10*$R$4) -> 0 | J10: =SUM(E10*$R$5) -> 0 | K10: =F10*$R$6 -> 2700 | L10: =SUM(G10*$R$7) -> 0 | M10: =SUM(H10*$R$8) -> 0 | N10: =SUM(I10:M10) -> 2700
A11: 7 | B11: 46210 | F11: =F10-E10+D11 -> 112.5 | G11: 0 | H11: 0 | I11: =SUM(D11*$R$4) -> 0 | J11: =SUM(E11*$R$5) -> 0 | K11: =F11*$R$6 -> 2700 | L11: =SUM(G11*$R$7) -> 0 | M11: =SUM(H11*$R$8) -> 0 | N11: =SUM(I11:M11) -> 2700
A12: 8 | B12: 46211 | F12: =F11-E11+D12 -> 112.5 | G12: 0 | H12: 0 | I12: =SUM(D12*$R$4) -> 0 | J12: =SUM(E12*$R$5) -> 0 | K12: =F12*$R$6 -> 2700 | L12: =SUM(G12*$R$7) -> 0 | M12: =SUM(H12*$R$8) -> 0 | N12: =SUM(I12:M12) -> 2700
A13: 9 | B13: 46212 | E13: 22.5 | F13: =F12-E12+D13 -> 112.5 | G13: 0 | H13: 0 | I13: =SUM(D13*$R$4) -> 0 | J13: =SUM(E13*$R$5) -> 4050 | K13: =F13*$R$6 -> 2700 | L13: =SUM(G13*$R$7) -> 0 | M13: =SUM(H13*$R$8) -> 0 | N13: =SUM(I13:M13) -> 6750
A14: 10 | B14: 46213 | F14: =F13-E13+D14 -> 90 | G14: 0 | H14: 0 | I14: =SUM(D14*$R$4) -> 0 | J14: =SUM(E14*$R$5) -> 0 | K14: =F14*$R$6 -> 2160 | L14: =SUM(G14*$R$7) -> 0 | M14: =SUM(H14*$R$8) -> 0 | N14: =SUM(I14:M14) -> 2160
A15: 11 | B15: 46214 | F15: =F14-E14+D15 -> 90 | G15: 0 | H15: 0 | I15: =SUM(D15*$R$4) -> 0 | J15: =SUM(E15*$R$5) -> 0 | K15: =F15*$R$6 -> 2160 | L15: =SUM(G15*$R$7) -> 0 | M15: =SUM(H15*$R$8) -> 0 | N15: =SUM(I15:M15) -> 2160
A16: 12 | B16: 46215 | F16: =F15-E15+D16 -> 90 | G16: 0 | H16: 0 | I16: =SUM(D16*$R$4) -> 0 | J16: =SUM(E16*$R$5) -> 0 | K16: =F16*$R$6 -> 2160 | L16: =SUM(G16*$R$7) -> 0 | M16: =SUM(H16*$R$8) -> 0 | N16: =SUM(I16:M16) -> 2160
A17: 13 | B17: 46216 | F17: =F16-E16+D17 -> 90 | G17: 0 | H17: 0 | I17: =SUM(D17*$R$4) -> 0 | J17: =SUM(E17*$R$5) -> 0 | K17: =F17*$R$6 -> 2160 | L17: =SUM(G17*$R$7) -> 0 | M17: =SUM(H17*$R$8) -> 0 | N17: =SUM(I17:M17) -> 2160
A18: 14 | B18: 46217 | E18: 22.5 | F18: =F17-E17+D18 -> 90 | G18: 0 | H18: 0 | I18: =SUM(D18*$R$4) -> 0 | J18: =SUM(E18*$R$5) -> 4050 | K18: =F18*$R$6 -> 2160 | L18: =SUM(G18*$R$7) -> 0 | M18: =SUM(H18*$R$8) -> 0 | N18: =SUM(I18:M18) -> 6210
A19: 15 | B19: 46218 | F19: =F18-E18+D19 -> 67.5 | G19: 0 | H19: 0 | I19: =SUM(D19*$R$4) -> 0 | J19: =SUM(E19*$R$5) -> 0 | K19: =F19*$R$6 -> 1620 | L19: =SUM(G19*$R$7) -> 0 | M19: =SUM(H19*$R$8) -> 0 | N19: =SUM(I19:M19) -> 1620
A20: 16 | B20: 46219 | F20: =F19-E19+D20 -> 67.5 | G20: 0 | H20: 0 | I20: =SUM(D20*$R$4) -> 0 | J20: =SUM(E20*$R$5) -> 0 | K20: =F20*$R$6 -> 1620 | L20: =SUM(G20*$R$7) -> 0 | M20: =SUM(H20*$R$8) -> 0 | N20: =SUM(I20:M20) -> 1620
A21: 17 | B21: 46220 | F21: =F20-E20+D21 -> 67.5 | G21: 0 | H21: 0 | I21: =SUM(D21*$R$4) -> 0 | J21: =SUM(E21*$R$5) -> 0 | K21: =F21*$R$6 -> 1620 | L21: =SUM(G21*$R$7) -> 0 | M21: =SUM(H21*$R$8) -> 0 | N21: =SUM(I21:M21) -> 1620
A22: 18 | B22: 46221 | F22: =F21-E21+D22 -> 67.5 | G22: 0 | H22: 0 | I22: =SUM(D22*$R$4) -> 0 | J22: =SUM(E22*$R$5) -> 0 | K22: =F22*$R$6 -> 1620 | L22: =SUM(G22*$R$7) -> 0 | M22: =SUM(H22*$R$8) -> 0 | N22: =SUM(I22:M22) -> 1620
A23: 19 | B23: 46222 | F23: =F22-E22+D23 -> 67.5 | G23: 0 | H23: 0 | I23: =SUM(D23*$R$4) -> 0 | J23: =SUM(E23*$R$5) -> 0 | K23: =F23*$R$6 -> 1620 | L23: =SUM(G23*$R$7) -> 0 | M23: =SUM(H23*$R$8) -> 0 | N23: =SUM(I23:M23) -> 1620
A24: 20 | B24: 46223 | F24: =F23-E23+D24 -> 67.5 | G24: 0 | H24: 0 | I24: =SUM(D24*$R$4) -> 0 | J24: =SUM(E24*$R$5) -> 0 | K24: =F24*$R$6 -> 1620 | L24: =SUM(G24*$R$7) -> 0 | M24: =SUM(H24*$R$8) -> 0 | N24: =SUM(I24:M24) -> 1620
A25: 21 | B25: 46224 | F25: =F24-E24+D25 -> 67.5 | G25: 0 | H25: 0 | I25: =SUM(D25*$R$4) -> 0 | J25: =SUM(E25*$R$5) -> 0 | K25: =F25*$R$6 -> 1620 | L25: =SUM(G25*$R$7) -> 0 | M25: =SUM(H25*$R$8) -> 0 | N25: =SUM(I25:M25) -> 1620
A26: 22 | B26: 46225 | F26: =F25-E25+D26 -> 67.5 | G26: 0 | H26: 0 | I26: =SUM(D26*$R$4) -> 0 | J26: =SUM(E26*$R$5) -> 0 | K26: =F26*$R$6 -> 1620 | L26: =SUM(G26*$R$7) -> 0 | M26: =SUM(H26*$R$8) -> 0 | N26: =SUM(I26:M26) -> 1620
A27: 23 | B27: 46226 | F27: =F26-E26+D27 -> 67.5 | G27: 0 | H27: 0 | I27: =SUM(D27*$R$4) -> 0 | J27: =SUM(E27*$R$5) -> 0 | K27: =F27*$R$6 -> 1620 | L27: =SUM(G27*$R$7) -> 0 | M27: =SUM(H27*$R$8) -> 0 | N27: =SUM(I27:M27) -> 1620
A28: 24 | B28: 46227 | F28: =F27-E27+D28 -> 67.5 | G28: 0 | H28: 0 | I28: =SUM(D28*$R$4) -> 0 | J28: =SUM(E28*$R$5) -> 0 | K28: =F28*$R$6 -> 1620 | L28: =SUM(G28*$R$7) -> 0 | M28: =SUM(H28*$R$8) -> 0 | N28: =SUM(I28:M28) -> 1620
A29: 25 | B29: 46228 | F29: =F28-E28+D29 -> 67.5 | G29: 0 | H29: 0 | I29: =SUM(D29*$R$4) -> 0 | J29: =SUM(E29*$R$5) -> 0 | K29: =F29*$R$6 -> 1620 | L29: =SUM(G29*$R$7) -> 0 | M29: =SUM(H29*$R$8) -> 0 | N29: =SUM(I29:M29) -> 1620
A30: 26 | B30: 46229 | F30: =F29-E29+D30 -> 67.5 | G30: 0 | H30: 0 | I30: =SUM(D30*$R$4) -> 0 | J30: =SUM(E30*$R$5) -> 0 | K30: =F30*$R$6 -> 1620 | L30: =SUM(G30*$R$7) -> 0 | M30: =SUM(H30*$R$8) -> 0 | N30: =SUM(I30:M30) -> 1620
... A34: 30 | B34: 46233 | F34: =F33-E33+D34 -> 67.5 | G34: 0 | H34: 0 | I34: =SUM(D34*$R$4) -> 0 | J34: =SUM(E34*$R$5) -> 0 | K34: =F34*$R$6 -> 1620 | L34: =SUM(G34*$R$7) -> 0 | M34: =SUM(H34*$R$8) -> 0 | N34: =SUM(I34:M34) -> 1620
B35: 46234 | F35: =F34-E34+D35 -> 67.5 | I35: =SUM(D35*$R$4) -> 0 | J35: =SUM(E35*$R$5) -> 0 | K35: =F35*$R$6 -> 1620 | L35: =SUM(G35*$R$7) -> 0 | M35: =SUM(H35*$R$8) -> 0 | N35: =SUM(I35:M35) -> 1620
D36: =SUM(D5:D35) -> 0 | E36: =SUM(E5:E35) -> 45 | F36: =SUM(F5:F35) -> 2610 | G36: =SUM(G5:G35) -> 0 | H36: =SUM(H5:H35) -> 0 | I36: =SUM(I5:I35) -> 0 | J36: =SUM(J5:J35) -> 8100 | K36: =SUM(K5:K35) -> 62640 | ... N36: =SUM(N5:N35) -> 70740
N37: =N36*1.22 -> 86302.8

Sheet Центрополимер Баумана
A1: =N37 -> 262202.4
A2: ="Отчет по хранению товара за " & TEXT(B5,"ММММ ГГГГ") -> Отчет по хранению товара за Июль 2026
A3: № | B3: дата | D3: Выгрузка кол-во | E3: Загрузка кол-во | F3: Хранение | G3: переконсолидация (тонн) | H3: Паллетирование | I3: стоимость выгрузки | J3: стоимость загрузки | K3: стоимость хранения | L3: стоимость переконс. | M3: Стоимость паллетирования | N3: итого | Q3: Цены
Q4: Выгрузка | R4: 180
A5: 1 | B5: 46204 | F5: 337.5 | G5: 0 | H5: 0 | I5: =SUM(D5*$R$4) -> 0 | J5: =SUM(E5*$R$5) -> 0 | K5: =F5*$R$6 -> 8100 | L5: =SUM(G5*$R$7) -> 0 | M5: =SUM(H5*$R$8) -> 0 | N5: =SUM(I5:M5) -> 8100 | Q5: Загрузка | R5: 180
A6: 2 | B6: 46205 | F6: =F5-E5+D6 -> 337.5 | G6: 0 | H6: 0 | I6: =SUM(D6*$R$4) -> 0 | J6: =SUM(E6*$R$5) -> 0 | K6: =F6*$R$6 -> 8100 | L6: =SUM(G6*$R$7) -> 0 | M6: =SUM(H6*$R$8) -> 0 | N6: =SUM(I6:M6) -> 8100 | Q6: Хранение | R6: 24
A7: 3 | B7: 46206 | F7: =F6-E6+D7 -> 337.5 | G7: 0 | H7: 0 | I7: =SUM(D7*$R$4) -> 0 | J7: =SUM(E7*$R$5) -> 0 | K7: =F7*$R$6 -> 8100 | L7: =SUM(G7*$R$7) -> 0 | M7: =SUM(H7*$R$8) -> 0 | N7: =SUM(I7:M7) -> 8100 | Q7: Переконсолидация | R7: 1200
A8: 4 | B8: 46207 | F8: =F7-E7+D8 -> 337.5 | G8: 0 | H8: 0 | I8: =SUM(D8*$R$4) -> 0 | J8: =SUM(E8*$R$5) -> 0 | K8: =F8*$R$6 -> 8100 | L8: =SUM(G8*$R$7) -> 0 | M8: =SUM(H8*$R$8) -> 0 | N8: =SUM(I8:M8) -> 8100 | Q8: Паллетирование | R8: 240
A9: 5 | B9: 46208 | F9: =F8-E8+D9 -> 337.5 | G9: 0 | H9: 0 | I9: =SUM(D9*$R$4) -> 0 | J9: =SUM(E9*$R$5) -> 0 | K9: =F9*$R$6 -> 8100 | L9: =SUM(G9*$R$7) -> 0 | M9: =SUM(H9*$R$8) -> 0 | N9: =SUM(I9:M9) -> 8100
A10: 6 | B10: 46209 | E10: 22.5 | F10: =F9-E9+D10 -> 337.5 | G10: 0 | H10: 0 | I10: =SUM(D10*$R$4) -> 0 | J10: =SUM(E10*$R$5) -> 4050 | K10: =F10*$R$6 -> 8100 | L10: =SUM(G10*$R$7) -> 0 | M10: =SUM(H10*$R$8) -> 0 | N10: =SUM(I10:M10) -> 12150
A11: 7 | B11: 46210 | E11: 67.5 | F11: =F10-E10+D11 -> 315 | G11: 0 | H11: 0 | I11: =SUM(D11*$R$4) -> 0 | J11: =SUM(E11*$R$5) -> 12150 | K11: =F11*$R$6 -> 7560 | L11: =SUM(G11*$R$7) -> 0 | M11: =SUM(H11*$R$8) -> 0 | N11: =SUM(I11:M11) -> 19710
A12: 8 | B12: 46211 | F12: =F11-E11+D12 -> 247.5 | G12: 0 | H12: 0 | I12: =SUM(D12*$R$4) -> 0 | J12: =SUM(E12*$R$5) -> 0 | K12: =F12*$R$6 -> 5940 | L12: =SUM(G12*$R$7) -> 0 | M12: =SUM(H12*$R$8) -> 0 | N12: =SUM(I12:M12) -> 5940
A13: 9 | B13: 46212 | F13: =F12-E12+D13 -> 247.5 | G13: 0 | H13: 0 | I13: =SUM(D13*$R$4) -> 0 | J13: =SUM(E13*$R$5) -> 0 | K13: =F13*$R$6 -> 5940 | L13: =SUM(G13*$R$7) -> 0 | M13: =SUM(H13*$R$8) -> 0 | N13: =SUM(I13:M13) -> 5940
A14: 10 | B14: 46213 | F14: =F13-E13+D14 -> 247.5 | G14: 0 | H14: 0 | I14: =SUM(D14*$R$4) -> 0 | J14: =SUM(E14*$R$5) -> 0 | K14: =F14*$R$6 -> 5940 | L14: =SUM(G14*$R$7) -> 0 | M14: =SUM(H14*$R$8) -> 0 | N14: =SUM(I14:M14) -> 5940
A15: 11 | B15: 46214 | F15: =F14-E14+D15 -> 247.5 | G15: 0 | H15: 0 | I15: =SUM(D15*$R$4) -> 0 | J15: =SUM(E15*$R$5) -> 0 | K15: =F15*$R$6 -> 5940 | L15: =SUM(G15*$R$7) -> 0 | M15: =SUM(H15*$R$8) -> 0 | N15: =SUM(I15:M15) -> 5940
A16: 12 | B16: 46215 | F16: =F15-E15+D16 -> 247.5 | G16: 0 | H16: 0 | I16: =SUM(D16*$R$4) -> 0 | J16: =SUM(E16*$R$5) -> 0 | K16: =F16*$R$6 -> 5940 | L16: =SUM(G16*$R$7) -> 0 | M16: =SUM(H16*$R$8) -> 0 | N16: =SUM(I16:M16) -> 5940
A17: 13 | B17: 46216 | F17: =F16-E16+D17 -> 247.5 | G17: 0 | H17: 0 | I17: =SUM(D17*$R$4) -> 0 | J17: =SUM(E17*$R$5) -> 0 | K17: =F17*$R$6 -> 5940 | L17: =SUM(G17*$R$7) -> 0 | M17: =SUM(H17*$R$8) -> 0 | N17: =SUM(I17:M17) -> 5940
A18: 14 | B18: 46217 | F18: =F17-E17+D18 -> 247.5 | G18: 0 | H18: 0 | I18: =SUM(D18*$R$4) -> 0 | J18: =SUM(E18*$R$5) -> 0 | K18: =F18*$R$6 -> 5940 | L18: =SUM(G18*$R$7) -> 0 | M18: =SUM(H18*$R$8) -> 0 | N18: =SUM(I18:M18) -> 5940
A19: 15 | B19: 46218 | F19: =F18-E18+D19 -> 247.5 | G19: 0 | H19: 0 | I19: =SUM(D19*$R$4) -> 0 | J19: =SUM(E19*$R$5) -> 0 | K19: =F19*$R$6 -> 5940 | L19: =SUM(G19*$R$7) -> 0 | M19: =SUM(H19*$R$8) -> 0 | N19: =SUM(I19:M19) -> 5940
A20: 16 | B20: 46219 | F20: =F19-E19+D20 -> 247.5 | G20: 0 | H20: 0 | I20: =SUM(D20*$R$4) -> 0 | J20: =SUM(E20*$R$5) -> 0 | K20: =F20*$R$6 -> 5940 | L20: =SUM(G20*$R$7) -> 0 | M20: =SUM(H20*$R$8) -> 0 | N20: =SUM(I20:M20) -> 5940
A21: 17 | B21: 46220 | F21: =F20-E20+D21 -> 247.5 | G21: 0 | H21: 0 | I21: =SUM(D21*$R$4) -> 0 | J21: =SUM(E21*$R$5) -> 0 | K21: =F21*$R$6 -> 5940 | L21: =SUM(G21*$R$7) -> 0 | M21: =SUM(H21*$R$8) -> 0 | N21: =SUM(I21:M21) -> 5940
A22: 18 | B22: 46221 | F22: =F21-E21+D22 -> 247.5 | G22: 0 | H22: 0 | I22: =SUM(D22*$R$4) -> 0 | J22: =SUM(E22*$R$5) -> 0 | K22: =F22*$R$6 -> 5940 | L22: =SUM(G22*$R$7) -> 0 | M22: =SUM(H22*$R$8) -> 0 | N22: =SUM(I22:M22) -> 5940
A23: 19 | B23: 46222 | F23: =F22-E22+D23 -> 247.5 | G23: 0 | H23: 0 | I23: =SUM(D23*$R$4) -> 0 | J23: =SUM(E23*$R$5) -> 0 | K23: =F23*$R$6 -> 5940 | L23: =SUM(G23*$R$7) -> 0 | M23: =SUM(H23*$R$8) -> 0 | N23: =SUM(I23:M23) -> 5940
... A34: 30 | B34: 46233 | F34: =F33-E33+D34 -> 247.5 | G34: 0 | H34: 0 | I34: =SUM(D34*$R$4) -> 0 | J34: =SUM(E34*$R$5) -> 0 | K34: =F34*$R$6 -> 5940 | L34: =SUM(G34*$R$7) -> 0 | M34: =SUM(H34*$R$8) -> 0 | N34: =SUM(I34:M34) -> 5940
B35: 46234 | F35: =F34-E34+D35 -> 247.5 | I35: =SUM(D35*$R$4) -> 0 | J35: =SUM(E35*$R$5) -> 0 | K35: =F35*$R$6 -> 5940 | L35: =SUM(G35*$R$7) -> 0 | M35: =SUM(H35*$R$8) -> 0 | N35: =SUM(I35:M35) -> 5940
D36: =SUM(D5:D35) -> 0 | E36: =SUM(E5:E35) -> 90 | F36: =SUM(F5:F35) -> 8280 | G36: =SUM(G5:G35) -> 0 | H36: =SUM(H5:H35) -> 0 | I36: =SUM(I5:I35) -> 0 | J36: =SUM(J5:J35) -> 16200 | K36: =SUM(K5:K35) -> 198720 | ... N36: =SUM(N5:N35) -> 214920
N37: =N36*1.22 -> 262202.4

Sheet Центрополимер Новикова-Прибоя
A1: =N37 -> 0
A2: ="Отчет по хранению товара за " & TEXT(B5,"ММММ ГГГГ") -> Отчет по хранению товара за Июль 2026
A3: № | B3: дата | D3: Выгрузка кол-во | E3: Загрузка кол-во | F3: Хранение | G3: переконсолидация (тонн) | H3: Паллетирование | I3: стоимость выгрузки | J3: стоимость загрузки | K3: стоимость хранения | L3: стоимость переконс. | M3: Стоимость паллетирования | N3: итого | Q3: Цены
Q4: Выгрузка | R4: 120
A5: 1 | B5: 46204 | F5: 0 | G5: 0 | H5: 0 | I5: =SUM(D5*R4) -> 0 | J5: =SUM(E5*$R$5) -> 0 | K5: =SUM(F5*$R$6) -> 0 | L5: =SUM(G5*$R$7) -> 0 | M5: =SUM(H5*$R$8) -> 0 | N5: =SUM(I5:M5) -> 0 | Q5: Загрузка | R5: 120
A6: 2 | B6: 46205 | F6: =F5-E5+D6 -> 0 | G6: 0 | H6: 0 | I6: =SUM(D6*R5) -> 0 | J6: =SUM(E6*$R$5) -> 0 | K6: =SUM(F6*$R$6) -> 0 | L6: =SUM(G6*$R$7) -> 0 | M6: =SUM(H6*$R$8) -> 0 | N6: =SUM(I6:M6) -> 0 | Q6: Хранение | R6: 18
A7: 3 | B7: 46206 | F7: =F6-E6+D7 -> 0 | G7: 0 | H7: 0 | I7: =SUM(D7*R6) -> 0 | J7: =SUM(E7*$R$5) -> 0 | K7: =SUM(F7*$R$6) -> 0 | L7: =SUM(G7*$R$7) -> 0 | M7: =SUM(H7*$R$8) -> 0 | N7: =SUM(I7:M7) -> 0 | Q7: Переконсолидация | R7: 950
A8: 4 | B8: 46207 | F8: =F7-E7+D8 -> 0 | G8: 0 | H8: 0 | I8: =SUM(D8*R7) -> 0 | J8: =SUM(E8*$R$5) -> 0 | K8: =SUM(F8*$R$6) -> 0 | L8: =SUM(G8*$R$7) -> 0 | M8: =SUM(H8*$R$8) -> 0 | N8: =SUM(I8:M8) -> 0 | Q8: Паллетирование | R8: 120
A9: 5 | B9: 46208 | F9: =F8-E8+D9 -> 0 | G9: 0 | H9: 0 | I9: =SUM(D9*R8) -> 0 | J9: =SUM(E9*$R$5) -> 0 | K9: =SUM(F9*$R$6) -> 0 | L9: =SUM(G9*$R$7) -> 0 | M9: =SUM(H9*$R$8) -> 0 | N9: =SUM(I9:M9) -> 0
A10: 6 | B10: 46209 | F10: =F9-E9+D10 -> 0 | G10: 0 | H10: 0 | I10: =SUM(D10*R9) -> 0 | J10: =SUM(E10*$R$5) -> 0 | K10: =SUM(F10*$R$6) -> 0 | L10: =SUM(G10*$R$7) -> 0 | M10: =SUM(H10*$R$8) -> 0 | N10: =SUM(I10:M10) -> 0
A11: 7 | B11: 46210 | F11: =F10-E10+D11 -> 0 | G11: 0 | H11: 0 | I11: =SUM(D11*R10) -> 0 | J11: =SUM(E11*$R$5) -> 0 | K11: =SUM(F11*$R$6) -> 0 | L11: =SUM(G11*$R$7) -> 0 | M11: =SUM(H11*$R$8) -> 0 | N11: =SUM(I11:M11) -> 0
A12: 8 | B12: 46211 | F12: =F11-E11+D12 -> 0 | G12: 0 | H12: 0 | I12: =SUM(D12*R11) -> 0 | J12: =SUM(E12*$R$5) -> 0 | K12: =SUM(F12*$R$6) -> 0 | L12: =SUM(G12*$R$7) -> 0 | M12: =SUM(H12*$R$8) -> 0 | N12: =SUM(I12:M12) -> 0
A13: 9 | B13: 46212 | F13: =F12-E12+D13 -> 0 | G13: 0 | H13: 0 | I13: =SUM(D13*R12) -> 0 | J13: =SUM(E13*$R$5) -> 0 | K13: =SUM(F13*$R$6) -> 0 | L13: =SUM(G13*$R$7) -> 0 | M13: =SUM(H13*$R$8) -> 0 | N13: =SUM(I13:M13) -> 0
A14: 10 | B14: 46213 | F14: =F13-E13+D14 -> 0 | G14: 0 | H14: 0 | I14: =SUM(D14*R13) -> 0 | J14: =SUM(E14*$R$5) -> 0 | K14: =SUM(F14*$R$6) -> 0 | L14: =SUM(G14*$R$7) -> 0 | M14: =SUM(H14*$R$8) -> 0 | N14: =SUM(I14:M14) -> 0
A15: 11 | B15: 46214 | F15: =F14-E14+D15 -> 0 | G15: 0 | H15: 0 | I15: =SUM(D15*R14) -> 0 | J15: =SUM(E15*$R$5) -> 0 | K15: =SUM(F15*$R$6) -> 0 | L15: =SUM(G15*$R$7) -> 0 | M15: =SUM(H15*$R$8) -> 0 | N15: =SUM(I15:M15) -> 0
A16: 12 | B16: 46215 | F16: =F15-E15+D16 -> 0 | G16: 0 | H16: 0 | I16: =SUM(D16*R15) -> 0 | J16: =SUM(E16*$R$5) -> 0 | K16: =SUM(F16*$R$6) -> 0 | L16: =SUM(G16*$R$7) -> 0 | M16: =SUM(H16*$R$8) -> 0 | N16: =SUM(I16:M16) -> 0
A17: 13 | B17: 46216 | F17: =F16-E16+D17 -> 0 | G17: 0 | H17: 0 | I17: =SUM(D17*R16) -> 0 | J17: =SUM(E17*$R$5) -> 0 | K17: =SUM(F17*$R$6) -> 0 | L17: =SUM(G17*$R$7) -> 0 | M17: =SUM(H17*$R$8) -> 0 | N17: =SUM(I17:M17) -> 0
A18: 14 | B18: 46217 | F18: =F17-E17+D18 -> 0 | G18: 0 | H18: 0 | I18: =SUM(D18*R17) -> 0 | J18: =SUM(E18*$R$5) -> 0 | K18: =SUM(F18*$R$6) -> 0 | L18: =SUM(G18*$R$7) -> 0 | M18: =SUM(H18*$R$8) -> 0 | N18: =SUM(I18:M18) -> 0
A19: 15 | B19: 46218 | F19: =F18-E18+D19 -> 0 | G19: 0 | H19: 0 | I19: =SUM(D19*R18) -> 0 | J19: =SUM(E19*$R$5) -> 0 | K19: =SUM(F19*$R$6) -> 0 | L19: =SUM(G19*$R$7) -> 0 | M19: =SUM(H19*$R$8) -> 0 | N19: =SUM(I19:M19) -> 0
A20: 16 | B20: 46219 | F20: =F19-E19+D20 -> 0 | G20: 0 | H20: 0 | I20: =SUM(D20*R19) -> 0 | J20: =SUM(E20*$R$5) -> 0 | K20: =SUM(F20*$R$6) -> 0 | L20: =SUM(G20*$R$7) -> 0 | M20: =SUM(H20*$R$8) -> 0 | N20: =SUM(I20:M20) -> 0
... A34: 30 | B34: 46233 | F34: =F33-E33+D34 -> 0 | G34: 0 | H34: 0 | I34: =SUM(D34*R33) -> 0 | J34: =SUM(E34*$R$5) -> 0 | K34: =SUM(F34*$R$6) -> 0 | L34: =SUM(G34*$R$7) -> 0 | M34: =SUM(H34*$R$8) -> 0 | N34: =SUM(I34:M34) -> 0
F35: =F34-E34+D35 -> 0 | G35: 0 | H35: 0 | I35: =SUM(D35*R34) -> 0 | J35: =SUM(E35*$R$5) -> 0 | K35: =SUM(F35*$R$6) -> 0 | L35: =SUM(G35*$R$7) -> 0 | M35: =SUM(H35*$R$8) -> 0 | N35: =SUM(I35:M35) -> 0
D36: =SUM(D5:D35) -> 0 | E36: =SUM(E5:E35) -> 0 | F36: =SUM(F5:F35) -> 0 | G36: =SUM(G5:G35) -> 0 | H36: =SUM(H5:H35) -> 0 | I36: =SUM(I5:I35) -> 0 | J36: =SUM(J5:J35) -> 0 | K36: =SUM(K5:K35) -> 0 | ... N36: =SUM(N5:N35) -> 0
N37: =N36*1.22 -> 0

Sheet Центрополимер Екатеринбург
A1: =N37 -> 0
A2: ="Отчет по хранению товара за " & TEXT(B5,"ММММ ГГГГ") -> Отчет по хранению товара за Июль 2026
A3: № | B3: дата | D3: Выгрузка кол-во | E3: Загрузка кол-во | F3: Хранение | G3: переконсолидация (тонн) | H3: Паллетирование | I3: стоимость выгрузки | J3: стоимость загрузки | K3: стоимость хранения | L3: стоимость переконс. | M3: Стоимость паллетирования | N3: итого | Q3: Цены
Q4: Выгрузка | R4: 140
A5: 1 | B5: 46204 | F5: 0 | G5: 0 | H5: 0 | I5: =SUM(D5*$R$4) -> 0 | J5: =SUM(E5*$R$5) -> 0 | K5: =SUM(F5*$R$6) -> 0 | L5: =SUM(G5*$R$7) -> 0 | M5: =SUM(H5*$R$8) -> 0 | N5: =SUM(I5:M5) -> 0 | Q5: Загрузка | R5: 140
A6: 2 | B6: 46205 | F6: =F5-E5+D6 -> 0 | G6: 0 | H6: 0 | I6: =SUM(D6*$R$4) -> 0 | J6: =SUM(E6*$R$5) -> 0 | K6: =SUM(F6*$R$6) -> 0 | L6: =SUM(G6*$R$7) -> 0 | M6: =SUM(H6*$R$8) -> 0 | N6: =SUM(I6:M6) -> 0 | Q6: Хранение | R6: 20
A7: 3 | B7: 46206 | F7: =F6-E6+D7 -> 0 | G7: 0 | H7: 0 | I7: =SUM(D7*$R$4) -> 0 | J7: =SUM(E7*$R$5) -> 0 | K7: =SUM(F7*$R$6) -> 0 | L7: =SUM(G7*$R$7) -> 0 | M7: =SUM(H7*$R$8) -> 0 | N7: =SUM(I7:M7) -> 0 | Q7: Переконсолидация | R7: 950
A8: 4 | B8: 46207 | F8: =F7-E7+D8 -> 0 | G8: 0 | H8: 0 | I8: =SUM(D8*$R$4) -> 0 | J8: =SUM(E8*$R$5) -> 0 | K8: =SUM(F8*$R$6) -> 0 | L8: =SUM(G8*$R$7) -> 0 | M8: =SUM(H8*$R$8) -> 0 | N8: =SUM(I8:M8) -> 0 | Q8: Паллетирование | R8: 120
A9: 5 | B9: 46208 | F9: =F8-E8+D9 -> 0 | G9: 0 | H9: 0 | I9: =SUM(D9*$R$4) -> 0 | J9: =SUM(E9*$R$5) -> 0 | K9: =SUM(F9*$R$6) -> 0 | L9: =SUM(G9*$R$7) -> 0 | M9: =SUM(H9*$R$8) -> 0 | N9: =SUM(I9:M9) -> 0
A10: 6 | B10: 46209 | F10: =F9-E9+D10 -> 0 | G10: 0 | H10: 0 | I10: =SUM(D10*$R$4) -> 0 | J10: =SUM(E10*$R$5) -> 0 | K10: =SUM(F10*$R$6) -> 0 | L10: =SUM(G10*$R$7) -> 0 | M10: =SUM(H10*$R$8) -> 0 | N10: =SUM(I10:M10) -> 0
A11: 7 | B11: 46210 | F11: =F10-E10+D11 -> 0 | G11: 0 | H11: 0 | I11: =SUM(D11*$R$4) -> 0 | J11: =SUM(E11*$R$5) -> 0 | K11: =SUM(F11*$R$6) -> 0 | L11: =SUM(G11*$R$7) -> 0 | M11: =SUM(H11*$R$8) -> 0 | N11: =SUM(I11:M11) -> 0
A12: 8 | B12: 46211 | F12: =F11-E11+D12 -> 0 | G12: 0 | H12: 0 | I12: =SUM(D12*$R$4) -> 0 | J12: =SUM(E12*$R$5) -> 0 | K12: =SUM(F12*$R$6) -> 0 | L12: =SUM(G12*$R$7) -> 0 | M12: =SUM(H12*$R$8) -> 0 | N12: =SUM(I12:M12) -> 0
A13: 9 | B13: 46212 | F13: =F12-E12+D13 -> 0 | G13: 0 | H13: 0 | I13: =SUM(D13*$R$4) -> 0 | J13: =SUM(E13*$R$5) -> 0 | K13: =SUM(F13*$R$6) -> 0 | L13: =SUM(G13*$R$7) -> 0 | M13: =SUM(H13*$R$8) -> 0 | N13: =SUM(I13:M13) -> 0
A14: 10 | B14: 46213 | F14: =F13-E13+D14 -> 0 | G14: 0 | H14: 0 | I14: =SUM(D14*$R$4) -> 0 | J14: =SUM(E14*$R$5) -> 0 | K14: =SUM(F14*$R$6) -> 0 | L14: =SUM(G14*$R$7) -> 0 | M14: =SUM(H14*$R$8) -> 0 | N14: =SUM(I14:M14) -> 0
A15: 11 | B15: 46214 | F15: =F14-E14+D15 -> 0 | G15: 0 | H15: 0 | I15: =SUM(D15*$R$4) -> 0 | J15: =SUM(E15*$R$5) -> 0 | K15: =SUM(F15*$R$6) -> 0 | L15: =SUM(G15*$R$7) -> 0 | M15: =SUM(H15*$R$8) -> 0 | N15: =SUM(I15:M15) -> 0
A16: 12 | B16: 46215 | F16: =F15-E15+D16 -> 0 | G16: 0 | H16: 0 | I16: =SUM(D16*$R$4) -> 0 | J16: =SUM(E16*$R$5) -> 0 | K16: =SUM(F16*$R$6) -> 0 | L16: =SUM(G16*$R$7) -> 0 | M16: =SUM(H16*$R$8) -> 0 | N16: =SUM(I16:M16) -> 0
A17: 13 | B17: 46216 | F17: =F16-E16+D17 -> 0 | G17: 0 | H17: 0 | I17: =SUM(D17*$R$4) -> 0 | J17: =SUM(E17*$R$5) -> 0 | K17: =SUM(F17*$R$6) -> 0 | L17: =SUM(G17*$R$7) -> 0 | M17: =SUM(H17*$R$8) -> 0 | N17: =SUM(I17:M17) -> 0
A18: 14 | B18: 46217 | F18: =F17-E17+D18 -> 0 | G18: 0 | H18: 0 | I18: =SUM(D18*$R$4) -> 0 | J18: =SUM(E18*$R$5) -> 0 | K18: =SUM(F18*$R$6) -> 0 | L18: =SUM(G18*$R$7) -> 0 | M18: =SUM(H18*$R$8) -> 0 | N18: =SUM(I18:M18) -> 0
A19: 15 | B19: 46218 | F19: =F18-E18+D19 -> 0 | G19: 0 | H19: 0 | I19: =SUM(D19*$R$4) -> 0 | J19: =SUM(E19*$R$5) -> 0 | K19: =SUM(F19*$R$6) -> 0 | L19: =SUM(G19*$R$7) -> 0 | M19: =SUM(H19*$R$8) -> 0 | N19: =SUM(I19:M19) -> 0
A20: 16 | B20: 46219 | F20: =F19-E19+D20 -> 0 | G20: 0 | H20: 0 | I20: =SUM(D20*$R$4) -> 0 | J20: =SUM(E20*$R$5) -> 0 | K20: =SUM(F20*$R$6) -> 0 | L20: =SUM(G20*$R$7) -> 0 | M20: =SUM(H20*$R$8) -> 0 | N20: =SUM(I20:M20) -> 0
... A34: 30 | B34: 46233 | F34: =F33-E33+D34 -> 0 | G34: 0 | H34: 0 | I34: =SUM(D34*$R$4) -> 0 | J34: =SUM(E34*$R$5) -> 0 | K34: =SUM(F34*$R$6) -> 0 | L34: =SUM(G34*$R$7) -> 0 | M34: =SUM(H34*$R$8) -> 0 | N34: =SUM(I34:M34) -> 0
G35: 0 | H35: 0 | I35: =SUM(D35*$R$4) -> 0 | J35: =SUM(E35*$R$5) -> 0 | K35: =SUM(F35*$R$6) -> 0 | L35: =SUM(G35*$R$7) -> 0 | M35: =SUM(H35*$R$8) -> 0 | N35: =SUM(I35:M35) -> 0
D36: =SUM(D5:D35) -> 0 | E36: =SUM(E5:E35) -> 0 | F36: =SUM(F5:F35) -> 0 | G36: =SUM(G5:G35) -> 0 | H36: =SUM(H5:H35) -> 0 | I36: =SUM(I5:I35) -> 0 | J36: =SUM(J5:J35) -> 0 | K36: =SUM(K5:K35) -> 0 | ... N36: =SUM(N5:N35) -> 0
N37: =N36*1.22 -> 0

Sheet Центрополимер Новосибирск
A1: =N37 -> 0
A2: ="Отчет по хранению товара за " & TEXT(B5,"ММММ ГГГГ") -> Отчет по хранению товара за Июль 2026
A3: № | B3: дата | D3: Выгрузка кол-во | E3: Загрузка кол-во | F3: Хранение | G3: переконсолидация (тонн) | H3: Паллетирование | I3: стоимость выгрузки | J3: стоимость загрузки | K3: стоимость хранения | L3: стоимость переконс. | M3: Стоимость паллетирования | N3: итого | Q3: Цены
Q4: Выгрузка | R4: 140
A5: 1 | B5: 46204 | D5: 0 | E5: 0 | F5: 0 | G5: 0 | H5: 0 | I5: =SUM(D5*$R$4) -> 0 | J5: =SUM(E5*$R$5) -> 0 | K5: =SUM(F5*$R$6) -> 0 | L5: =SUM(G5*$R$7) -> 0 | M5: =SUM(H5*$R$8) -> 0 | N5: =SUM(I5:M5) -> 0 | Q5: Загрузка | R5: 140
A6: 2 | B6: 46205 | D6: 0 | E6: 0 | F6: =F5-E5+D6 -> 0 | G6: 0 | H6: 0 | I6: =SUM(D6*$R$4) -> 0 | J6: =SUM(E6*$R$5) -> 0 | K6: =SUM(F6*$R$6) -> 0 | L6: =SUM(G6*$R$7) -> 0 | M6: =SUM(H6*$R$8) -> 0 | N6: =SUM(I6:M6) -> 0 | Q6: Хранение | R6: 26
A7: 3 | B7: 46206 | D7: 0 | E7: 0 | F7: =F6-E6+D7 -> 0 | G7: 0 | H7: 0 | I7: =SUM(D7*$R$4) -> 0 | J7: =SUM(E7*$R$5) -> 0 | K7: =SUM(F7*$R$6) -> 0 | L7: =SUM(G7*$R$7) -> 0 | M7: =SUM(H7*$R$8) -> 0 | N7: =SUM(I7:M7) -> 0 | Q7: Переконсолидация | R7: 950
A8: 4 | B8: 46207 | D8: 0 | E8: 0 | F8: =F7-E7+D8 -> 0 | G8: 0 | H8: 0 | I8: =SUM(D8*$R$4) -> 0 | J8: =SUM(E8*$R$5) -> 0 | K8: =SUM(F8*$R$6) -> 0 | L8: =SUM(G8*$R$7) -> 0 | M8: =SUM(H8*$R$8) -> 0 | N8: =SUM(I8:M8) -> 0 | Q8: Паллетирование | R8: 120
A9: 5 | B9: 46208 | D9: 0 | E9: 0 | F9: =F8-E8+D9 -> 0 | G9: 0 | H9: 0 | I9: =SUM(D9*$R$4) -> 0 | J9: =SUM(E9*$R$5) -> 0 | K9: =SUM(F9*$R$6) -> 0 | L9: =SUM(G9*$R$7) -> 0 | M9: =SUM(H9*$R$8) -> 0 | N9: =SUM(I9:M9) -> 0
A10: 6 | B10: 46209 | D10: 0 | E10: 0 | F10: =F9-E9+D10 -> 0 | G10: 0 | H10: 0 | I10: =SUM(D10*$R$4) -> 0 | J10: =SUM(E10*$R$5) -> 0 | K10: =SUM(F10*$R$6) -> 0 | L10: =SUM(G10*$R$7) -> 0 | M10: =SUM(H10*$R$8) -> 0 | N10: =SUM(I10:M10) -> 0
A11: 7 | B11: 46210 | D11: 0 | E11: 0 | F11: =F10-E10+D11 -> 0 | G11: 0 | H11: 0 | I11: =SUM(D11*$R$4) -> 0 | J11: =SUM(E11*$R$5) -> 0 | K11: =SUM(F11*$R$6) -> 0 | L11: =SUM(G11*$R$7) -> 0 | M11: =SUM(H11*$R$8) -> 0 | N11: =SUM(I11:M11) -> 0
A12: 8 | B12: 46211 | D12: 0 | E12: 0 | F12: =F11-E11+D12 -> 0 | G12: 0 | H12: 0 | I12: =SUM(D12*$R$4) -> 0 | J12: =SUM(E12*$R$5) -> 0 | K12: =SUM(F12*$R$6) -> 0 | L12: =SUM(G12*$R$7) -> 0 | M12: =SUM(H12*$R$8) -> 0 | N12: =SUM(I12:M12) -> 0
A13: 9 | B13: 46212 | D13: 0 | E13: 0 | F13: =F12-E12+D13 -> 0 | G13: 0 | H13: 0 | I13: =SUM(D13*$R$4) -> 0 | J13: =SUM(E13*$R$5) -> 0 | K13: =SUM(F13*$R$6) -> 0 | L13: =SUM(G13*$R$7) -> 0 | M13: =SUM(H13*$R$8) -> 0 | N13: =SUM(I13:M13) -> 0
A14: 10 | B14: 46213 | D14: 0 | E14: 0 | F14: =F13-E13+D14 -> 0 | G14: 0 | H14: 0 | I14: =SUM(D14*$R$4) -> 0 | J14: =SUM(E14*$R$5) -> 0 | K14: =SUM(F14*$R$6) -> 0 | L14: =SUM(G14*$R$7) -> 0 | M14: =SUM(H14*$R$8) -> 0 | N14: =SUM(I14:M14) -> 0
A15: 11 | B15: 46214 | D15: 0 | E15: 0 | F15: =F14-E14+D15 -> 0 | G15: 0 | H15: 0 | I15: =SUM(D15*$R$4) -> 0 | J15: =SUM(E15*$R$5) -> 0 | K15: =SUM(F15*$R$6) -> 0 | L15: =SUM(G15*$R$7) -> 0 | M15: =SUM(H15*$R$8) -> 0 | N15: =SUM(I15:M15) -> 0
A16: 12 | B16: 46215 | D16: 0 | E16: 0 | F16: =F15-E15+D16 -> 0 | G16: 0 | H16: 0 | I16: =SUM(D16*$R$4) -> 0 | J16: =SUM(E16*$R$5) -> 0 | K16: =SUM(F16*$R$6) -> 0 | L16: =SUM(G16*$R$7) -> 0 | M16: =SUM(H16*$R$8) -> 0 | N16: =SUM(I16:M16) -> 0
A17: 13 | B17: 46216 | D17: 0 | E17: 0 | F17: =F16-E16+D17 -> 0 | G17: 0 | H17: 0 | I17: =SUM(D17*$R$4) -> 0 | J17: =SUM(E17*$R$5) -> 0 | K17: =SUM(F17*$R$6) -> 0 | L17: =SUM(G17*$R$7) -> 0 | M17: =SUM(H17*$R$8) -> 0 | N17: =SUM(I17:M17) -> 0
A18: 14 | B18: 46217 | D18: 0 | E18: 0 | F18: =F17-E17+D18 -> 0 | G18: 0 | H18: 0 | I18: =SUM(D18*$R$4) -> 0 | J18: =SUM(E18*$R$5) -> 0 | K18: =SUM(F18*$R$6) -> 0 | L18: =SUM(G18*$R$7) -> 0 | M18: =SUM(H18*$R$8) -> 0 | N18: =SUM(I18:M18) -> 0
A19: 15 | B19: 46218 | D19: 0 | E19: 0 | F19: =F18-E18+D19 -> 0 | G19: 0 | H19: 0 | I19: =SUM(D19*$R$4) -> 0 | J19: =SUM(E19*$R$5) -> 0 | K19: =SUM(F19*$R$6) -> 0 | L19: =SUM(G19*$R$7) -> 0 | M19: =SUM(H19*$R$8) -> 0 | N19: =SUM(I19:M19) -> 0
A20: 16 | B20: 46219 | D20: 0 | E20: 0 | F20: =F19-E19+D20 -> 0 | G20: 0 | H20: 0 | I20: =SUM(D20*$R$4) -> 0 | J20: =SUM(E20*$R$5) -> 0 | K20: =SUM(F20*$R$6) -> 0 | L20: =SUM(G20*$R$7) -> 0 | M20: =SUM(H20*$R$8) -> 0 | N20: =SUM(I20:M20) -> 0
... A34: 30 | B34: 46233 | D34: 0 | E34: 0 | F34: =F33-E33+D34 -> 0 | G34: 0 | H34: 0 | I34: =SUM(D34*$R$4) -> 0 | J34: =SUM(E34*$R$5) -> 0 | K34: =SUM(F34*$R$6) -> 0 | L34: =SUM(G34*$R$7) -> 0 | M34: =SUM(H34*$R$8) -> 0 | N34: =SUM(I34:M34) -> 0
B35: 46234 | D35: 0 | E35: 0 | F35: =F34-E34+D35 -> 0 | G35: 0 | H35: 0 | I35: =SUM(D35*$R$4) -> 0 | J35: =SUM(E35*$R$5) -> 0 | K35: =SUM(F35*$R$6) -> 0 | L35: =SUM(G35*$R$7) -> 0 | M35: =SUM(H35*$R$8) -> 0 | N35: =SUM(I35:M35) -> 0
D36: =SUM(D5:D35) -> 0 | E36: =SUM(E5:E35) -> 0 | F36: =SUM(F5:F35) -> 0 | G36: =SUM(G5:G35) -> 0 | H36: =SUM(H5:H35) -> 0 | I36: =SUM(I5:I35) -> 0 | J36: =SUM(J5:J35) -> 0 | K36: =SUM(K5:K35) -> 0 | ... N36: =SUM(N5:N35) -> 0
N37: =N36*1.22 -> 0

Sheet Юг Полимер Зеленодольск
A1: =N37 -> 0
A2: ="Отчет по хранению товара за " & TEXT(B5,"ММММ ГГГГ") -> Отчет по хранению товара за Июль 2026 | I2: Зеленодольск
A3: № | B3: дата | D3: Выгрузка кол-во | E3: Загрузка кол-во | F3: Хранение | G3: переконсолидация (тонн) | H3: Паллетирование | I3: стоимость выгрузки | J3: стоимость загрузки | K3: стоимость хранения | L3: стоимость переконс. | M3: Стоимость паллетирования | N3: итого | Q3: Цены
Q4: Выгрузка | R4: 140
A5: 1 | B5: 46204 | F5: 0 | G5: 0 | H5: 0 | I5: =SUM(D5*$R$4) -> 0 | J5: =SUM(E5*$R$5) -> 0 | K5: =SUM(F5*$R$6) -> 0 | L5: =SUM(G5*$R$7) -> 0 | M5: =SUM(H5*$R$8) -> 0 | N5: =SUM(I5:M5) -> 0 | Q5: Загрузка | R5: 140
A6: 2 | B6: 46205 | F6: =F5-E5+D6 -> 0 | G6: 0 | H6: 0 | I6: =SUM(D6*$R$4) -> 0 | J6: =SUM(E6*$R$5) -> 0 | K6: =SUM(F6*$R$6) -> 0 | L6: =SUM(G6*$R$7) -> 0 | M6: =SUM(H6*$R$8) -> 0 | N6: =SUM(I6:M6) -> 0 | Q6: Хранение | R6: 15
A7: 3 | B7: 46206 | F7: =F6-E6+D7 -> 0 | G7: 0 | H7: 0 | I7: =SUM(D7*$R$4) -> 0 | J7: =SUM(E7*$R$5) -> 0 | K7: =SUM(F7*$R$6) -> 0 | L7: =SUM(G7*$R$7) -> 0 | M7: =SUM(H7*$R$8) -> 0 | N7: =SUM(I7:M7) -> 0 | Q7: Переконсолидация | R7: 120
A8: 4 | B8: 46207 | F8: =F7-E7+D8 -> 0 | G8: 0 | H8: 0 | I8: =SUM(D8*$R$4) -> 0 | J8: =SUM(E8*$R$5) -> 0 | K8: =SUM(F8*$R$6) -> 0 | L8: =SUM(G8*$R$7) -> 0 | M8: =SUM(H8*$R$8) -> 0 | N8: =SUM(I8:M8) -> 0 | Q8: Паллетирование | R8: 150
A9: 5 | B9: 46208 | F9: =F8-E8+D9 -> 0 | G9: 0 | H9: 0 | I9: =SUM(D9*$R$4) -> 0 | J9: =SUM(E9*$R$5) -> 0 | K9: =SUM(F9*$R$6) -> 0 | L9: =SUM(G9*$R$7) -> 0 | M9: =SUM(H9*$R$8) -> 0 | N9: =SUM(I9:M9) -> 0
A10: 6 | B10: 46209 | F10: =F9-E9+D10 -> 0 | G10: 0 | H10: 0 | I10: =SUM(D10*$R$4) -> 0 | J10: =SUM(E10*$R$5) -> 0 | K10: =SUM(F10*$R$6) -> 0 | L10: =SUM(G10*$R$7) -> 0 | M10: =SUM(H10*$R$8) -> 0 | N10: =SUM(I10:M10) -> 0
A11: 7 | B11: 46210 | F11: =F10-E10+D11 -> 0 | G11: 0 | H11: 0 | I11: =SUM(D11*$R$4) -> 0 | J11: =SUM(E11*$R$5) -> 0 | K11: =SUM(F11*$R$6) -> 0 | L11: =SUM(G11*$R$7) -> 0 | M11: =SUM(H11*$R$8) -> 0 | N11: =SUM(I11:M11) -> 0
A12: 8 | B12: 46211 | F12: =F11-E11+D12 -> 0 | G12: 0 | H12: 0 | I12: =SUM(D12*$R$4) -> 0 | J12: =SUM(E12*$R$5) -> 0 | K12: =SUM(F12*$R$6) -> 0 | L12: =SUM(G12*$R$7) -> 0 | M12: =SUM(H12*$R$8) -> 0 | N12: =SUM(I12:M12) -> 0
A13: 9 | B13: 46212 | F13: =F12-E12+D13 -> 0 | G13: 0 | H13: 0 | I13: =SUM(D13*$R$4) -> 0 | J13: =SUM(E13*$R$5) -> 0 | K13: =SUM(F13*$R$6) -> 0 | L13: =SUM(G13*$R$7) -> 0 | M13: =SUM(H13*$R$8) -> 0 | N13: =SUM(I13:M13) -> 0
A14: 10 | B14: 46213 | F14: =F13-E13+D14 -> 0 | G14: 0 | H14: 0 | I14: =SUM(D14*$R$4) -> 0 | J14: =SUM(E14*$R$5) -> 0 | K14: =SUM(F14*$R$6) -> 0 | L14: =SUM(G14*$R$7) -> 0 | M14: =SUM(H14*$R$8) -> 0 | N14: =SUM(I14:M14) -> 0
A15: 11 | B15: 46214 | F15: =F14-E14+D15 -> 0 | G15: 0 | H15: 0 | I15: =SUM(D15*$R$4) -> 0 | J15: =SUM(E15*$R$5) -> 0 | K15: =SUM(F15*$R$6) -> 0 | L15: =SUM(G15*$R$7) -> 0 | M15: =SUM(H15*$R$8) -> 0 | N15: =SUM(I15:M15) -> 0
A16: 12 | B16: 46215 | F16: =F15-E15+D16 -> 0 | G16: 0 | H16: 0 | I16: =SUM(D16*$R$4) -> 0 | J16: =SUM(E16*$R$5) -> 0 | K16: =SUM(F16*$R$6) -> 0 | L16: =SUM(G16*$R$7) -> 0 | M16: =SUM(H16*$R$8) -> 0 | N16: =SUM(I16:M16) -> 0
A17: 13 | B17: 46216 | F17: =F16-E16+D17 -> 0 | G17: 0 | H17: 0 | I17: =SUM(D17*$R$4) -> 0 | J17: =SUM(E17*$R$5) -> 0 | K17: =SUM(F17*$R$6) -> 0 | L17: =SUM(G17*$R$7) -> 0 | M17: =SUM(H17*$R$8) -> 0 | N17: =SUM(I17:M17) -> 0
A18: 14 | B18: 46217 | F18: =F17-E17+D18 -> 0 | G18: 0 | H18: 0 | I18: =SUM(D18*$R$4) -> 0 | J18: =SUM(E18*$R$5) -> 0 | K18: =SUM(F18*$R$6) -> 0 | L18: =SUM(G18*$R$7) -> 0 | M18: =SUM(H18*$R$8) -> 0 | N18: =SUM(I18:M18) -> 0
A19: 15 | B19: 46218 | F19: =F18-E18+D19 -> 0 | G19: 0 | H19: 0 | I19: =SUM(D19*$R$4) -> 0 | J19: =SUM(E19*$R$5) -> 0 | K19: =SUM(F19*$R$6) -> 0 | L19: =SUM(G19*$R$7) -> 0 | M19: =SUM(H19*$R$8) -> 0 | N19: =SUM(I19:M19) -> 0
A20: 16 | B20: 46219 | F20: =F19-E19+D20 -> 0 | G20: 0 | H20: 0 | I20: =SUM(D20*$R$4) -> 0 | J20: =SUM(E20*$R$5) -> 0 | K20: =SUM(F20*$R$6) -> 0 | L20: =SUM(G20*$R$7) -> 0 | M20: =SUM(H20*$R$8) -> 0 | N20: =SUM(I20:M20) -> 0
... A34: 30 | B34: 46233 | F34: =F33-E33+D34 -> 0 | G34: 0 | H34: 0 | I34: =SUM(D34*$R$4) -> 0 | J34: =SUM(E34*$R$5) -> 0 | K34: =SUM(F34*$R$6) -> 0 | L34: =SUM(G34*$R$7) -> 0 | M34: =SUM(H34*$R$8) -> 0 | N34: =SUM(I34:M34) -> 0
G35: 0 | H35: 0 | I35: =SUM(D35*$R$4) -> 0 | J35: =SUM(E35*$R$5) -> 0 | K35: =SUM(F35*$R$6) -> 0 | L35: =SUM(G35*$R$7) -> 0 | M35: =SUM(H35*$R$8) -> 0 | N35: =SUM(I35:M35) -> 0
D36: =SUM(D5:D35) -> 0 | E36: =SUM(E5:E35) -> 0 | F36: =SUM(F5:F35) -> 0 | G36: =SUM(G5:G35) -> 0 | H36: =SUM(H5:H35) -> 0 | I36: =SUM(I5:I35) -> 0 | J36: =SUM(J5:J35) -> 0 | K36: =SUM(K5:K35) -> 0 | ... N36: =SUM(N5:N35) -> 0
N37: =N36*1.22 -> 0

Sheet Юг Полимер Новикова-Прибоя
A1: =N37 -> 0
A2: ="Отчет по хранению товара за " & TEXT(B5,"ММММ ГГГГ") -> Отчет по хранению товара за Июль 2026 | I2: Новикова
A3: № | B3: дата | D3: Выгрузка кол-во | E3: Загрузка кол-во | F3: Хранение | G3: переконсолидация (тонн) | H3: Паллетирование | I3: стоимость выгрузки | J3: стоимость загрузки | K3: стоимость хранения | L3: стоимость переконс. | M3: Стоимость паллетирования | N3: итого | Q3: Цены
Q4: Выгрузка | R4: 120
A5: 1 | B5: 46204 | F5: 0 | G5: 0 | H5: 0 | I5: =SUM(D5*$R$4) -> 0 | J5: =SUM(E5*$R$5) -> 0 | K5: =SUM(F5*$R$6) -> 0 | L5: =SUM(G5*$R$7) -> 0 | M5: =SUM(H5*$R$8) -> 0 | N5: =SUM(I5:M5) -> 0 | Q5: Загрузка | R5: 120
A6: 2 | B6: 46205 | F6: =F5-E5+D6 -> 0 | G6: 0 | H6: 0 | I6: =SUM(D6*$R$4) -> 0 | J6: =SUM(E6*$R$5) -> 0 | K6: =SUM(F6*$R$6) -> 0 | L6: =SUM(G6*$R$7) -> 0 | M6: =SUM(H6*$R$8) -> 0 | N6: =SUM(I6:M6) -> 0 | Q6: Хранение | R6: 18
A7: 3 | B7: 46206 | F7: =F6-E6+D7 -> 0 | G7: 0 | H7: 0 | I7: =SUM(D7*$R$4) -> 0 | J7: =SUM(E7*$R$5) -> 0 | K7: =SUM(F7*$R$6) -> 0 | L7: =SUM(G7*$R$7) -> 0 | M7: =SUM(H7*$R$8) -> 0 | N7: =SUM(I7:M7) -> 0 | Q7: Переконсолидация | R7: 950
A8: 4 | B8: 46207 | F8: =F7-E7+D8 -> 0 | G8: 0 | H8: 0 | I8: =SUM(D8*$R$4) -> 0 | J8: =SUM(E8*$R$5) -> 0 | K8: =SUM(F8*$R$6) -> 0 | L8: =SUM(G8*$R$7) -> 0 | M8: =SUM(H8*$R$8) -> 0 | N8: =SUM(I8:M8) -> 0 | Q8: Паллетирование | R8: 120
A9: 5 | B9: 46208 | F9: =F8-E8+D9 -> 0 | G9: 0 | H9: 0 | I9: =SUM(D9*$R$4) -> 0 | J9: =SUM(E9*$R$5) -> 0 | K9: =SUM(F9*$R$6) -> 0 | L9: =SUM(G9*$R$7) -> 0 | M9: =SUM(H9*$R$8) -> 0 | N9: =SUM(I9:M9) -> 0
A10: 6 | B10: 46209 | F10: =F9-E9+D10 -> 0 | G10: 0 | H10: 0 | I10: =SUM(D10*$R$4) -> 0 | J10: =SUM(E10*$R$5) -> 0 | K10: =SUM(F10*$R$6) -> 0 | L10: =SUM(G10*$R$7) -> 0 | M10: =SUM(H10*$R$8) -> 0 | N10: =SUM(I10:M10) -> 0
A11: 7 | B11: 46210 | F11: =F10-E10+D11 -> 0 | G11: 0 | H11: 0 | I11: =SUM(D11*$R$4) -> 0 | J11: =SUM(E11*$R$5) -> 0 | K11: =SUM(F11*$R$6) -> 0 | L11: =SUM(G11*$R$7) -> 0 | M11: =SUM(H11*$R$8) -> 0 | N11: =SUM(I11:M11) -> 0
A12: 8 | B12: 46211 | F12: =F11-E11+D12 -> 0 | G12: 0 | H12: 0 | I12: =SUM(D12*$R$4) -> 0 | J12: =SUM(E12*$R$5) -> 0 | K12: =SUM(F12*$R$6) -> 0 | L12: =SUM(G12*$R$7) -> 0 | M12: =SUM(H12*$R$8) -> 0 | N12: =SUM(I12:M12) -> 0
A13: 9 | B13: 46212 | F13: =F12-E12+D13 -> 0 | G13: 0 | H13: 0 | I13: =SUM(D13*$R$4) -> 0 | J13: =SUM(E13*$R$5) -> 0 | K13: =SUM(F13*$R$6) -> 0 | L13: =SUM(G13*$R$7) -> 0 | M13: =SUM(H13*$R$8) -> 0 | N13: =SUM(I13:M13) -> 0
A14: 10 | B14: 46213 | F14: =F13-E13+D14 -> 0 | G14: 0 | H14: 0 | I14: =SUM(D14*$R$4) -> 0 | J14: =SUM(E14*$R$5) -> 0 | K14: =SUM(F14*$R$6) -> 0 | L14: =SUM(G14*$R$7) -> 0 | M14: =SUM(H14*$R$8) -> 0 | N14: =SUM(I14:M14) -> 0
A15: 11 | B15: 46214 | F15: =F14-E14+D15 -> 0 | G15: 0 | H15: 0 | I15: =SUM(D15*$R$4) -> 0 | J15: =SUM(E15*$R$5) -> 0 | K15: =SUM(F15*$R$6) -> 0 | L15: =SUM(G15*$R$7) -> 0 | M15: =SUM(H15*$R$8) -> 0 | N15: =SUM(I15:M15) -> 0
A16: 12 | B16: 46215 | F16: =F15-E15+D16 -> 0 | G16: 0 | H16: 0 | I16: =SUM(D16*$R$4) -> 0 | J16: =SUM(E16*$R$5) -> 0 | K16: =SUM(F16*$R$6) -> 0 | L16: =SUM(G16*$R$7) -> 0 | M16: =SUM(H16*$R$8) -> 0 | N16: =SUM(I16:M16) -> 0
A17: 13 | B17: 46216 | F17: =F16-E16+D17 -> 0 | G17: 0 | H17: 0 | I17: =SUM(D17*$R$4) -> 0 | J17: =SUM(E17*$R$5) -> 0 | K17: =SUM(F17*$R$6) -> 0 | L17: =SUM(G17*$R$7) -> 0 | M17: =SUM(H17*$R$8) -> 0 | N17: =SUM(I17:M17) -> 0
A18: 14 | B18: 46217 | F18: =F17-E17+D18 -> 0 | G18: 0 | H18: 0 | I18: =SUM(D18*$R$4) -> 0 | J18: =SUM(E18*$R$5) -> 0 | K18: =SUM(F18*$R$6) -> 0 | L18: =SUM(G18*$R$7) -> 0 | M18: =SUM(H18*$R$8) -> 0 | N18: =SUM(I18:M18) -> 0
A19: 15 | B19: 46218 | F19: =F18-E18+D19 -> 0 | G19: 0 | H19: 0 | I19: =SUM(D19*$R$4) -> 0 | J19: =SUM(E19*$R$5) -> 0 | K19: =SUM(F19*$R$6) -> 0 | L19: =SUM(G19*$R$7) -> 0 | M19: =SUM(H19*$R$8) -> 0 | N19: =SUM(I19:M19) -> 0
A20: 16 | B20: 46219 | F20: =F19-E19+D20 -> 0 | G20: 0 | H20: 0 | I20: =SUM(D20*$R$4) -> 0 | J20: =SUM(E20*$R$5) -> 0 | K20: =SUM(F20*$R$6) -> 0 | L20: =SUM(G20*$R$7) -> 0 | M20: =SUM(H20*$R$8) -> 0 | N20: =SUM(I20:M20) -> 0
... A34: 30 | B34: 46233 | F34: =F33-E33+D34 -> 0 | G34: 0 | H34: 0 | I34: =SUM(D34*$R$4) -> 0 | J34: =SUM(E34*$R$5) -> 0 | K34: =SUM(F34*$R$6) -> 0 | L34: =SUM(G34*$R$7) -> 0 | M34: =SUM(H34*$R$8) -> 0 | N34: =SUM(I34:M34) -> 0
G35: 0 | H35: 0 | I35: =SUM(D35*$R$4) -> 0 | J35: =SUM(E35*$R$5) -> 0 | K35: =SUM(F35*$R$6) -> 0 | L35: =SUM(G35*$R$7) -> 0 | M35: =SUM(H35*$R$8) -> 0 | N35: =SUM(I35:M35) -> 0
D36: =SUM(D5:D35) -> 0 | E36: =SUM(E5:E35) -> 0 | F36: =SUM(F5:F35) -> 0 | G36: =SUM(G5:G35) -> 0 | H36: =SUM(H5:H35) -> 0 | I36: =SUM(I5:I35) -> 0 | J36: =SUM(J5:J35) -> 0 | K36: =SUM(K5:K35) -> 0 | ... N36: =SUM(N5:N35) -> 0
N37: =N36*1.22 -> 0

Sheet Юг Полимер Баумана
A1: =N37 -> 337898.52
A2: ="Отчет по хранению товара за " & TEXT(B5,"ММММ ГГГГ") -> Отчет по хранению товара за Июль 2026 | I2: Баумана
A3: № | B3: дата | D3: Выгрузка кол-во | E3: Загрузка кол-во | F3: Хранение | G3: переконсолидация (тонн) | H3: Паллетирование | I3: стоимость выгрузки | J3: стоимость загрузки | K3: стоимость хранения | L3: стоимость переконс. | M3: Стоимость паллетирования | N3: итого | Q3: Цены
Q4: Выгрузка | R4: 140
A5: 1 | B5: 46204 | D5: 0 | F5: 405 | G5: 0 | H5: 0 | I5: =SUM(D5*$R$4) -> 0 | J5: =SUM(E5*$R$5) -> 0 | K5: =SUM(F5*$R$6) -> 10530 | L5: =SUM(G5*$R$7) -> 0 | M5: =SUM(H5*$R$8) -> 0 | N5: =SUM(I5:M5) -> 10530 | Q5: Загрузка | R5: 140
A6: 2 | B6: 46205 | D6: 0 | F6: =F5-E5+D6 -> 405 | G6: 0 | H6: 0 | I6: =SUM(D6*$R$4) -> 0 | J6: =SUM(E6*$R$5) -> 0 | K6: =SUM(F6*$R$6) -> 10530 | L6: =SUM(G6*$R$7) -> 0 | M6: =SUM(H6*$R$8) -> 0 | N6: =SUM(I6:M6) -> 10530 | Q6: Хранение | R6: 26
A7: 3 | B7: 46206 | D7: 0 | F7: =F6-E6+D7 -> 405 | G7: 0 | H7: 0 | I7: =SUM(D7*$R$4) -> 0 | J7: =SUM(E7*$R$5) -> 0 | K7: =SUM(F7*$R$6) -> 10530 | L7: =SUM(G7*$R$7) -> 0 | M7: =SUM(H7*$R$8) -> 0 | N7: =SUM(I7:M7) -> 10530 | Q7: Переконсолидация | R7: 950
A8: 4 | B8: 46207 | D8: 0 | F8: =F7-E7+D8 -> 405 | G8: 0 | H8: 0 | I8: =SUM(D8*$R$4) -> 0 | J8: =SUM(E8*$R$5) -> 0 | K8: =SUM(F8*$R$6) -> 10530 | L8: =SUM(G8*$R$7) -> 0 | M8: =SUM(H8*$R$8) -> 0 | N8: =SUM(I8:M8) -> 10530 | Q8: Паллетирование | R8: 120
A9: 5 | B9: 46208 | D9: 0 | F9: =F8-E8+D9 -> 405 | G9: 0 | H9: 0 | I9: =SUM(D9*$R$4) -> 0 | J9: =SUM(E9*$R$5) -> 0 | K9: =SUM(F9*$R$6) -> 10530 | L9: =SUM(G9*$R$7) -> 0 | M9: =SUM(H9*$R$8) -> 0 | N9: =SUM(I9:M9) -> 10530
A10: 6 | B10: 46209 | D10: 0 | F10: =F9-E9+D10 -> 405 | G10: 0 | H10: 0 | I10: =SUM(D10*$R$4) -> 0 | J10: =SUM(E10*$R$5) -> 0 | K10: =SUM(F10*$R$6) -> 10530 | L10: =SUM(G10*$R$7) -> 0 | M10: =SUM(H10*$R$8) -> 0 | N10: =SUM(I10:M10) -> 10530
A11: 7 | B11: 46210 | D11: 0 | F11: =F10-E10+D11 -> 405 | G11: 0 | H11: 0 | I11: =SUM(D11*$R$4) -> 0 | J11: =SUM(E11*$R$5) -> 0 | K11: =SUM(F11*$R$6) -> 10530 | L11: =SUM(G11*$R$7) -> 0 | M11: =SUM(H11*$R$8) -> 0 | N11: =SUM(I11:M11) -> 10530
A12: 8 | B12: 46211 | D12: 0 | E12: 43.5 | F12: =F11-E11+D12 -> 405 | G12: 0 | H12: 0 | I12: =SUM(D12*$R$4) -> 0 | J12: =SUM(E12*$R$5) -> 6090 | K12: =SUM(F12*$R$6) -> 10530 | L12: =SUM(G12*$R$7) -> 0 | M12: =SUM(H12*$R$8) -> 0 | N12: =SUM(I12:M12) -> 16620
A13: 9 | B13: 46212 | D13: 0 | E13: 21 | F13: =F12-E12+D13 -> 361.5 | G13: 0 | H13: 0 | I13: =SUM(D13*$R$4) -> 0 | J13: =SUM(E13*$R$5) -> 2940 | K13: =SUM(F13*$R$6) -> 9399 | L13: =SUM(G13*$R$7) -> 0 | M13: =SUM(H13*$R$8) -> 0 | N13: =SUM(I13:M13) -> 12339
A14: 10 | B14: 46213 | D14: 0 | F14: =F13-E13+D14 -> 340.5 | G14: 0 | H14: 0 | I14: =SUM(D14*$R$4) -> 0 | J14: =SUM(E14*$R$5) -> 0 | K14: =SUM(F14*$R$6) -> 8853 | L14: =SUM(G14*$R$7) -> 0 | M14: =SUM(H14*$R$8) -> 0 | N14: =SUM(I14:M14) -> 8853
A15: 11 | B15: 46214 | D15: 0 | F15: =F14-E14+D15 -> 340.5 | G15: 0 | H15: 0 | I15: =SUM(D15*$R$4) -> 0 | J15: =SUM(E15*$R$5) -> 0 | K15: =SUM(F15*$R$6) -> 8853 | L15: =SUM(G15*$R$7) -> 0 | M15: =SUM(H15*$R$8) -> 0 | N15: =SUM(I15:M15) -> 8853
A16: 12 | B16: 46215 | D16: 0 | F16: =F15-E15+D16 -> 340.5 | G16: 0 | H16: 0 | I16: =SUM(D16*$R$4) -> 0 | J16: =SUM(E16*$R$5) -> 0 | K16: =SUM(F16*$R$6) -> 8853 | L16: =SUM(G16*$R$7) -> 0 | M16: =SUM(H16*$R$8) -> 0 | N16: =SUM(I16:M16) -> 8853
A17: 13 | B17: 46216 | D17: 0 | E17: 21 | F17: =F16-E16+D17 -> 340.5 | G17: 0 | H17: 0 | I17: =SUM(D17*$R$4) -> 0 | J17: =SUM(E17*$R$5) -> 2940 | K17: =SUM(F17*$R$6) -> 8853 | L17: =SUM(G17*$R$7) -> 0 | M17: =SUM(H17*$R$8) -> 0 | N17: =SUM(I17:M17) -> 11793
A18: 14 | B18: 46217 | D18: 0 | F18: =F17-E17+D18 -> 319.5 | G18: 0 | H18: 0 | I18: =SUM(D18*$R$4) -> 0 | J18: =SUM(E18*$R$5) -> 0 | K18: =SUM(F18*$R$6) -> 8307 | L18: =SUM(G18*$R$7) -> 0 | M18: =SUM(H18*$R$8) -> 0 | N18: =SUM(I18:M18) -> 8307
A19: 15 | B19: 46218 | D19: 0 | E19: 21 | F19: =F18-E18+D19 -> 319.5 | G19: 0 | H19: 0 | I19: =SUM(D19*$R$4) -> 0 | J19: =SUM(E19*$R$5) -> 2940 | K19: =SUM(F19*$R$6) -> 8307 | L19: =SUM(G19*$R$7) -> 0 | M19: =SUM(H19*$R$8) -> 0 | N19: =SUM(I19:M19) -> 11247
A20: 16 | B20: 46219 | D20: 0 | F20: =F19-E19+D20 -> 298.5 | G20: 0 | H20: 0 | I20: =SUM(D20*$R$4) -> 0 | J20: =SUM(E20*$R$5) -> 0 | K20: =SUM(F20*$R$6) -> 7761 | L20: =SUM(G20*$R$7) -> 0 | M20: =SUM(H20*$R$8) -> 0 | N20: =SUM(I20:M20) -> 7761
A21: 17 | B21: 46220 | D21: 0 | F21: =F20-E20+D21 -> 298.5 | G21: 0 | H21: 0 | I21: =SUM(D21*$R$4) -> 0 | J21: =SUM(E21*$R$5) -> 0 | K21: =SUM(F21*$R$6) -> 7761 | L21: =SUM(G21*$R$7) -> 0 | M21: =SUM(H21*$R$8) -> 0 | N21: =SUM(I21:M21) -> 7761
A22: 18 | B22: 46221 | D22: 0 | F22: =F21-E21+D22 -> 298.5 | G22: 0 | H22: 0 | I22: =SUM(D22*$R$4) -> 0 | J22: =SUM(E22*$R$5) -> 0 | K22: =SUM(F22*$R$6) -> 7761 | L22: =SUM(G22*$R$7) -> 0 | M22: =SUM(H22*$R$8) -> 0 | N22: =SUM(I22:M22) -> 7761
A23: 19 | B23: 46222 | D23: 0 | F23: =F22-E22+D23 -> 298.5 | G23: 0 | H23: 0 | I23: =SUM(D23*$R$4) -> 0 | J23: =SUM(E23*$R$5) -> 0 | K23: =SUM(F23*$R$6) -> 7761 | L23: =SUM(G23*$R$7) -> 0 | M23: =SUM(H23*$R$8) -> 0 | N23: =SUM(I23:M23) -> 7761
A24: 20 | B24: 46223 | D24: 0 | E24: 45 | F24: =F23-E23+D24 -> 298.5 | G24: 0 | H24: 0 | I24: =SUM(D24*$R$4) -> 0 | J24: =SUM(E24*$R$5) -> 6300 | K24: =SUM(F24*$R$6) -> 7761 | L24: =SUM(G24*$R$7) -> 0 | M24: =SUM(H24*$R$8) -> 0 | N24: =SUM(I24:M24) -> 14061
A25: 21 | B25: 46224 | D25: 0 | F25: =F24-E24+D25 -> 253.5 | G25: 0 | H25: 0 | I25: =SUM(D25*$R$4) -> 0 | J25: =SUM(E25*$R$5) -> 0 | K25: =SUM(F25*$R$6) -> 6591 | L25: =SUM(G25*$R$7) -> 0 | M25: =SUM(H25*$R$8) -> 0 | N25: =SUM(I25:M25) -> 6591
A26: 22 | B26: 46225 | D26: 0 | E26: 45 | F26: =F25-E25+D26 -> 253.5 | G26: 0 | H26: 0 | I26: =SUM(D26*$R$4) -> 0 | J26: =SUM(E26*$R$5) -> 6300 | K26: =SUM(F26*$R$6) -> 6591 | L26: =SUM(G26*$R$7) -> 0 | M26: =SUM(H26*$R$8) -> 0 | N26: =SUM(I26:M26) -> 12891
A27: 23 | B27: 46226 | D27: 0 | E27: 22.5 | F27: =F26-E26+D27 -> 208.5 | G27: 0 | H27: 0 | I27: =SUM(D27*$R$4) -> 0 | J27: =SUM(E27*$R$5) -> 3150 | K27: =SUM(F27*$R$6) -> 5421 | L27: =SUM(G27*$R$7) -> 0 | M27: =SUM(H27*$R$8) -> 0 | N27: =SUM(I27:M27) -> 8571
A28: 24 | B28: 46227 | D28: 0 | F28: =F27-E27+D28 -> 186 | G28: 0 | H28: 0 | I28: =SUM(D28*$R$4) -> 0 | J28: =SUM(E28*$R$5) -> 0 | K28: =SUM(F28*$R$6) -> 4836 | L28: =SUM(G28*$R$7) -> 0 | M28: =SUM(H28*$R$8) -> 0 | N28: =SUM(I28:M28) -> 4836
A29: 25 | B29: 46228 | D29: 0 | F29: =F28-E28+D29 -> 186 | G29: 0 | H29: 0 | I29: =SUM(D29*$R$4) -> 0 | J29: =SUM(E29*$R$5) -> 0 | K29: =SUM(F29*$R$6) -> 4836 | L29: =SUM(G29*$R$7) -> 0 | M29: =SUM(H29*$R$8) -> 0 | N29: =SUM(I29:M29) -> 4836
A30: 26 | B30: 46229 | D30: 0 | F30: =F29-E29+D30 -> 186 | G30: 0 | H30: 0 | I30: =SUM(D30*$R$4) -> 0 | J30: =SUM(E30*$R$5) -> 0 | K30: =SUM(F30*$R$6) -> 4836 | L30: =SUM(G30*$R$7) -> 0 | M30: =SUM(H30*$R$8) -> 0 | N30: =SUM(I30:M30) -> 4836
A31: 27 | B31: 46230 | D31: 0 | F31: =F30-E30+D31 -> 186 | G31: 0 | H31: 0 | I31: =SUM(D31*$R$4) -> 0 | J31: =SUM(E31*$R$5) -> 0 | K31: =SUM(F31*$R$6) -> 4836 | L31: =SUM(G31*$R$7) -> 0 | M31: =SUM(H31*$R$8) -> 0 | N31: =SUM(I31:M31) -> 4836
A32: 28 | B32: 46231 | D32: 0 | F32: =F31-E31+D32 -> 186 | G32: 0 | H32: 0 | I32: =SUM(D32*$R$4) -> 0 | J32: =SUM(E32*$R$5) -> 0 | K32: =SUM(F32*$R$6) -> 4836 | L32: =SUM(G32*$R$7) -> 0 | M32: =SUM(H32*$R$8) -> 0 | N32: =SUM(I32:M32) -> 4836
A33: 29 | B33: 46232 | D33: 0 | E33: 22.5 | F33: =F32-E32+D33 -> 186 | G33: 0 | H33: 0 | I33: =SUM(D33*$R$4) -> 0 | J33: =SUM(E33*$R$5) -> 3150 | K33: =SUM(F33*$R$6) -> 4836 | L33: =SUM(G33*$R$7) -> 0 | M33: =SUM(H33*$R$8) -> 0 | N33: =SUM(I33:M33) -> 7986
A34: 30 | B34: 46233 | D34: 0 | E34: 22.5 | F34: =F33-E33+D34 -> 163.5 | G34: 0 | H34: 0 | I34: =SUM(D34*$R$4) -> 0 | J34: =SUM(E34*$R$5) -> 3150 | K34: =SUM(F34*$R$6) -> 4251 | L34: =SUM(G34*$R$7) -> 0 | M34: =SUM(H34*$R$8) -> 0 | N34: =SUM(I34:M34) -> 7401
B35: 46234 | F35: =F34-E34+D35 -> 141 | G35: 0 | H35: 0 | I35: =SUM(D35*$R$4) -> 0 | J35: =SUM(E35*$R$5) -> 0 | K35: =SUM(F35*$R$6) -> 3666 | L35: =SUM(G35*$R$7) -> 0 | M35: =SUM(H35*$R$8) -> 0 | N35: =SUM(I35:M35) -> 3666
D36: =SUM(D5:D35) -> 0 | E36: =SUM(E5:E35) -> 264 | F36: =SUM(F5:F35) -> 9231 | G36: =SUM(G5:G35) -> 0 | H36: =SUM(H5:H35) -> 0 | I36: =SUM(I5:I35) -> 0 | J36: =SUM(J5:J35) -> 36960 | K36: =SUM(K5:K35) -> 240006 | ... N36: =SUM(N5:N35) -> 276966
N37: =N36*1.22 -> 337898.52

Sheet Приоритет Казань_Автосервисная
A1: =N37 -> 0
A2: ="Отчет по хранению товара за " & TEXT(B5,"ММММ ГГГГ") -> Отчет по хранению товара за Июль 2026 | I2: Казань_Автосервисная
A3: № | B3: дата | D3: Выгрузка кол-во | E3: Загрузка кол-во | F3: Хранение | G3: переконсолидация (тонн) | H3: Паллетирование | I3: стоимость выгрузки | J3: стоимость загрузки | K3: стоимость хранения | L3: стоимость переконс. | M3: Стоимость паллетирования | N3: итого | Q3: Цены
Q4: Выгрузка | R4: 144
A5: 1 | B5: 46204 | F5: 0 | G5: 0 | H5: 0 | I5: =SUM(D5*$R$4) -> 0 | J5: =SUM(E5*$R$5) -> 0 | K5: =SUM(F5*$R$6) -> 0 | L5: =SUM(G5*$R$7) -> 0 | M5: =SUM(H5*$R$8) -> 0 | N5: =SUM(I5:M5) -> 0 | Q5: Загрузка | R5: 144
A6: 2 | B6: 46205 | F6: =F5+D6-E5 -> 0 | G6: 0 | H6: 0 | I6: =SUM(D6*$R$4) -> 0 | J6: =SUM(E6*$R$5) -> 0 | K6: =SUM(F6*$R$6) -> 0 | L6: =SUM(G6*$R$7) -> 0 | M6: =SUM(H6*$R$8) -> 0 | N6: =SUM(I6:M6) -> 0 | Q6: Хранение | R6: 42
A7: 3 | B7: 46206 | F7: =F6+D7-E6 -> 0 | G7: 0 | H7: 0 | I7: =SUM(D7*$R$4) -> 0 | J7: =SUM(E7*$R$5) -> 0 | K7: =SUM(F7*$R$6) -> 0 | L7: =SUM(G7*$R$7) -> 0 | M7: =SUM(H7*$R$8) -> 0 | N7: =SUM(I7:M7) -> 0 | Q7: Переконсолидация | R7: 1200
A8: 4 | B8: 46207 | F8: =F7+D8-E7 -> 0 | G8: 0 | H8: 0 | I8: =SUM(D8*$R$4) -> 0 | J8: =SUM(E8*$R$5) -> 0 | K8: =SUM(F8*$R$6) -> 0 | L8: =SUM(G8*$R$7) -> 0 | M8: =SUM(H8*$R$8) -> 0 | N8: =SUM(I8:M8) -> 0 | Q8: Паллетирование | R8: 240
A9: 5 | B9: 46208 | F9: =F8+D9-E8 -> 0 | G9: 0 | H9: 0 | I9: =SUM(D9*$R$4) -> 0 | J9: =SUM(E9*$R$5) -> 0 | K9: =SUM(F9*$R$6) -> 0 | L9: =SUM(G9*$R$7) -> 0 | M9: =SUM(H9*$R$8) -> 0 | N9: =SUM(I9:M9) -> 0
A10: 6 | B10: 46209 | F10: =F9+D10-E9 -> 0 | G10: 0 | H10: 0 | I10: =SUM(D10*$R$4) -> 0 | J10: =SUM(E10*$R$5) -> 0 | K10: =SUM(F10*$R$6) -> 0 | L10: =SUM(G10*$R$7) -> 0 | M10: =SUM(H10*$R$8) -> 0 | N10: =SUM(I10:M10) -> 0
A11: 7 | B11: 46210 | F11: =F10+D11-E10 -> 0 | G11: 0 | H11: 0 | I11: =SUM(D11*$R$4) -> 0 | J11: =SUM(E11*$R$5) -> 0 | K11: =SUM(F11*$R$6) -> 0 | L11: =SUM(G11*$R$7) -> 0 | M11: =SUM(H11*$R$8) -> 0 | N11: =SUM(I11:M11) -> 0
A12: 8 | B12: 46211 | F12: =F11+D12-E11 -> 0 | G12: 0 | H12: 0 | I12: =SUM(D12*$R$4) -> 0 | J12: =SUM(E12*$R$5) -> 0 | K12: =SUM(F12*$R$6) -> 0 | L12: =SUM(G12*$R$7) -> 0 | M12: =SUM(H12*$R$8) -> 0 | N12: =SUM(I12:M12) -> 0
A13: 9 | B13: 46212 | F13: =F12+D13-E12 -> 0 | G13: 0 | H13: 0 | I13: =SUM(D13*$R$4) -> 0 | J13: =SUM(E13*$R$5) -> 0 | K13: =SUM(F13*$R$6) -> 0 | L13: =SUM(G13*$R$7) -> 0 | M13: =SUM(H13*$R$8) -> 0 | N13: =SUM(I13:M13) -> 0
A14: 10 | B14: 46213 | F14: =F13+D14-E13 -> 0 | G14: 0 | H14: 0 | I14: =SUM(D14*$R$4) -> 0 | J14: =SUM(E14*$R$5) -> 0 | K14: =SUM(F14*$R$6) -> 0 | L14: =SUM(G14*$R$7) -> 0 | M14: =SUM(H14*$R$8) -> 0 | N14: =SUM(I14:M14) -> 0
A15: 11 | B15: 46214 | F15: =F14+D15-E14 -> 0 | G15: 0 | H15: 0 | I15: =SUM(D15*$R$4) -> 0 | J15: =SUM(E15*$R$5) -> 0 | K15: =SUM(F15*$R$6) -> 0 | L15: =SUM(G15*$R$7) -> 0 | M15: =SUM(H15*$R$8) -> 0 | N15: =SUM(I15:M15) -> 0
A16: 12 | B16: 46215 | F16: =F15+D16-E15 -> 0 | G16: 0 | H16: 0 | I16: =SUM(D16*$R$4) -> 0 | J16: =SUM(E16*$R$5) -> 0 | K16: =SUM(F16*$R$6) -> 0 | L16: =SUM(G16*$R$7) -> 0 | M16: =SUM(H16*$R$8) -> 0 | N16: =SUM(I16:M16) -> 0
A17: 13 | B17: 46216 | F17: =F16+D17-E16 -> 0 | G17: 0 | H17: 0 | I17: =SUM(D17*$R$4) -> 0 | J17: =SUM(E17*$R$5) -> 0 | K17: =SUM(F17*$R$6) -> 0 | L17: =SUM(G17*$R$7) -> 0 | M17: =SUM(H17*$R$8) -> 0 | N17: =SUM(I17:M17) -> 0
A18: 14 | B18: 46217 | F18: =F17+D18-E17 -> 0 | G18: 0 | H18: 0 | I18: =SUM(D18*$R$4) -> 0 | J18: =SUM(E18*$R$5) -> 0 | K18: =SUM(F18*$R$6) -> 0 | L18: =SUM(G18*$R$7) -> 0 | M18: =SUM(H18*$R$8) -> 0 | N18: =SUM(I18:M18) -> 0
A19: 15 | B19: 46218 | F19: =F18+D19-E18 -> 0 | G19: 0 | H19: 0 | I19: =SUM(D19*$R$4) -> 0 | J19: =SUM(E19*$R$5) -> 0 | K19: =SUM(F19*$R$6) -> 0 | L19: =SUM(G19*$R$7) -> 0 | M19: =SUM(H19*$R$8) -> 0 | N19: =SUM(I19:M19) -> 0
A20: 16 | B20: 46219 | F20: =F19+D20-E19 -> 0 | G20: 0 | H20: 0 | I20: =SUM(D20*$R$4) -> 0 | J20: =SUM(E20*$R$5) -> 0 | K20: =SUM(F20*$R$6) -> 0 | L20: =SUM(G20*$R$7) -> 0 | M20: =SUM(H20*$R$8) -> 0 | N20: =SUM(I20:M20) -> 0
... A34: 30 | B34: 46233 | F34: =F33+D34-E33 -> 0 | G34: 0 | H34: 0 | I34: =SUM(D34*$R$4) -> 0 | J34: =SUM(E34*$R$5) -> 0 | K34: =SUM(F34*$R$6) -> 0 | L34: =SUM(G34*$R$7) -> 0 | M34: =SUM(H34*$R$8) -> 0 | N34: =SUM(I34:M34) -> 0
A35: 31 | G35: 0 | H35: 0 | I35: =SUM(D35*$R$4) -> 0 | J35: =SUM(E35*$R$5) -> 0 | K35: =SUM(F35*$R$6) -> 0 | L35: =SUM(G35*$R$7) -> 0 | M35: =SUM(H35*$R$8) -> 0 | N35: =SUM(I35:M35) -> 0
D36: =SUM(D5:D35) -> 0 | E36: =SUM(E5:E35) -> 0 | F36: =SUM(F5:F35) -> 0 | G36: =SUM(G5:G35) -> 0 | H36: =SUM(H5:H35) -> 0 | I36: =SUM(I5:I35) -> 0 | J36: =SUM(J5:J35) -> 0 | K36: =SUM(K5:K35) -> 0 | ... N36: =SUM(N5:N35) -> 0
N37: =N36*1.22 -> 0

Sheet Приоритет Казань_Приволжская
A1: =N37 -> 0
A2: ="Отчет по хранению товара за " & TEXT(B5,"ММММ ГГГГ") -> Отчет по хранению товара за Июль 2026 | I2: Казань_Приволжская
A3: № | B3: дата | D3: Выгрузка кол-во | E3: Загрузка кол-во | F3: Хранение | G3: переконсолидация (тонн) | H3: Паллетирование | I3: стоимость выгрузки | J3: стоимость загрузки | K3: стоимость хранения | L3: стоимость переконс. | M3: Стоимость паллетирования | N3: итого | Q3: Цены
Q4: Выгрузка | R4: 140
A5: 1 | B5: 46204 | F5: 0 | G5: 0 | H5: 0 | I5: =SUM(D5*$R$4) -> 0 | J5: =SUM(E5*$R$5) -> 0 | K5: =SUM(F5*$R$6) -> 0 | L5: =SUM(G5*$R$7) -> 0 | M5: =SUM(H5*$R$8) -> 0 | N5: =SUM(I5:M5) -> 0 | Q5: Загрузка | R5: 140
A6: 2 | B6: 46205 | F6: =F5+D6-E5 -> 0 | G6: 0 | H6: 0 | I6: =SUM(D6*$R$4) -> 0 | J6: =SUM(E6*$R$5) -> 0 | K6: =SUM(F6*$R$6) -> 0 | L6: =SUM(G6*$R$7) -> 0 | M6: =SUM(H6*$R$8) -> 0 | N6: =SUM(I6:M6) -> 0 | Q6: Хранение | R6: 34
A7: 3 | B7: 46206 | F7: =F6+D7-E6 -> 0 | G7: 0 | H7: 0 | I7: =SUM(D7*$R$4) -> 0 | J7: =SUM(E7*$R$5) -> 0 | K7: =SUM(F7*$R$6) -> 0 | L7: =SUM(G7*$R$7) -> 0 | M7: =SUM(H7*$R$8) -> 0 | N7: =SUM(I7:M7) -> 0 | Q7: Переконсолидация | R7: 1200
A8: 4 | B8: 46207 | F8: =F7+D8-E7 -> 0 | G8: 0 | H8: 0 | I8: =SUM(D8*$R$4) -> 0 | J8: =SUM(E8*$R$5) -> 0 | K8: =SUM(F8*$R$6) -> 0 | L8: =SUM(G8*$R$7) -> 0 | M8: =SUM(H8*$R$8) -> 0 | N8: =SUM(I8:M8) -> 0 | Q8: Паллетирование | R8: 240
A9: 5 | B9: 46208 | F9: =F8+D9-E8 -> 0 | G9: 0 | H9: 0 | I9: =SUM(D9*$R$4) -> 0 | J9: =SUM(E9*$R$5) -> 0 | K9: =SUM(F9*$R$6) -> 0 | L9: =SUM(G9*$R$7) -> 0 | M9: =SUM(H9*$R$8) -> 0 | N9: =SUM(I9:M9) -> 0
A10: 6 | B10: 46209 | F10: =F9+D10-E9 -> 0 | G10: 0 | H10: 0 | I10: =SUM(D10*$R$4) -> 0 | J10: =SUM(E10*$R$5) -> 0 | K10: =SUM(F10*$R$6) -> 0 | L10: =SUM(G10*$R$7) -> 0 | M10: =SUM(H10*$R$8) -> 0 | N10: =SUM(I10:M10) -> 0
A11: 7 | B11: 46210 | F11: =F10+D11-E10 -> 0 | G11: 0 | H11: 0 | I11: =SUM(D11*$R$4) -> 0 | J11: =SUM(E11*$R$5) -> 0 | K11: =SUM(F11*$R$6) -> 0 | L11: =SUM(G11*$R$7) -> 0 | M11: =SUM(H11*$R$8) -> 0 | N11: =SUM(I11:M11) -> 0
A12: 8 | B12: 46211 | F12: =F11+D12-E11 -> 0 | G12: 0 | H12: 0 | I12: =SUM(D12*$R$4) -> 0 | J12: =SUM(E12*$R$5) -> 0 | K12: =SUM(F12*$R$6) -> 0 | L12: =SUM(G12*$R$7) -> 0 | M12: =SUM(H12*$R$8) -> 0 | N12: =SUM(I12:M12) -> 0
A13: 9 | B13: 46212 | F13: =F12+D13-E12 -> 0 | G13: 0 | H13: 0 | I13: =SUM(D13*$R$4) -> 0 | J13: =SUM(E13*$R$5) -> 0 | K13: =SUM(F13*$R$6) -> 0 | L13: =SUM(G13*$R$7) -> 0 | M13: =SUM(H13*$R$8) -> 0 | N13: =SUM(I13:M13) -> 0
A14: 10 | B14: 46213 | F14: =F13+D14-E13 -> 0 | G14: 0 | H14: 0 | I14: =SUM(D14*$R$4) -> 0 | J14: =SUM(E14*$R$5) -> 0 | K14: =SUM(F14*$R$6) -> 0 | L14: =SUM(G14*$R$7) -> 0 | M14: =SUM(H14*$R$8) -> 0 | N14: =SUM(I14:M14) -> 0
A15: 11 | B15: 46214 | F15: =F14+D15-E14 -> 0 | G15: 0 | H15: 0 | I15: =SUM(D15*$R$4) -> 0 | J15: =SUM(E15*$R$5) -> 0 | K15: =SUM(F15*$R$6) -> 0 | L15: =SUM(G15*$R$7) -> 0 | M15: =SUM(H15*$R$8) -> 0 | N15: =SUM(I15:M15) -> 0
A16: 12 | B16: 46215 | F16: =F15+D16-E15 -> 0 | G16: 0 | H16: 0 | I16: =SUM(D16*$R$4) -> 0 | J16: =SUM(E16*$R$5) -> 0 | K16: =SUM(F16*$R$6) -> 0 | L16: =SUM(G16*$R$7) -> 0 | M16: =SUM(H16*$R$8) -> 0 | N16: =SUM(I16:M16) -> 0
A17: 13 | B17: 46216 | F17: =F16+D17-E16 -> 0 | G17: 0 | H17: 0 | I17: =SUM(D17*$R$4) -> 0 | J17: =SUM(E17*$R$5) -> 0 | K17: =SUM(F17*$R$6) -> 0 | L17: =SUM(G17*$R$7) -> 0 | M17: =SUM(H17*$R$8) -> 0 | N17: =SUM(I17:M17) -> 0
A18: 14 | B18: 46217 | F18: =F17+D18-E17 -> 0 | G18: 0 | H18: 0 | I18: =SUM(D18*$R$4) -> 0 | J18: =SUM(E18*$R$5) -> 0 | K18: =SUM(F18*$R$6) -> 0 | L18: =SUM(G18*$R$7) -> 0 | M18: =SUM(H18*$R$8) -> 0 | N18: =SUM(I18:M18) -> 0
A19: 15 | B19: 46218 | F19: =F18+D19-E18 -> 0 | G19: 0 | H19: 0 | I19: =SUM(D19*$R$4) -> 0 | J19: =SUM(E19*$R$5) -> 0 | K19: =SUM(F19*$R$6) -> 0 | L19: =SUM(G19*$R$7) -> 0 | M19: =SUM(H19*$R$8) -> 0 | N19: =SUM(I19:M19) -> 0
A20: 16 | B20: 46219 | F20: =F19+D20-E19 -> 0 | G20: 0 | H20: 0 | I20: =SUM(D20*$R$4) -> 0 | J20: =SUM(E20*$R$5) -> 0 | K20: =SUM(F20*$R$6) -> 0 | L20: =SUM(G20*$R$7) -> 0 | M20: =SUM(H20*$R$8) -> 0 | N20: =SUM(I20:M20) -> 0
... A35: 31 | B35: 46234 | F35: =F34+D35-E34 -> 0 | G35: 0 | H35: 0 | I35: =SUM(D35*$R$4) -> 0 | J35: =SUM(E35*$R$5) -> 0 | K35: =SUM(F35*$R$6) -> 0 | L35: =SUM(G35*$R$7) -> 0 | M35: =SUM(H35*$R$8) -> 0 | N35: =SUM(I35:M35) -> 0
D36: =SUM(D5:D35) -> 0 | E36: =SUM(E5:E35) -> 0 | F36: =SUM(F5:F35) -> 0 | G36: =SUM(G5:G35) -> 0 | H36: =SUM(H5:H35) -> 0 | I36: =SUM(I5:I35) -> 0 | J36: =SUM(J5:J35) -> 0 | K36: =SUM(K5:K35) -> 0 | ... N36: =SUM(N5:N35) -> 0
N37: =N36*1.22 -> 0

Sheet Приоритет Зеленодольск
A1: =N37 -> 0
A2: ="Отчет по хранению товара за " & TEXT(B5,"ММММ ГГГГ") -> Отчет по хранению товара за Июль 2026 | I2: Зеленодольск
A3: № | B3: дата | D3: Выгрузка кол-во | E3: Загрузка кол-во | F3: Хранение | G3: переконсолидация (тонн) | H3: Паллетирование | I3: стоимость выгрузки | J3: стоимость загрузки | K3: стоимость хранения | L3: стоимость переконс. | M3: Стоимость паллетирования | N3: итого | Q3: Цены
Q4: Выгрузка | R4: 120
A5: 1 | B5: 46204 | F5: 0 | G5: 0 | H5: 0 | I5: =SUM(D5*$R$4) -> 0 | J5: =SUM(E5*$R$5) -> 0 | K5: =SUM(F5*$R$6) -> 0 | L5: =SUM(G5*$R$7) -> 0 | M5: =SUM(H5*$R$8) -> 0 | N5: =SUM(I5:M5) -> 0 | Q5: Загрузка | R5: 120
A6: 2 | B6: 46205 | F6: =F5+D6-E5 -> 0 | G6: 0 | H6: 0 | I6: =SUM(D6*$R$4) -> 0 | J6: =SUM(E6*$R$5) -> 0 | K6: =SUM(F6*$R$6) -> 0 | L6: =SUM(G6*$R$7) -> 0 | M6: =SUM(H6*$R$8) -> 0 | N6: =SUM(I6:M6) -> 0 | Q6: Хранение | R6: 18
A7: 3 | B7: 46206 | F7: =F6+D7-E6 -> 0 | G7: 0 | H7: 0 | I7: =SUM(D7*$R$4) -> 0 | J7: =SUM(E7*$R$5) -> 0 | K7: =SUM(F7*$R$6) -> 0 | L7: =SUM(G7*$R$7) -> 0 | M7: =SUM(H7*$R$8) -> 0 | N7: =SUM(I7:M7) -> 0 | Q7: Переконсолидация | R7: 950
A8: 4 | B8: 46207 | F8: =F7+D8-E7 -> 0 | G8: 0 | H8: 0 | I8: =SUM(D8*$R$4) -> 0 | J8: =SUM(E8*$R$5) -> 0 | K8: =SUM(F8*$R$6) -> 0 | L8: =SUM(G8*$R$7) -> 0 | M8: =SUM(H8*$R$8) -> 0 | N8: =SUM(I8:M8) -> 0 | Q8: Паллетирование | R8: 120
A9: 5 | B9: 46208 | F9: =F8+D9-E8 -> 0 | G9: 0 | H9: 0 | I9: =SUM(D9*$R$4) -> 0 | J9: =SUM(E9*$R$5) -> 0 | K9: =SUM(F9*$R$6) -> 0 | L9: =SUM(G9*$R$7) -> 0 | M9: =SUM(H9*$R$8) -> 0 | N9: =SUM(I9:M9) -> 0
A10: 6 | B10: 46209 | F10: =F9+D10-E9 -> 0 | G10: 0 | H10: 0 | I10: =SUM(D10*$R$4) -> 0 | J10: =SUM(E10*$R$5) -> 0 | K10: =SUM(F10*$R$6) -> 0 | L10: =SUM(G10*$R$7) -> 0 | M10: =SUM(H10*$R$8) -> 0 | N10: =SUM(I10:M10) -> 0
A11: 7 | B11: 46210 | F11: =F10+D11-E10 -> 0 | G11: 0 | H11: 0 | I11: =SUM(D11*$R$4) -> 0 | J11: =SUM(E11*$R$5) -> 0 | K11: =SUM(F11*$R$6) -> 0 | L11: =SUM(G11*$R$7) -> 0 | M11: =SUM(H11*$R$8) -> 0 | N11: =SUM(I11:M11) -> 0
A12: 8 | B12: 46211 | F12: =F11+D12-E11 -> 0 | G12: 0 | H12: 0 | I12: =SUM(D12*$R$4) -> 0 | J12: =SUM(E12*$R$5) -> 0 | K12: =SUM(F12*$R$6) -> 0 | L12: =SUM(G12*$R$7) -> 0 | M12: =SUM(H12*$R$8) -> 0 | N12: =SUM(I12:M12) -> 0
A13: 9 | B13: 46212 | F13: =F12+D13-E12 -> 0 | G13: 0 | H13: 0 | I13: =SUM(D13*$R$4) -> 0 | J13: =SUM(E13*$R$5) -> 0 | K13: =SUM(F13*$R$6) -> 0 | L13: =SUM(G13*$R$7) -> 0 | M13: =SUM(H13*$R$8) -> 0 | N13: =SUM(I13:M13) -> 0
A14: 10 | B14: 46213 | F14: =F13+D14-E13 -> 0 | G14: 0 | H14: 0 | I14: =SUM(D14*$R$4) -> 0 | J14: =SUM(E14*$R$5) -> 0 | K14: =SUM(F14*$R$6) -> 0 | L14: =SUM(G14*$R$7) -> 0 | M14: =SUM(H14*$R$8) -> 0 | N14: =SUM(I14:M14) -> 0
A15: 11 | B15: 46214 | F15: =F14+D15-E14 -> 0 | G15: 0 | H15: 0 | I15: =SUM(D15*$R$4) -> 0 | J15: =SUM(E15*$R$5) -> 0 | K15: =SUM(F15*$R$6) -> 0 | L15: =SUM(G15*$R$7) -> 0 | M15: =SUM(H15*$R$8) -> 0 | N15: =SUM(I15:M15) -> 0
A16: 12 | B16: 46215 | F16: =F15+D16-E15 -> 0 | G16: 0 | H16: 0 | I16: =SUM(D16*$R$4) -> 0 | J16: =SUM(E16*$R$5) -> 0 | K16: =SUM(F16*$R$6) -> 0 | L16: =SUM(G16*$R$7) -> 0 | M16: =SUM(H16*$R$8) -> 0 | N16: =SUM(I16:M16) -> 0
A17: 13 | B17: 46216 | F17: =F16+D17-E16 -> 0 | G17: 0 | H17: 0 | I17: =SUM(D17*$R$4) -> 0 | J17: =SUM(E17*$R$5) -> 0 | K17: =SUM(F17*$R$6) -> 0 | L17: =SUM(G17*$R$7) -> 0 | M17: =SUM(H17*$R$8) -> 0 | N17: =SUM(I17:M17) -> 0
A18: 14 | B18: 46217 | F18: =F17+D18-E17 -> 0 | G18: 0 | H18: 0 | I18: =SUM(D18*$R$4) -> 0 | J18: =SUM(E18*$R$5) -> 0 | K18: =SUM(F18*$R$6) -> 0 | L18: =SUM(G18*$R$7) -> 0 | M18: =SUM(H18*$R$8) -> 0 | N18: =SUM(I18:M18) -> 0
A19: 15 | B19: 46218 | F19: =F18+D19-E18 -> 0 | G19: 0 | H19: 0 | I19: =SUM(D19*$R$4) -> 0 | J19: =SUM(E19*$R$5) -> 0 | K19: =SUM(F19*$R$6) -> 0 | L19: =SUM(G19*$R$7) -> 0 | M19: =SUM(H19*$R$8) -> 0 | N19: =SUM(I19:M19) -> 0
A20: 16 | B20: 46219 | F20: =F19+D20-E19 -> 0 | G20: 0 | H20: 0 | I20: =SUM(D20*$R$4) -> 0 | J20: =SUM(E20*$R$5) -> 0 | K20: =SUM(F20*$R$6) -> 0 | L20: =SUM(G20*$R$7) -> 0 | M20: =SUM(H20*$R$8) -> 0 | N20: =SUM(I20:M20) -> 0
... A35: 31 | B35: 46234 | F35: =F34+D35-E34 -> 0 | G35: 0 | H35: 0 | I35: =SUM(D35*$R$4) -> 0 | J35: =SUM(E35*$R$5) -> 0 | K35: =SUM(F35*$R$6) -> 0 | L35: =SUM(G35*$R$7) -> 0 | M35: =SUM(H35*$R$8) -> 0 | N35: =SUM(I35:M35) -> 0
D36: =SUM(D5:D35) -> 0 | E36: =SUM(E5:E35) -> 0 | F36: =SUM(F5:F35) -> 0 | G36: =SUM(G5:G35) -> 0 | H36: =SUM(H5:H35) -> 0 | I36: =SUM(I5:I35) -> 0 | J36: =SUM(J5:J35) -> 0 | K36: =SUM(K5:K35) -> 0 | ... N36: =SUM(N5:N35) -> 0
N37: =N36*1.22 -> 0

Sheet Приоритет Екатеринбург
A1: =N37 -> 0
A2: ="Отчет по хранению товара за " & TEXT(B5,"ММММ ГГГГ") -> Отчет по хранению товара за Июль 2026 | I2: Екатеринбург
A3: № | B3: дата | D3: Выгрузка кол-во | E3: Загрузка кол-во | F3: Хранение | G3: переконсолидация (тонн) | H3: Паллетирование | I3: стоимость выгрузки | J3: стоимость загрузки | K3: стоимость хранения | L3: стоимость переконс. | M3: Стоимость паллетирования | N3: итого | Q3: Цены
Q4: Выгрузка | R4: 140
A5: 1 | B5: 46204 | F5: 0 | G5: 0 | H5: 0 | I5: =SUM(D5*$R$4) -> 0 | J5: =SUM(E5*$R$5) -> 0 | K5: =SUM(F5*$R$6) -> 0 | L5: =SUM(G5*$R$7) -> 0 | M5: =SUM(H5*$R$8) -> 0 | N5: =SUM(I5:M5) -> 0 | Q5: Загрузка | R5: 140
A6: 2 | B6: 46205 | F6: =F5+D6-E5 -> 0 | G6: 0 | H6: 0 | I6: =SUM(D6*$R$4) -> 0 | J6: =SUM(E6*$R$5) -> 0 | K6: =SUM(F6*$R$6) -> 0 | L6: =SUM(G6*$R$7) -> 0 | M6: =SUM(H6*$R$8) -> 0 | N6: =SUM(I6:M6) -> 0 | Q6: Хранение | R6: 20
A7: 3 | B7: 46206 | F7: =F6+D7-E6 -> 0 | G7: 0 | H7: 0 | I7: =SUM(D7*$R$4) -> 0 | J7: =SUM(E7*$R$5) -> 0 | K7: =SUM(F7*$R$6) -> 0 | L7: =SUM(G7*$R$7) -> 0 | M7: =SUM(H7*$R$8) -> 0 | N7: =SUM(I7:M7) -> 0 | Q7: Переконсолидация | R7: 950
A8: 4 | B8: 46207 | F8: =F7+D8-E7 -> 0 | G8: 0 | H8: 0 | I8: =SUM(D8*$R$4) -> 0 | J8: =SUM(E8*$R$5) -> 0 | K8: =SUM(F8*$R$6) -> 0 | L8: =SUM(G8*$R$7) -> 0 | M8: =SUM(H8*$R$8) -> 0 | N8: =SUM(I8:M8) -> 0 | Q8: Паллетирование | R8: 120
A9: 5 | B9: 46208 | F9: =F8+D9-E8 -> 0 | G9: 0 | H9: 0 | I9: =SUM(D9*$R$4) -> 0 | J9: =SUM(E9*$R$5) -> 0 | K9: =SUM(F9*$R$6) -> 0 | L9: =SUM(G9*$R$7) -> 0 | M9: =SUM(H9*$R$8) -> 0 | N9: =SUM(I9:M9) -> 0
A10: 6 | B10: 46209 | F10: =F9+D10-E9 -> 0 | G10: 0 | H10: 0 | I10: =SUM(D10*$R$4) -> 0 | J10: =SUM(E10*$R$5) -> 0 | K10: =SUM(F10*$R$6) -> 0 | L10: =SUM(G10*$R$7) -> 0 | M10: =SUM(H10*$R$8) -> 0 | N10: =SUM(I10:M10) -> 0
A11: 7 | B11: 46210 | F11: =F10+D11-E10 -> 0 | G11: 0 | H11: 0 | I11: =SUM(D11*$R$4) -> 0 | J11: =SUM(E11*$R$5) -> 0 | K11: =SUM(F11*$R$6) -> 0 | L11: =SUM(G11*$R$7) -> 0 | M11: =SUM(H11*$R$8) -> 0 | N11: =SUM(I11:M11) -> 0
A12: 8 | B12: 46211 | F12: =F11+D12-E11 -> 0 | G12: 0 | H12: 0 | I12: =SUM(D12*$R$4) -> 0 | J12: =SUM(E12*$R$5) -> 0 | K12: =SUM(F12*$R$6) -> 0 | L12: =SUM(G12*$R$7) -> 0 | M12: =SUM(H12*$R$8) -> 0 | N12: =SUM(I12:M12) -> 0
A13: 9 | B13: 46212 | F13: =F12+D13-E12 -> 0 | G13: 0 | H13: 0 | I13: =SUM(D13*$R$4) -> 0 | J13: =SUM(E13*$R$5) -> 0 | K13: =SUM(F13*$R$6) -> 0 | L13: =SUM(G13*$R$7) -> 0 | M13: =SUM(H13*$R$8) -> 0 | N13: =SUM(I13:M13) -> 0
A14: 10 | B14: 46213 | F14: =F13+D14-E13 -> 0 | G14: 0 | H14: 0 | I14: =SUM(D14*$R$4) -> 0 | J14: =SUM(E14*$R$5) -> 0 | K14: =SUM(F14*$R$6) -> 0 | L14: =SUM(G14*$R$7) -> 0 | M14: =SUM(H14*$R$8) -> 0 | N14: =SUM(I14:M14) -> 0
A15: 11 | B15: 46214 | F15: =F14+D15-E14 -> 0 | G15: 0 | H15: 0 | I15: =SUM(D15*$R$4) -> 0 | J15: =SUM(E15*$R$5) -> 0 | K15: =SUM(F15*$R$6) -> 0 | L15: =SUM(G15*$R$7) -> 0 | M15: =SUM(H15*$R$8) -> 0 | N15: =SUM(I15:M15) -> 0
A16: 12 | B16: 46215 | F16: =F15+D16-E15 -> 0 | G16: 0 | H16: 0 | I16: =SUM(D16*$R$4) -> 0 | J16: =SUM(E16*$R$5) -> 0 | K16: =SUM(F16*$R$6) -> 0 | L16: =SUM(G16*$R$7) -> 0 | M16: =SUM(H16*$R$8) -> 0 | N16: =SUM(I16:M16) -> 0
A17: 13 | B17: 46216 | F17: =F16+D17-E16 -> 0 | G17: 0 | H17: 0 | I17: =SUM(D17*$R$4) -> 0 | J17: =SUM(E17*$R$5) -> 0 | K17: =SUM(F17*$R$6) -> 0 | L17: =SUM(G17*$R$7) -> 0 | M17: =SUM(H17*$R$8) -> 0 | N17: =SUM(I17:M17) -> 0
A18: 14 | B18: 46217 | F18: =F17+D18-E17 -> 0 | G18: 0 | H18: 0 | I18: =SUM(D18*$R$4) -> 0 | J18: =SUM(E18*$R$5) -> 0 | K18: =SUM(F18*$R$6) -> 0 | L18: =SUM(G18*$R$7) -> 0 | M18: =SUM(H18*$R$8) -> 0 | N18: =SUM(I18:M18) -> 0
A19: 15 | B19: 46218 | F19: =F18+D19-E18 -> 0 | G19: 0 | H19: 0 | I19: =SUM(D19*$R$4) -> 0 | J19: =SUM(E19*$R$5) -> 0 | K19: =SUM(F19*$R$6) -> 0 | L19: =SUM(G19*$R$7) -> 0 | M19: =SUM(H19*$R$8) -> 0 | N19: =SUM(I19:M19) -> 0
A20: 16 | B20: 46219 | F20: =F19+D20-E19 -> 0 | G20: 0 | H20: 0 | I20: =SUM(D20*$R$4) -> 0 | J20: =SUM(E20*$R$5) -> 0 | K20: =SUM(F20*$R$6) -> 0 | L20: =SUM(G20*$R$7) -> 0 | M20: =SUM(H20*$R$8) -> 0 | N20: =SUM(I20:M20) -> 0
... A34: 30 | B34: 46233 | F34: =F33+D34-E33 -> 0 | G34: 0 | H34: 0 | I34: =SUM(D34*$R$4) -> 0 | J34: =SUM(E34*$R$5) -> 0 | K34: =SUM(F34*$R$6) -> 0 | L34: =SUM(G34*$R$7) -> 0 | M34: =SUM(H34*$R$8) -> 0 | N34: =SUM(I34:M34) -> 0
A35: 31 | F35: =F34+D35-E34 -> 0 | G35: 0 | H35: 0 | I35: =SUM(D35*$R$4) -> 0 | J35: =SUM(E35*$R$5) -> 0 | K35: =SUM(F35*$R$6) -> 0 | L35: =SUM(G35*$R$7) -> 0 | M35: =SUM(H35*$R$8) -> 0 | N35: =SUM(I35:M35) -> 0
D36: =SUM(D5:D35) -> 0 | E36: =SUM(E5:E35) -> 0 | F36: =SUM(F5:F35) -> 0 | G36: =SUM(G5:G35) -> 0 | H36: =SUM(H5:H35) -> 0 | I36: =SUM(I5:I35) -> 0 | J36: =SUM(J5:J35) -> 0 | K36: =SUM(K5:K35) -> 0 | ... N36: =SUM(N5:N35) -> 0
N37: =N36*1.22 -> 0

Sheet Приоритет Новикова-Прибоя
A1: =N37 -> 76585.5
A2: ="Отчет по хранению товара за " & TEXT(B5,"ММММ ГГГГ") -> Отчет по хранению товара за Июль 2026 | I2: Новикова
A3: № | B3: дата | D3: Выгрузка кол-во | E3: Загрузка кол-во | F3: Хранение | G3: переконсолидация (тонн) | H3: Паллетирование | I3: стоимость выгрузки | J3: стоимость загрузки | K3: стоимость хранения | L3: стоимость переконс. | M3: Стоимость паллетирования | N3: итого | Q3: Цены
Q4: Выгрузка | R4: 120
A5: 1 | B5: 46204 | F5: 112.5 | G5: 0 | H5: 0 | I5: =SUM(D5*$R$4) -> 0 | J5: =SUM(E5*$R$5) -> 0 | K5: =SUM(F5*$R$6) -> 2025 | L5: =SUM(G5*$R$7) -> 0 | M5: =SUM(H5*$R$8) -> 0 | N5: =SUM(I5:M5) -> 2025 | Q5: Загрузка | R5: 120
A6: 2 | B6: 46205 | F6: =F5+D6-E5 -> 112.5 | G6: 0 | H6: 0 | I6: =SUM(D6*$R$4) -> 0 | J6: =SUM(E6*$R$5) -> 0 | K6: =SUM(F6*$R$6) -> 2025 | L6: =SUM(G6*$R$7) -> 0 | M6: =SUM(H6*$R$8) -> 0 | N6: =SUM(I6:M6) -> 2025 | Q6: Хранение | R6: 18
A7: 3 | B7: 46206 | F7: =F6+D7-E6 -> 112.5 | G7: 0 | H7: 0 | I7: =SUM(D7*$R$4) -> 0 | J7: =SUM(E7*$R$5) -> 0 | K7: =SUM(F7*$R$6) -> 2025 | L7: =SUM(G7*$R$7) -> 0 | M7: =SUM(H7*$R$8) -> 0 | N7: =SUM(I7:M7) -> 2025 | Q7: Переконсолидация | R7: 950
A8: 4 | B8: 46207 | F8: =F7+D8-E7 -> 112.5 | G8: 0 | H8: 0 | I8: =SUM(D8*$R$4) -> 0 | J8: =SUM(E8*$R$5) -> 0 | K8: =SUM(F8*$R$6) -> 2025 | L8: =SUM(G8*$R$7) -> 0 | M8: =SUM(H8*$R$8) -> 0 | N8: =SUM(I8:M8) -> 2025 | Q8: Паллетирование | R8: 120
A9: 5 | B9: 46208 | F9: =F8+D9-E8 -> 112.5 | G9: 0 | H9: 0 | I9: =SUM(D9*$R$4) -> 0 | J9: =SUM(E9*$R$5) -> 0 | K9: =SUM(F9*$R$6) -> 2025 | L9: =SUM(G9*$R$7) -> 0 | M9: =SUM(H9*$R$8) -> 0 | N9: =SUM(I9:M9) -> 2025
A10: 6 | B10: 46209 | F10: =F9+D10-E9 -> 112.5 | G10: 0 | H10: 0 | I10: =SUM(D10*$R$4) -> 0 | J10: =SUM(E10*$R$5) -> 0 | K10: =SUM(F10*$R$6) -> 2025 | L10: =SUM(G10*$R$7) -> 0 | M10: =SUM(H10*$R$8) -> 0 | N10: =SUM(I10:M10) -> 2025
A11: 7 | B11: 46210 | F11: =F10+D11-E10 -> 112.5 | G11: 0 | H11: 0 | I11: =SUM(D11*$R$4) -> 0 | J11: =SUM(E11*$R$5) -> 0 | K11: =SUM(F11*$R$6) -> 2025 | L11: =SUM(G11*$R$7) -> 0 | M11: =SUM(H11*$R$8) -> 0 | N11: =SUM(I11:M11) -> 2025
A12: 8 | B12: 46211 | F12: =F11+D12-E11 -> 112.5 | G12: 0 | H12: 0 | I12: =SUM(D12*$R$4) -> 0 | J12: =SUM(E12*$R$5) -> 0 | K12: =SUM(F12*$R$6) -> 2025 | L12: =SUM(G12*$R$7) -> 0 | M12: =SUM(H12*$R$8) -> 0 | N12: =SUM(I12:M12) -> 2025
A13: 9 | B13: 46212 | F13: =F12+D13-E12 -> 112.5 | G13: 0 | H13: 0 | I13: =SUM(D13*$R$4) -> 0 | J13: =SUM(E13*$R$5) -> 0 | K13: =SUM(F13*$R$6) -> 2025 | L13: =SUM(G13*$R$7) -> 0 | M13: =SUM(H13*$R$8) -> 0 | N13: =SUM(I13:M13) -> 2025
A14: 10 | B14: 46213 | F14: =F13+D14-E13 -> 112.5 | G14: 0 | H14: 0 | I14: =SUM(D14*$R$4) -> 0 | J14: =SUM(E14*$R$5) -> 0 | K14: =SUM(F14*$R$6) -> 2025 | L14: =SUM(G14*$R$7) -> 0 | M14: =SUM(H14*$R$8) -> 0 | N14: =SUM(I14:M14) -> 2025
A15: 11 | B15: 46214 | F15: =F14+D15-E14 -> 112.5 | G15: 0 | H15: 0 | I15: =SUM(D15*$R$4) -> 0 | J15: =SUM(E15*$R$5) -> 0 | K15: =SUM(F15*$R$6) -> 2025 | L15: =SUM(G15*$R$7) -> 0 | M15: =SUM(H15*$R$8) -> 0 | N15: =SUM(I15:M15) -> 2025
A16: 12 | B16: 46215 | F16: =F15+D16-E15 -> 112.5 | G16: 0 | H16: 0 | I16: =SUM(D16*$R$4) -> 0 | J16: =SUM(E16*$R$5) -> 0 | K16: =SUM(F16*$R$6) -> 2025 | L16: =SUM(G16*$R$7) -> 0 | M16: =SUM(H16*$R$8) -> 0 | N16: =SUM(I16:M16) -> 2025
A17: 13 | B17: 46216 | F17: =F16+D17-E16 -> 112.5 | G17: 0 | H17: 0 | I17: =SUM(D17*$R$4) -> 0 | J17: =SUM(E17*$R$5) -> 0 | K17: =SUM(F17*$R$6) -> 2025 | L17: =SUM(G17*$R$7) -> 0 | M17: =SUM(H17*$R$8) -> 0 | N17: =SUM(I17:M17) -> 2025
A18: 14 | B18: 46217 | F18: =F17+D18-E17 -> 112.5 | G18: 0 | H18: 0 | I18: =SUM(D18*$R$4) -> 0 | J18: =SUM(E18*$R$5) -> 0 | K18: =SUM(F18*$R$6) -> 2025 | L18: =SUM(G18*$R$7) -> 0 | M18: =SUM(H18*$R$8) -> 0 | N18: =SUM(I18:M18) -> 2025
A19: 15 | B19: 46218 | F19: =F18+D19-E18 -> 112.5 | G19: 0 | H19: 0 | I19: =SUM(D19*$R$4) -> 0 | J19: =SUM(E19*$R$5) -> 0 | K19: =SUM(F19*$R$6) -> 2025 | L19: =SUM(G19*$R$7) -> 0 | M19: =SUM(H19*$R$8) -> 0 | N19: =SUM(I19:M19) -> 2025
A20: 16 | B20: 46219 | F20: =F19+D20-E19 -> 112.5 | G20: 0 | H20: 0 | I20: =SUM(D20*$R$4) -> 0 | J20: =SUM(E20*$R$5) -> 0 | K20: =SUM(F20*$R$6) -> 2025 | L20: =SUM(G20*$R$7) -> 0 | M20: =SUM(H20*$R$8) -> 0 | N20: =SUM(I20:M20) -> 2025
... A34: 30 | B34: 46233 | F34: =F33+D34-E33 -> 112.5 | G34: 0 | H34: 0 | I34: =SUM(D34*$R$4) -> 0 | J34: =SUM(E34*$R$5) -> 0 | K34: =SUM(F34*$R$6) -> 2025 | L34: =SUM(G34*$R$7) -> 0 | M34: =SUM(H34*$R$8) -> 0 | N34: =SUM(I34:M34) -> 2025
A35: 31 | B35: 46234 | F35: =F34+D35-E34 -> 112.5 | I35: =SUM(D35*$R$4) -> 0 | J35: =SUM(E35*$R$5) -> 0 | K35: =SUM(F35*$R$6) -> 2025 | L35: =SUM(G35*$R$7) -> 0 | M35: =SUM(H35*$R$8) -> 0 | N35: =SUM(I35:M35) -> 2025
D36: =SUM(D5:D35) -> 0 | E36: =SUM(E5:E35) -> 0 | F36: =SUM(F5:F35) -> 3487.5 | G36: =SUM(G5:G35) -> 0 | H36: =SUM(H5:H35) -> 0 | I36: =SUM(I5:I35) -> 0 | J36: =SUM(J5:J35) -> 0 | K36: =SUM(K5:K35) -> 62775 | ... N36: =SUM(N5:N35) -> 62775
N37: =N36*1.22 -> 76585.5

Sheet Приоритет Баумана
A1: =N37 -> 122207.4
A2: ="Отчет по хранению товара за " & TEXT(B5,"ММММ ГГГГ") -> Отчет по хранению товара за Июль 2026 | I2: Баумана
A3: № | B3: дата | D3: Выгрузка кол-во | E3: Загрузка кол-во | F3: Хранение | G3: переконсолидация (тонн) | H3: Паллетирование | I3: стоимость выгрузки | J3: стоимость загрузки | K3: стоимость хранения | L3: стоимость переконс. | M3: Стоимость паллетирования | N3: итого | Q3: Цены
Q4: Выгрузка | R4: 120
A5: 1 | B5: 46204 | D5: 0 | F5: 202.5 | G5: 0 | H5: 0 | I5: =SUM(D5*$R$4) -> 0 | J5: =SUM(E5*$R$5) -> 0 | K5: =SUM(F5*$R$6) -> 3645 | L5: =SUM(G5*$R$7) -> 0 | M5: =SUM(H5*$R$8) -> 0 | N5: =SUM(I5:M5) -> 3645 | Q5: Загрузка | R5: 120
A6: 2 | B6: 46205 | D6: 0 | F6: =F5+D6-E5 -> 202.5 | G6: 0 | H6: 0 | I6: =SUM(D6*$R$4) -> 0 | J6: =SUM(E6*$R$5) -> 0 | K6: =SUM(F6*$R$6) -> 3645 | L6: =SUM(G6*$R$7) -> 0 | M6: =SUM(H6*$R$8) -> 0 | N6: =SUM(I6:M6) -> 3645 | Q6: Хранение | R6: 18
A7: 3 | B7: 46206 | D7: 0 | F7: =F6+D7-E6 -> 202.5 | G7: 0 | H7: 0 | I7: =SUM(D7*$R$4) -> 0 | J7: =SUM(E7*$R$5) -> 0 | K7: =SUM(F7*$R$6) -> 3645 | L7: =SUM(G7*$R$7) -> 0 | M7: =SUM(H7*$R$8) -> 0 | N7: =SUM(I7:M7) -> 3645 | Q7: Переконсолидация | R7: 950
A8: 4 | B8: 46207 | D8: 0 | F8: =F7+D8-E7 -> 202.5 | G8: 0 | H8: 0 | I8: =SUM(D8*$R$4) -> 0 | J8: =SUM(E8*$R$5) -> 0 | K8: =SUM(F8*$R$6) -> 3645 | L8: =SUM(G8*$R$7) -> 0 | M8: =SUM(H8*$R$8) -> 0 | N8: =SUM(I8:M8) -> 3645 | Q8: Паллетирование | R8: 120
A9: 5 | B9: 46208 | D9: 0 | F9: =F8+D9-E8 -> 202.5 | G9: 0 | H9: 0 | I9: =SUM(D9*$R$4) -> 0 | J9: =SUM(E9*$R$5) -> 0 | K9: =SUM(F9*$R$6) -> 3645 | L9: =SUM(G9*$R$7) -> 0 | M9: =SUM(H9*$R$8) -> 0 | N9: =SUM(I9:M9) -> 3645
A10: 6 | B10: 46209 | D10: 0 | F10: =F9+D10-E9 -> 202.5 | G10: 0 | H10: 0 | I10: =SUM(D10*$R$4) -> 0 | J10: =SUM(E10*$R$5) -> 0 | K10: =SUM(F10*$R$6) -> 3645 | L10: =SUM(G10*$R$7) -> 0 | M10: =SUM(H10*$R$8) -> 0 | N10: =SUM(I10:M10) -> 3645
A11: 7 | B11: 46210 | D11: 0 | F11: =F10+D11-E10 -> 202.5 | G11: 0 | H11: 0 | I11: =SUM(D11*$R$4) -> 0 | J11: =SUM(E11*$R$5) -> 0 | K11: =SUM(F11*$R$6) -> 3645 | L11: =SUM(G11*$R$7) -> 0 | M11: =SUM(H11*$R$8) -> 0 | N11: =SUM(I11:M11) -> 3645
A12: 8 | B12: 46211 | D12: 0 | F12: =F11+D12-E11 -> 202.5 | G12: 0 | H12: 0 | I12: =SUM(D12*$R$4) -> 0 | J12: =SUM(E12*$R$5) -> 0 | K12: =SUM(F12*$R$6) -> 3645 | L12: =SUM(G12*$R$7) -> 0 | M12: =SUM(H12*$R$8) -> 0 | N12: =SUM(I12:M12) -> 3645
A13: 9 | B13: 46212 | D13: 0 | F13: =F12+D13-E12 -> 202.5 | G13: 0 | H13: 0 | I13: =SUM(D13*$R$4) -> 0 | J13: =SUM(E13*$R$5) -> 0 | K13: =SUM(F13*$R$6) -> 3645 | L13: =SUM(G13*$R$7) -> 0 | M13: =SUM(H13*$R$8) -> 0 | N13: =SUM(I13:M13) -> 3645
A14: 10 | B14: 46213 | D14: 0 | F14: =F13+D14-E13 -> 202.5 | G14: 0 | H14: 0 | I14: =SUM(D14*$R$4) -> 0 | J14: =SUM(E14*$R$5) -> 0 | K14: =SUM(F14*$R$6) -> 3645 | L14: =SUM(G14*$R$7) -> 0 | M14: =SUM(H14*$R$8) -> 0 | N14: =SUM(I14:M14) -> 3645
A15: 11 | B15: 46214 | D15: 0 | E15: 22.5 | F15: =F14+D15-E14 -> 202.5 | G15: 0 | H15: 0 | I15: =SUM(D15*$R$4) -> 0 | J15: =SUM(E15*$R$5) -> 2700 | K15: =SUM(F15*$R$6) -> 3645 | L15: =SUM(G15*$R$7) -> 0 | M15: =SUM(H15*$R$8) -> 0 | N15: =SUM(I15:M15) -> 6345
A16: 12 | B16: 46215 | D16: 0 | F16: =F15+D16-E15 -> 180 | G16: 0 | H16: 0 | I16: =SUM(D16*$R$4) -> 0 | J16: =SUM(E16*$R$5) -> 0 | K16: =SUM(F16*$R$6) -> 3240 | L16: =SUM(G16*$R$7) -> 0 | M16: =SUM(H16*$R$8) -> 0 | N16: =SUM(I16:M16) -> 3240
A17: 13 | B17: 46216 | D17: 0 | E17: 22.5 | F17: =F16+D17-E16 -> 180 | G17: 0 | H17: 0 | I17: =SUM(D17*$R$4) -> 0 | J17: =SUM(E17*$R$5) -> 2700 | K17: =SUM(F17*$R$6) -> 3240 | L17: =SUM(G17*$R$7) -> 0 | M17: =SUM(H17*$R$8) -> 0 | N17: =SUM(I17:M17) -> 5940
A18: 14 | B18: 46217 | D18: 0 | F18: =F17+D18-E17 -> 157.5 | G18: 0 | H18: 0 | I18: =SUM(D18*$R$4) -> 0 | J18: =SUM(E18*$R$5) -> 0 | K18: =SUM(F18*$R$6) -> 2835 | L18: =SUM(G18*$R$7) -> 0 | M18: =SUM(H18*$R$8) -> 0 | N18: =SUM(I18:M18) -> 2835
A19: 15 | B19: 46218 | D19: 0 | F19: =F18+D19-E18 -> 157.5 | G19: 0 | H19: 0 | I19: =SUM(D19*$R$4) -> 0 | J19: =SUM(E19*$R$5) -> 0 | K19: =SUM(F19*$R$6) -> 2835 | L19: =SUM(G19*$R$7) -> 0 | M19: =SUM(H19*$R$8) -> 0 | N19: =SUM(I19:M19) -> 2835
A20: 16 | B20: 46219 | D20: 0 | E20: 22.5 | F20: =F19+D20-E19 -> 157.5 | G20: 0 | H20: 0 | I20: =SUM(D20*$R$4) -> 0 | J20: =SUM(E20*$R$5) -> 2700 | K20: =SUM(F20*$R$6) -> 2835 | L20: =SUM(G20*$R$7) -> 0 | M20: =SUM(H20*$R$8) -> 0 | N20: =SUM(I20:M20) -> 5535
A21: 17 | B21: 46220 | D21: 0 | F21: =F20+D21-E20 -> 135 | G21: 0 | H21: 0 | I21: =SUM(D21*$R$4) -> 0 | J21: =SUM(E21*$R$5) -> 0 | K21: =SUM(F21*$R$6) -> 2430 | L21: =SUM(G21*$R$7) -> 0 | M21: =SUM(H21*$R$8) -> 0 | N21: =SUM(I21:M21) -> 2430
A22: 18 | B22: 46221 | D22: 0 | F22: =F21+D22-E21 -> 135 | G22: 0 | H22: 0 | I22: =SUM(D22*$R$4) -> 0 | J22: =SUM(E22*$R$5) -> 0 | K22: =SUM(F22*$R$6) -> 2430 | L22: =SUM(G22*$R$7) -> 0 | M22: =SUM(H22*$R$8) -> 0 | N22: =SUM(I22:M22) -> 2430
A23: 19 | B23: 46222 | D23: 0 | F23: =F22+D23-E22 -> 135 | G23: 0 | H23: 0 | I23: =SUM(D23*$R$4) -> 0 | J23: =SUM(E23*$R$5) -> 0 | K23: =SUM(F23*$R$6) -> 2430 | L23: =SUM(G23*$R$7) -> 0 | M23: =SUM(H23*$R$8) -> 0 | N23: =SUM(I23:M23) -> 2430
A24: 20 | B24: 46223 | D24: 0 | E24: 22.5 | F24: =F23+D24-E23 -> 135 | G24: 0 | H24: 0 | I24: =SUM(D24*$R$4) -> 0 | J24: =SUM(E24*$R$5) -> 2700 | K24: =SUM(F24*$R$6) -> 2430 | L24: =SUM(G24*$R$7) -> 0 | M24: =SUM(H24*$R$8) -> 0 | N24: =SUM(I24:M24) -> 5130
A25: 21 | B25: 46224 | D25: 0 | F25: =F24+D25-E24 -> 112.5 | G25: 0 | H25: 0 | I25: =SUM(D25*$R$4) -> 0 | J25: =SUM(E25*$R$5) -> 0 | K25: =SUM(F25*$R$6) -> 2025 | L25: =SUM(G25*$R$7) -> 0 | M25: =SUM(H25*$R$8) -> 0 | N25: =SUM(I25:M25) -> 2025
A26: 22 | B26: 46225 | D26: 0 | F26: =F25+D26-E25 -> 112.5 | G26: 0 | H26: 0 | I26: =SUM(D26*$R$4) -> 0 | J26: =SUM(E26*$R$5) -> 0 | K26: =SUM(F26*$R$6) -> 2025 | L26: =SUM(G26*$R$7) -> 0 | M26: =SUM(H26*$R$8) -> 0 | N26: =SUM(I26:M26) -> 2025
A27: 23 | B27: 46226 | D27: 0 | F27: =F26+D27-E26 -> 112.5 | G27: 0 | H27: 0 | I27: =SUM(D27*$R$4) -> 0 | J27: =SUM(E27*$R$5) -> 0 | K27: =SUM(F27*$R$6) -> 2025 | L27: =SUM(G27*$R$7) -> 0 | M27: =SUM(H27*$R$8) -> 0 | N27: =SUM(I27:M27) -> 2025
A28: 24 | B28: 46227 | D28: 0 | F28: =F27+D28-E27 -> 112.5 | G28: 0 | H28: 0 | I28: =SUM(D28*$R$4) -> 0 | J28: =SUM(E28*$R$5) -> 0 | K28: =SUM(F28*$R$6) -> 2025 | L28: =SUM(G28*$R$7) -> 0 | M28: =SUM(H28*$R$8) -> 0 | N28: =SUM(I28:M28) -> 2025
A29: 25 | B29: 46228 | D29: 0 | F29: =F28+D29-E28 -> 112.5 | G29: 0 | H29: 0 | I29: =SUM(D29*$R$4) -> 0 | J29: =SUM(E29*$R$5) -> 0 | K29: =SUM(F29*$R$6) -> 2025 | L29: =SUM(G29*$R$7) -> 0 | M29: =SUM(H29*$R$8) -> 0 | N29: =SUM(I29:M29) -> 2025
A30: 26 | B30: 46229 | D30: 0 | F30: =F29+D30-E29 -> 112.5 | G30: 0 | H30: 0 | I30: =SUM(D30*$R$4) -> 0 | J30: =SUM(E30*$R$5) -> 0 | K30: =SUM(F30*$R$6) -> 2025 | L30: =SUM(G30*$R$7) -> 0 | M30: =SUM(H30*$R$8) -> 0 | N30: =SUM(I30:M30) -> 2025
A31: 27 | B31: 46230 | D31: 0 | F31: =F30+D31-E30 -> 112.5 | G31: 0 | H31: 0 | I31: =SUM(D31*$R$4) -> 0 | J31: =SUM(E31*$R$5) -> 0 | K31: =SUM(F31*$R$6) -> 2025 | L31: =SUM(G31*$R$7) -> 0 | M31: =SUM(H31*$R$8) -> 0 | N31: =SUM(I31:M31) -> 2025
A32: 28 | B32: 46231 | D32: 0 | F32: =F31+D32-E31 -> 112.5 | G32: 0 | H32: 0 | I32: =SUM(D32*$R$4) -> 0 | J32: =SUM(E32*$R$5) -> 0 | K32: =SUM(F32*$R$6) -> 2025 | L32: =SUM(G32*$R$7) -> 0 | M32: =SUM(H32*$R$8) -> 0 | N32: =SUM(I32:M32) -> 2025
A33: 29 | B33: 46232 | D33: 0 | F33: =F32+D33-E32 -> 112.5 | G33: 0 | H33: 0 | I33: =SUM(D33*$R$4) -> 0 | J33: =SUM(E33*$R$5) -> 0 | K33: =SUM(F33*$R$6) -> 2025 | L33: =SUM(G33*$R$7) -> 0 | M33: =SUM(H33*$R$8) -> 0 | N33: =SUM(I33:M33) -> 2025
A34: 30 | B34: 46233 | D34: 0 | E34: 22.5 | F34: =F33+D34-E33 -> 112.5 | G34: 0 | H34: 0 | I34: =SUM(D34*$R$4) -> 0 | J34: =SUM(E34*$R$5) -> 2700 | K34: =SUM(F34*$R$6) -> 2025 | L34: =SUM(G34*$R$7) -> 0 | M34: =SUM(H34*$R$8) -> 0 | N34: =SUM(I34:M34) -> 4725
A35: 31 | B35: 46234 | F35: =F34+D35-E34 -> 90 | I35: =SUM(D35*$R$4) -> 0 | J35: =SUM(E35*$R$5) -> 0 | K35: =SUM(F35*$R$6) -> 1620 | L35: =SUM(G35*$R$7) -> 0 | M35: =SUM(H35*$R$8) -> 0 | N35: =SUM(I35:M35) -> 1620
D36: =SUM(D5:D35) -> 0 | E36: =SUM(E5:E35) -> 112.5 | F36: =SUM(F5:F35) -> 4815 | G36: =SUM(G5:G35) -> 0 | H36: =SUM(H5:H35) -> 0 | I36: =SUM(I5:I35) -> 0 | J36: =SUM(J5:J35) -> 13500 | K36: =SUM(K5:K35) -> 86670 | ... N36: =SUM(N5:N35) -> 100170
N37: =N36*1.22 -> 122207.4

Sheet Фармпласт Новикова-Прибоя
A1: =N37 -> 102937.5
A2: ="Отчет по хранению товара за " & TEXT(B5,"ММММ ГГГГ") -> Отчет по хранению товара за Июль 2026 | I2: Новикова
A3: № | B3: дата | D3: Выгрузка кол-во | E3: Загрузка кол-во | F3: Хранение | G3: переконсолидация (тонн) | H3: Паллетирование | I3: стоимость выгрузки | J3: стоимость загрузки | K3: стоимость хранения | L3: стоимость переконс. | M3: Стоимость паллетирования | N3: итого | Q3: Цены
Q4: Выгрузка | R4: 120
A5: 1 | B5: 46204 | D5: 0 | F5: 180 | G5: 0 | H5: 0 | I5: =SUM(D5*$R$4) -> 0 | J5: =SUM(E5*$R$5) -> 0 | K5: =SUM(F5*$R$6) -> 3240 | L5: =SUM(G5*$R$7) -> 0 | M5: =SUM(H5*$R$8) -> 0 | N5: =SUM(I5:M5) -> 3240 | Q5: Загрузка | R5: 120
A6: 2 | B6: 46205 | D6: 0 | F6: =F5+D6-E5 -> 180 | G6: 0 | H6: 0 | I6: =SUM(D6*$R$4) -> 0 | J6: =SUM(E6*$R$5) -> 0 | K6: =SUM(F6*$R$6) -> 3240 | L6: =SUM(G6*$R$7) -> 0 | M6: =SUM(H6*$R$8) -> 0 | N6: =SUM(I6:M6) -> 3240 | Q6: Хранение | R6: 18
A7: 3 | B7: 46206 | D7: 0 | F7: =F6+D7-E6 -> 180 | G7: 0 | H7: 0 | I7: =SUM(D7*$R$4) -> 0 | J7: =SUM(E7*$R$5) -> 0 | K7: =SUM(F7*$R$6) -> 3240 | L7: =SUM(G7*$R$7) -> 0 | M7: =SUM(H7*$R$8) -> 0 | N7: =SUM(I7:M7) -> 3240 | Q7: Переконсолидация | R7: 950
A8: 4 | B8: 46207 | D8: 0 | F8: =F7+D8-E7 -> 180 | G8: 0 | H8: 0 | I8: =SUM(D8*$R$4) -> 0 | J8: =SUM(E8*$R$5) -> 0 | K8: =SUM(F8*$R$6) -> 3240 | L8: =SUM(G8*$R$7) -> 0 | M8: =SUM(H8*$R$8) -> 0 | N8: =SUM(I8:M8) -> 3240 | Q8: Паллетирование | R8: 120
A9: 5 | B9: 46208 | D9: 0 | F9: =F8+D9-E8 -> 180 | G9: 0 | H9: 0 | I9: =SUM(D9*$R$4) -> 0 | J9: =SUM(E9*$R$5) -> 0 | K9: =SUM(F9*$R$6) -> 3240 | L9: =SUM(G9*$R$7) -> 0 | M9: =SUM(H9*$R$8) -> 0 | N9: =SUM(I9:M9) -> 3240
A10: 6 | B10: 46209 | D10: 0 | F10: =F9+D10-E9 -> 180 | G10: 0 | H10: 0 | I10: =SUM(D10*$R$4) -> 0 | J10: =SUM(E10*$R$5) -> 0 | K10: =SUM(F10*$R$6) -> 3240 | L10: =SUM(G10*$R$7) -> 0 | M10: =SUM(H10*$R$8) -> 0 | N10: =SUM(I10:M10) -> 3240
A11: 7 | B11: 46210 | D11: 0 | F11: =F10+D11-E10 -> 180 | G11: 0 | H11: 0 | I11: =SUM(D11*$R$4) -> 0 | J11: =SUM(E11*$R$5) -> 0 | K11: =SUM(F11*$R$6) -> 3240 | L11: =SUM(G11*$R$7) -> 0 | M11: =SUM(H11*$R$8) -> 0 | N11: =SUM(I11:M11) -> 3240
A12: 8 | B12: 46211 | D12: 0 | F12: =F11+D12-E11 -> 180 | G12: 0 | H12: 0 | I12: =SUM(D12*$R$4) -> 0 | J12: =SUM(E12*$R$5) -> 0 | K12: =SUM(F12*$R$6) -> 3240 | L12: =SUM(G12*$R$7) -> 0 | M12: =SUM(H12*$R$8) -> 0 | N12: =SUM(I12:M12) -> 3240
A13: 9 | B13: 46212 | D13: 0 | E13: 22.5 | F13: =F12+D13-E12 -> 180 | G13: 0 | H13: 0 | I13: =SUM(D13*$R$4) -> 0 | J13: =SUM(E13*$R$5) -> 2700 | K13: =SUM(F13*$R$6) -> 3240 | L13: =SUM(G13*$R$7) -> 0 | M13: =SUM(H13*$R$8) -> 0 | N13: =SUM(I13:M13) -> 5940
A14: 10 | B14: 46213 | D14: 0 | F14: =F13+D14-E13 -> 157.5 | G14: 0 | H14: 0 | I14: =SUM(D14*$R$4) -> 0 | J14: =SUM(E14*$R$5) -> 0 | K14: =SUM(F14*$R$6) -> 2835 | L14: =SUM(G14*$R$7) -> 0 | M14: =SUM(H14*$R$8) -> 0 | N14: =SUM(I14:M14) -> 2835
A15: 11 | B15: 46214 | D15: 0 | F15: =F14+D15-E14 -> 157.5 | G15: 0 | H15: 0 | I15: =SUM(D15*$R$4) -> 0 | J15: =SUM(E15*$R$5) -> 0 | K15: =SUM(F15*$R$6) -> 2835 | L15: =SUM(G15*$R$7) -> 0 | M15: =SUM(H15*$R$8) -> 0 | N15: =SUM(I15:M15) -> 2835
A16: 12 | B16: 46215 | D16: 0 | F16: =F15+D16-E15 -> 157.5 | G16: 0 | H16: 0 | I16: =SUM(D16*$R$4) -> 0 | J16: =SUM(E16*$R$5) -> 0 | K16: =SUM(F16*$R$6) -> 2835 | L16: =SUM(G16*$R$7) -> 0 | M16: =SUM(H16*$R$8) -> 0 | N16: =SUM(I16:M16) -> 2835
A17: 13 | B17: 46216 | D17: 0 | F17: =F16+D17-E16 -> 157.5 | G17: 0 | H17: 0 | I17: =SUM(D17*$R$4) -> 0 | J17: =SUM(E17*$R$5) -> 0 | K17: =SUM(F17*$R$6) -> 2835 | L17: =SUM(G17*$R$7) -> 0 | M17: =SUM(H17*$R$8) -> 0 | N17: =SUM(I17:M17) -> 2835
A18: 14 | B18: 46217 | D18: 0 | E18: 22.5 | F18: =F17+D18-E17 -> 157.5 | G18: 0 | H18: 0 | I18: =SUM(D18*$R$4) -> 0 | J18: =SUM(E18*$R$5) -> 2700 | K18: =SUM(F18*$R$6) -> 2835 | L18: =SUM(G18*$R$7) -> 0 | M18: =SUM(H18*$R$8) -> 0 | N18: =SUM(I18:M18) -> 5535
A19: 15 | B19: 46218 | D19: 0 | F19: =F18+D19-E18 -> 135 | G19: 0 | H19: 0 | I19: =SUM(D19*$R$4) -> 0 | J19: =SUM(E19*$R$5) -> 0 | K19: =SUM(F19*$R$6) -> 2430 | L19: =SUM(G19*$R$7) -> 0 | M19: =SUM(H19*$R$8) -> 0 | N19: =SUM(I19:M19) -> 2430
A20: 16 | B20: 46219 | D20: 0 | E20: 22.5 | F20: =F19+D20-E19 -> 135 | G20: 0 | H20: 0 | I20: =SUM(D20*$R$4) -> 0 | J20: =SUM(E20*$R$5) -> 2700 | K20: =SUM(F20*$R$6) -> 2430 | L20: =SUM(G20*$R$7) -> 0 | M20: =SUM(H20*$R$8) -> 0 | N20: =SUM(I20:M20) -> 5130
A21: 17 | B21: 46220 | D21: 0 | F21: =F20+D21-E20 -> 112.5 | G21: 0 | H21: 0 | I21: =SUM(D21*$R$4) -> 0 | J21: =SUM(E21*$R$5) -> 0 | K21: =SUM(F21*$R$6) -> 2025 | L21: =SUM(G21*$R$7) -> 0 | M21: =SUM(H21*$R$8) -> 0 | N21: =SUM(I21:M21) -> 2025
A22: 18 | B22: 46221 | D22: 0 | F22: =F21+D22-E21 -> 112.5 | G22: 0 | H22: 0 | I22: =SUM(D22*$R$4) -> 0 | J22: =SUM(E22*$R$5) -> 0 | K22: =SUM(F22*$R$6) -> 2025 | L22: =SUM(G22*$R$7) -> 0 | M22: =SUM(H22*$R$8) -> 0 | N22: =SUM(I22:M22) -> 2025
A23: 19 | B23: 46222 | D23: 0 | F23: =F22+D23-E22 -> 112.5 | G23: 0 | H23: 0 | I23: =SUM(D23*$R$4) -> 0 | J23: =SUM(E23*$R$5) -> 0 | K23: =SUM(F23*$R$6) -> 2025 | L23: =SUM(G23*$R$7) -> 0 | M23: =SUM(H23*$R$8) -> 0 | N23: =SUM(I23:M23) -> 2025
A24: 20 | B24: 46223 | D24: 0 | E24: 22.5 | F24: =F23+D24-E23 -> 112.5 | G24: 0 | H24: 0 | I24: =SUM(D24*$R$4) -> 0 | J24: =SUM(E24*$R$5) -> 2700 | K24: =SUM(F24*$R$6) -> 2025 | L24: =SUM(G24*$R$7) -> 0 | M24: =SUM(H24*$R$8) -> 0 | N24: =SUM(I24:M24) -> 4725
A25: 21 | B25: 46224 | D25: 0 | F25: =F24+D25-E24 -> 90 | G25: 0 | H25: 0 | I25: =SUM(D25*$R$4) -> 0 | J25: =SUM(E25*$R$5) -> 0 | K25: =SUM(F25*$R$6) -> 1620 | L25: =SUM(G25*$R$7) -> 0 | M25: =SUM(H25*$R$8) -> 0 | N25: =SUM(I25:M25) -> 1620
A26: 22 | B26: 46225 | D26: 0 | F26: =F25+D26-E25 -> 90 | G26: 0 | H26: 0 | I26: =SUM(D26*$R$4) -> 0 | J26: =SUM(E26*$R$5) -> 0 | K26: =SUM(F26*$R$6) -> 1620 | L26: =SUM(G26*$R$7) -> 0 | M26: =SUM(H26*$R$8) -> 0 | N26: =SUM(I26:M26) -> 1620
A27: 23 | B27: 46226 | D27: 0 | E27: 22.5 | F27: =F26+D27-E26 -> 90 | G27: 0 | H27: 0 | I27: =SUM(D27*$R$4) -> 0 | J27: =SUM(E27*$R$5) -> 2700 | K27: =SUM(F27*$R$6) -> 1620 | L27: =SUM(G27*$R$7) -> 0 | M27: =SUM(H27*$R$8) -> 0 | N27: =SUM(I27:M27) -> 4320
A28: 24 | B28: 46227 | D28: 0 | F28: =F27+D28-E27 -> 67.5 | G28: 0 | H28: 0 | I28: =SUM(D28*$R$4) -> 0 | J28: =SUM(E28*$R$5) -> 0 | K28: =SUM(F28*$R$6) -> 1215 | L28: =SUM(G28*$R$7) -> 0 | M28: =SUM(H28*$R$8) -> 0 | N28: =SUM(I28:M28) -> 1215
A29: 25 | B29: 46228 | D29: 0 | F29: =F28+D29-E28 -> 67.5 | G29: 0 | H29: 0 | I29: =SUM(D29*$R$4) -> 0 | J29: =SUM(E29*$R$5) -> 0 | K29: =SUM(F29*$R$6) -> 1215 | L29: =SUM(G29*$R$7) -> 0 | M29: =SUM(H29*$R$8) -> 0 | N29: =SUM(I29:M29) -> 1215
A30: 26 | B30: 46229 | D30: 0 | F30: =F29+D30-E29 -> 67.5 | G30: 0 | H30: 0 | I30: =SUM(D30*$R$4) -> 0 | J30: =SUM(E30*$R$5) -> 0 | K30: =SUM(F30*$R$6) -> 1215 | L30: =SUM(G30*$R$7) -> 0 | M30: =SUM(H30*$R$8) -> 0 | N30: =SUM(I30:M30) -> 1215
A31: 27 | B31: 46230 | D31: 0 | F31: =F30+D31-E30 -> 67.5 | G31: 0 | H31: 0 | I31: =SUM(D31*$R$4) -> 0 | J31: =SUM(E31*$R$5) -> 0 | K31: =SUM(F31*$R$6) -> 1215 | L31: =SUM(G31*$R$7) -> 0 | M31: =SUM(H31*$R$8) -> 0 | N31: =SUM(I31:M31) -> 1215
A32: 28 | B32: 46231 | D32: 0 | F32: =F31+D32-E31 -> 67.5 | G32: 0 | H32: 0 | I32: =SUM(D32*$R$4) -> 0 | J32: =SUM(E32*$R$5) -> 0 | K32: =SUM(F32*$R$6) -> 1215 | L32: =SUM(G32*$R$7) -> 0 | M32: =SUM(H32*$R$8) -> 0 | N32: =SUM(I32:M32) -> 1215
A33: 29 | B33: 46232 | D33: 0 | F33: =F32+D33-E32 -> 67.5 | G33: 0 | H33: 0 | I33: =SUM(D33*$R$4) -> 0 | J33: =SUM(E33*$R$5) -> 0 | K33: =SUM(F33*$R$6) -> 1215 | L33: =SUM(G33*$R$7) -> 0 | M33: =SUM(H33*$R$8) -> 0 | N33: =SUM(I33:M33) -> 1215
A34: 30 | B34: 46233 | D34: 0 | F34: =F33+D34-E33 -> 67.5 | G34: 0 | H34: 0 | I34: =SUM(D34*$R$4) -> 0 | J34: =SUM(E34*$R$5) -> 0 | K34: =SUM(F34*$R$6) -> 1215 | L34: =SUM(G34*$R$7) -> 0 | M34: =SUM(H34*$R$8) -> 0 | N34: =SUM(I34:M34) -> 1215
A35: 31 | B35: 46234 | F35: =F34+D35-E34 -> 67.5 | I35: =SUM(D35*$R$4) -> 0 | J35: =SUM(E35*$R$5) -> 0 | K35: =SUM(F35*$R$6) -> 1215 | L35: =SUM(G35*$R$7) -> 0 | M35: =SUM(H35*$R$8) -> 0 | N35: =SUM(I35:M35) -> 1215
D36: =SUM(D5:D35) -> 0 | E36: =SUM(E5:E35) -> 112.5 | F36: =SUM(F5:F35) -> 3937.5 | G36: =SUM(G5:G35) -> 0 | H36: =SUM(H5:H35) -> 0 | I36: =SUM(I5:I35) -> 0 | J36: =SUM(J5:J35) -> 13500 | K36: =SUM(K5:K35) -> 70875 | ... N36: =SUM(N5:N35) -> 84375
N37: =N36*1.22 -> 102937.5

Sheet Фармпласт Баумана
A1: =N37 -> 416008.41
A2: ="Отчет по хранению товара за " & TEXT(B5,"ММММ ГГГГ") -> Отчет по хранению товара за Июль 2026 | I2: Баумана
A3: № | B3: дата | D3: Выгрузка кол-во | E3: Загрузка кол-во | F3: Хранение | G3: переконсолидация (тонн) | H3: Паллетирование | I3: стоимость выгрузки | J3: стоимость загрузки | K3: стоимость хранения | L3: стоимость переконс. | M3: Стоимость паллетирования | N3: итого | Q3: Цены
Q4: Выгрузка | R4: 120
A5: 1 | B5: 46204 | D5: 0 | F5: 715.5 | G5: 0 | H5: 0 | I5: =SUM(D5*$R$4) -> 0 | J5: =SUM(E5*$R$5) -> 0 | K5: =SUM(F5*$R$6) -> 12879 | L5: =SUM(G5*$R$7) -> 0 | M5: =SUM(H5*$R$8) -> 0 | N5: =SUM(I5:M5) -> 12879 | Q5: Загрузка | R5: 120
A6: 2 | B6: 46205 | D6: 0 | E6: 22 | F6: =F5+D6-E5 -> 715.5 | G6: 0 | H6: 0 | I6: =SUM(D6*$R$4) -> 0 | J6: =SUM(E6*$R$5) -> 2640 | K6: =SUM(F6*$R$6) -> 12879 | L6: =SUM(G6*$R$7) -> 0 | M6: =SUM(H6*$R$8) -> 0 | N6: =SUM(I6:M6) -> 15519 | Q6: Хранение | R6: 18
A7: 3 | B7: 46206 | D7: 0 | E7: 22.5 | F7: =F6+D7-E6 -> 693.5 | G7: 0 | H7: 0 | I7: =SUM(D7*$R$4) -> 0 | J7: =SUM(E7*$R$5) -> 2700 | K7: =SUM(F7*$R$6) -> 12483 | L7: =SUM(G7*$R$7) -> 0 | M7: =SUM(H7*$R$8) -> 0 | N7: =SUM(I7:M7) -> 15183 | Q7: Переконсолидация | R7: 950
A8: 4 | B8: 46207 | D8: 0 | F8: =F7+D8-E7 -> 671 | G8: 0 | H8: 0 | I8: =SUM(D8*$R$4) -> 0 | J8: =SUM(E8*$R$5) -> 0 | K8: =SUM(F8*$R$6) -> 12078 | L8: =SUM(G8*$R$7) -> 0 | M8: =SUM(H8*$R$8) -> 0 | N8: =SUM(I8:M8) -> 12078 | Q8: Паллетирование | R8: 120
A9: 5 | B9: 46208 | D9: 0 | F9: =F8+D9-E8 -> 671 | G9: 0 | H9: 0 | I9: =SUM(D9*$R$4) -> 0 | J9: =SUM(E9*$R$5) -> 0 | K9: =SUM(F9*$R$6) -> 12078 | L9: =SUM(G9*$R$7) -> 0 | M9: =SUM(H9*$R$8) -> 0 | N9: =SUM(I9:M9) -> 12078
A10: 6 | B10: 46209 | D10: 0 | E10: 21 | F10: =F9+D10-E9 -> 671 | G10: 0 | H10: 0 | I10: =SUM(D10*$R$4) -> 0 | J10: =SUM(E10*$R$5) -> 2520 | K10: =SUM(F10*$R$6) -> 12078 | L10: =SUM(G10*$R$7) -> 0 | M10: =SUM(H10*$R$8) -> 0 | N10: =SUM(I10:M10) -> 14598
A11: 7 | B11: 46210 | D11: 0 | E11: 21 | F11: =F10+D11-E10 -> 650 | G11: 0 | H11: 0 | I11: =SUM(D11*$R$4) -> 0 | J11: =SUM(E11*$R$5) -> 2520 | K11: =SUM(F11*$R$6) -> 11700 | L11: =SUM(G11*$R$7) -> 0 | M11: =SUM(H11*$R$8) -> 0 | N11: =SUM(I11:M11) -> 14220
A12: 8 | B12: 46211 | D12: 0 | E12: 22.5 | F12: =F11+D12-E11 -> 629 | G12: 0 | H12: 0 | I12: =SUM(D12*$R$4) -> 0 | J12: =SUM(E12*$R$5) -> 2700 | K12: =SUM(F12*$R$6) -> 11322 | L12: =SUM(G12*$R$7) -> 0 | M12: =SUM(H12*$R$8) -> 0 | N12: =SUM(I12:M12) -> 14022
A13: 9 | B13: 46212 | D13: 0 | E13: 44.5 | F13: =F12+D13-E12 -> 606.5 | G13: 0 | H13: 0 | I13: =SUM(D13*$R$4) -> 0 | J13: =SUM(E13*$R$5) -> 5340 | K13: =SUM(F13*$R$6) -> 10917 | L13: =SUM(G13*$R$7) -> 0 | M13: =SUM(H13*$R$8) -> 0 | N13: =SUM(I13:M13) -> 16257
A14: 10 | B14: 46213 | D14: 0 | F14: =F13+D14-E13 -> 562 | G14: 0 | H14: 0 | I14: =SUM(D14*$R$4) -> 0 | J14: =SUM(E14*$R$5) -> 0 | K14: =SUM(F14*$R$6) -> 10116 | L14: =SUM(G14*$R$7) -> 0 | M14: =SUM(H14*$R$8) -> 0 | N14: =SUM(I14:M14) -> 10116
A15: 11 | B15: 46214 | D15: 0 | F15: =F14+D15-E14 -> 562 | G15: 0 | H15: 0 | I15: =SUM(D15*$R$4) -> 0 | J15: =SUM(E15*$R$5) -> 0 | K15: =SUM(F15*$R$6) -> 10116 | L15: =SUM(G15*$R$7) -> 0 | M15: =SUM(H15*$R$8) -> 0 | N15: =SUM(I15:M15) -> 10116
A16: 12 | B16: 46215 | D16: 0 | F16: =F15+D16-E15 -> 562 | G16: 0 | H16: 0 | I16: =SUM(D16*$R$4) -> 0 | J16: =SUM(E16*$R$5) -> 0 | K16: =SUM(F16*$R$6) -> 10116 | L16: =SUM(G16*$R$7) -> 0 | M16: =SUM(H16*$R$8) -> 0 | N16: =SUM(I16:M16) -> 10116
A17: 13 | B17: 46216 | D17: 0 | F17: =F16+D17-E16 -> 562 | G17: 0 | H17: 0 | I17: =SUM(D17*$R$4) -> 0 | J17: =SUM(E17*$R$5) -> 0 | K17: =SUM(F17*$R$6) -> 10116 | L17: =SUM(G17*$R$7) -> 0 | M17: =SUM(H17*$R$8) -> 0 | N17: =SUM(I17:M17) -> 10116
A18: 14 | B18: 46217 | D18: 0 | E18: 22.5 | F18: =F17+D18-E17 -> 562 | G18: 0 | H18: 0 | I18: =SUM(D18*$R$4) -> 0 | J18: =SUM(E18*$R$5) -> 2700 | K18: =SUM(F18*$R$6) -> 10116 | L18: =SUM(G18*$R$7) -> 0 | M18: =SUM(H18*$R$8) -> 0 | N18: =SUM(I18:M18) -> 12816
A19: 15 | B19: 46218 | D19: 0 | F19: =F18+D19-E18 -> 539.5 | G19: 0 | H19: 0 | I19: =SUM(D19*$R$4) -> 0 | J19: =SUM(E19*$R$5) -> 0 | K19: =SUM(F19*$R$6) -> 9711 | L19: =SUM(G19*$R$7) -> 0 | M19: =SUM(H19*$R$8) -> 0 | N19: =SUM(I19:M19) -> 9711
A20: 16 | B20: 46219 | D20: 0 | F20: =F19+D20-E19 -> 539.5 | G20: 0 | H20: 0 | I20: =SUM(D20*$R$4) -> 0 | J20: =SUM(E20*$R$5) -> 0 | K20: =SUM(F20*$R$6) -> 9711 | L20: =SUM(G20*$R$7) -> 0 | M20: =SUM(H20*$R$8) -> 0 | N20: =SUM(I20:M20) -> 9711
A21: 17 | B21: 46220 | D21: 0 | E21: 44.5 | F21: =F20+D21-E20 -> 539.5 | G21: 0 | H21: 0 | I21: =SUM(D21*$R$4) -> 0 | J21: =SUM(E21*$R$5) -> 5340 | K21: =SUM(F21*$R$6) -> 9711 | L21: =SUM(G21*$R$7) -> 0 | M21: =SUM(H21*$R$8) -> 0 | N21: =SUM(I21:M21) -> 15051
A22: 18 | B22: 46221 | D22: 0 | E22: 22.5 | F22: =F21+D22-E21 -> 495 | G22: 0 | H22: 0 | I22: =SUM(D22*$R$4) -> 0 | J22: =SUM(E22*$R$5) -> 2700 | K22: =SUM(F22*$R$6) -> 8910 | L22: =SUM(G22*$R$7) -> 0 | M22: =SUM(H22*$R$8) -> 0 | N22: =SUM(I22:M22) -> 11610
A23: 19 | B23: 46222 | D23: 0 | F23: =F22+D23-E22 -> 472.5 | G23: 0 | H23: 0 | I23: =SUM(D23*$R$4) -> 0 | J23: =SUM(E23*$R$5) -> 0 | K23: =SUM(F23*$R$6) -> 8505 | L23: =SUM(G23*$R$7) -> 0 | M23: =SUM(H23*$R$8) -> 0 | N23: =SUM(I23:M23) -> 8505
A24: 20 | B24: 46223 | D24: 0 | E24: 22 | F24: =F23+D24-E23 -> 472.5 | G24: 0 | H24: 0 | I24: =SUM(D24*$R$4) -> 0 | J24: =SUM(E24*$R$5) -> 2640 | K24: =SUM(F24*$R$6) -> 8505 | L24: =SUM(G24*$R$7) -> 0 | M24: =SUM(H24*$R$8) -> 0 | N24: =SUM(I24:M24) -> 11145
A25: 21 | B25: 46224 | D25: 0 | F25: =F24+D25-E24 -> 450.5 | G25: 0 | H25: 0 | I25: =SUM(D25*$R$4) -> 0 | J25: =SUM(E25*$R$5) -> 0 | K25: =SUM(F25*$R$6) -> 8109 | L25: =SUM(G25*$R$7) -> 0 | M25: =SUM(H25*$R$8) -> 0 | N25: =SUM(I25:M25) -> 8109
A26: 22 | B26: 46225 | D26: 0 | F26: =F25+D26-E25 -> 450.5 | G26: 0 | H26: 0 | I26: =SUM(D26*$R$4) -> 0 | J26: =SUM(E26*$R$5) -> 0 | K26: =SUM(F26*$R$6) -> 8109 | L26: =SUM(G26*$R$7) -> 0 | M26: =SUM(H26*$R$8) -> 0 | N26: =SUM(I26:M26) -> 8109
A27: 23 | B27: 46226 | D27: 0 | F27: =F26+D27-E26 -> 450.5 | G27: 0 | H27: 0 | I27: =SUM(D27*$R$4) -> 0 | J27: =SUM(E27*$R$5) -> 0 | K27: =SUM(F27*$R$6) -> 8109 | L27: =SUM(G27*$R$7) -> 0 | M27: =SUM(H27*$R$8) -> 0 | N27: =SUM(I27:M27) -> 8109
A28: 24 | B28: 46227 | D28: 0 | E28: 21 | F28: =F27+D28-E27 -> 450.5 | G28: 0 | H28: 0 | I28: =SUM(D28*$R$4) -> 0 | J28: =SUM(E28*$R$5) -> 2520 | K28: =SUM(F28*$R$6) -> 8109 | L28: =SUM(G28*$R$7) -> 0 | M28: =SUM(H28*$R$8) -> 0 | N28: =SUM(I28:M28) -> 10629
A29: 25 | B29: 46228 | D29: 0 | F29: =F28+D29-E28 -> 429.5 | G29: 0 | H29: 0 | I29: =SUM(D29*$R$4) -> 0 | J29: =SUM(E29*$R$5) -> 0 | K29: =SUM(F29*$R$6) -> 7731 | L29: =SUM(G29*$R$7) -> 0 | M29: =SUM(H29*$R$8) -> 0 | N29: =SUM(I29:M29) -> 7731
A30: 26 | B30: 46229 | D30: 0 | F30: =F29+D30-E29 -> 429.5 | G30: 0 | H30: 0 | I30: =SUM(D30*$R$4) -> 0 | J30: =SUM(E30*$R$5) -> 0 | K30: =SUM(F30*$R$6) -> 7731 | L30: =SUM(G30*$R$7) -> 0 | M30: =SUM(H30*$R$8) -> 0 | N30: =SUM(I30:M30) -> 7731
A31: 27 | B31: 46230 | D31: 0 | F31: =F30+D31-E30 -> 429.5 | G31: 0 | H31: 0 | I31: =SUM(D31*$R$4) -> 0 | J31: =SUM(E31*$R$5) -> 0 | K31: =SUM(F31*$R$6) -> 7731 | L31: =SUM(G31*$R$7) -> 0 | M31: =SUM(H31*$R$8) -> 0 | N31: =SUM(I31:M31) -> 7731
A32: 28 | B32: 46231 | D32: 0 | F32: =F31+D32-E31 -> 429.5 | G32: 0 | H32: 0 | I32: =SUM(D32*$R$4) -> 0 | J32: =SUM(E32*$R$5) -> 0 | K32: =SUM(F32*$R$6) -> 7731 | L32: =SUM(G32*$R$7) -> 0 | M32: =SUM(H32*$R$8) -> 0 | N32: =SUM(I32:M32) -> 7731
A33: 29 | B33: 46232 | D33: 0 | E33: 40.125 | F33: =F32+D33-E32 -> 429.5 | G33: 0 | H33: 0 | I33: =SUM(D33*$R$4) -> 0 | J33: =SUM(E33*$R$5) -> 4815 | K33: =SUM(F33*$R$6) -> 7731 | L33: =SUM(G33*$R$7) -> 0 | M33: =SUM(H33*$R$8) -> 0 | N33: =SUM(I33:M33) -> 12546
A34: 30 | B34: 46233 | D34: 0 | F34: =F33+D34-E33 -> 389.375 | G34: 0 | H34: 0 | I34: =SUM(D34*$R$4) -> 0 | J34: =SUM(E34*$R$5) -> 0 | K34: =SUM(F34*$R$6) -> 7008.75 | L34: =SUM(G34*$R$7) -> 0 | M34: =SUM(H34*$R$8) -> 0 | N34: =SUM(I34:M34) -> 7008.75
A35: 31 | B35: 46234 | E35: 22.5 | F35: =F34+D35-E34 -> 389.375 | I35: =SUM(D35*$R$4) -> 0 | J35: =SUM(E35*$R$5) -> 2700 | K35: =SUM(F35*$R$6) -> 7008.75 | L35: =SUM(G35*$R$7) -> 0 | M35: =SUM(H35*$R$8) -> 0 | N35: =SUM(I35:M35) -> 9708.75
D36: =SUM(D5:D35) -> 0 | E36: =SUM(E5:E35) -> 348.625 | F36: =SUM(F5:F35) -> 16619.75 | G36: =SUM(G5:G35) -> 0 | H36: =SUM(H5:H35) -> 0 | I36: =SUM(I5:I35) -> 0 | J36: =SUM(J5:J35) -> 41835 | K36: =SUM(K5:K35) -> 299155.5 | ... N36: =SUM(N5:N35) -> 340990.5
N37: =N36*1.22 -> 416008.41

Sheet Фармпласт Казань_Автосервисная
A1: =N37 -> 0
A2: ="Отчет по хранению товара за " & TEXT(B5,"ММММ ГГГГ") -> Отчет по хранению товара за Июль 2026 | I2: Казань_Автосервисная
A3: № | B3: дата | D3: Выгрузка кол-во | E3: Загрузка кол-во | F3: Хранение | G3: переконсолидация (тонн) | H3: Паллетирование | I3: стоимость выгрузки | J3: стоимость загрузки | K3: стоимость хранения | L3: стоимость переконс. | M3: Стоимость паллетирования | N3: итого | Q3: Цены
Q4: Выгрузка | R4: 144
A5: 1 | B5: 46204 | F5: 0 | G5: 0 | H5: 0 | I5: =SUM(D5*$R$4) -> 0 | J5: =SUM(E5*$R$5) -> 0 | K5: =SUM(F5*$R$6) -> 0 | L5: =SUM(G5*$R$7) -> 0 | M5: =SUM(H5*$R$8) -> 0 | N5: =SUM(I5:M5) -> 0 | Q5: Загрузка | R5: 144
A6: 2 | B6: 46205 | F6: =F5+D6-E5 -> 0 | G6: 0 | H6: 0 | I6: =SUM(D6*$R$4) -> 0 | J6: =SUM(E6*$R$5) -> 0 | K6: =SUM(F6*$R$6) -> 0 | L6: =SUM(G6*$R$7) -> 0 | M6: =SUM(H6*$R$8) -> 0 | N6: =SUM(I6:M6) -> 0 | Q6: Хранение | R6: 42
A7: 3 | B7: 46206 | F7: =F6+D7-E6 -> 0 | G7: 0 | H7: 0 | I7: =SUM(D7*$R$4) -> 0 | J7: =SUM(E7*$R$5) -> 0 | K7: =SUM(F7*$R$6) -> 0 | L7: =SUM(G7*$R$7) -> 0 | M7: =SUM(H7*$R$8) -> 0 | N7: =SUM(I7:M7) -> 0 | Q7: Переконсолидация | R7: 1200
A8: 4 | B8: 46207 | F8: =F7+D8-E7 -> 0 | G8: 0 | H8: 0 | I8: =SUM(D8*$R$4) -> 0 | J8: =SUM(E8*$R$5) -> 0 | K8: =SUM(F8*$R$6) -> 0 | L8: =SUM(G8*$R$7) -> 0 | M8: =SUM(H8*$R$8) -> 0 | N8: =SUM(I8:M8) -> 0 | Q8: Паллетирование | R8: 240
A9: 5 | B9: 46208 | F9: =F8+D9-E8 -> 0 | G9: 0 | H9: 0 | I9: =SUM(D9*$R$4) -> 0 | J9: =SUM(E9*$R$5) -> 0 | K9: =SUM(F9*$R$6) -> 0 | L9: =SUM(G9*$R$7) -> 0 | M9: =SUM(H9*$R$8) -> 0 | N9: =SUM(I9:M9) -> 0
A10: 6 | B10: 46209 | F10: =F9+D10-E9 -> 0 | G10: 0 | H10: 0 | I10: =SUM(D10*$R$4) -> 0 | J10: =SUM(E10*$R$5) -> 0 | K10: =SUM(F10*$R$6) -> 0 | L10: =SUM(G10*$R$7) -> 0 | M10: =SUM(H10*$R$8) -> 0 | N10: =SUM(I10:M10) -> 0
A11: 7 | B11: 46210 | F11: =F10+D11-E10 -> 0 | G11: 0 | H11: 0 | I11: =SUM(D11*$R$4) -> 0 | J11: =SUM(E11*$R$5) -> 0 | K11: =SUM(F11*$R$6) -> 0 | L11: =SUM(G11*$R$7) -> 0 | M11: =SUM(H11*$R$8) -> 0 | N11: =SUM(I11:M11) -> 0
A12: 8 | B12: 46211 | F12: =F11+D12-E11 -> 0 | G12: 0 | H12: 0 | I12: =SUM(D12*$R$4) -> 0 | J12: =SUM(E12*$R$5) -> 0 | K12: =SUM(F12*$R$6) -> 0 | L12: =SUM(G12*$R$7) -> 0 | M12: =SUM(H12*$R$8) -> 0 | N12: =SUM(I12:M12) -> 0
A13: 9 | B13: 46212 | F13: =F12+D13-E12 -> 0 | G13: 0 | H13: 0 | I13: =SUM(D13*$R$4) -> 0 | J13: =SUM(E13*$R$5) -> 0 | K13: =SUM(F13*$R$6) -> 0 | L13: =SUM(G13*$R$7) -> 0 | M13: =SUM(H13*$R$8) -> 0 | N13: =SUM(I13:M13) -> 0
A14: 10 | B14: 46213 | F14: =F13+D14-E13 -> 0 | G14: 0 | H14: 0 | I14: =SUM(D14*$R$4) -> 0 | J14: =SUM(E14*$R$5) -> 0 | K14: =SUM(F14*$R$6) -> 0 | L14: =SUM(G14*$R$7) -> 0 | M14: =SUM(H14*$R$8) -> 0 | N14: =SUM(I14:M14) -> 0
A15: 11 | B15: 46214 | F15: =F14+D15-E14 -> 0 | G15: 0 | H15: 0 | I15: =SUM(D15*$R$4) -> 0 | J15: =SUM(E15*$R$5) -> 0 | K15: =SUM(F15*$R$6) -> 0 | L15: =SUM(G15*$R$7) -> 0 | M15: =SUM(H15*$R$8) -> 0 | N15: =SUM(I15:M15) -> 0
A16: 12 | B16: 46215 | F16: =F15+D16-E15 -> 0 | G16: 0 | H16: 0 | I16: =SUM(D16*$R$4) -> 0 | J16: =SUM(E16*$R$5) -> 0 | K16: =SUM(F16*$R$6) -> 0 | L16: =SUM(G16*$R$7) -> 0 | M16: =SUM(H16*$R$8) -> 0 | N16: =SUM(I16:M16) -> 0
A17: 13 | B17: 46216 | F17: =F16+D17-E16 -> 0 | G17: 0 | H17: 0 | I17: =SUM(D17*$R$4) -> 0 | J17: =SUM(E17*$R$5) -> 0 | K17: =SUM(F17*$R$6) -> 0 | L17: =SUM(G17*$R$7) -> 0 | M17: =SUM(H17*$R$8) -> 0 | N17: =SUM(I17:M17) -> 0
A18: 14 | B18: 46217 | F18: =F17+D18-E17 -> 0 | G18: 0 | H18: 0 | I18: =SUM(D18*$R$4) -> 0 | J18: =SUM(E18*$R$5) -> 0 | K18: =SUM(F18*$R$6) -> 0 | L18: =SUM(G18*$R$7) -> 0 | M18: =SUM(H18*$R$8) -> 0 | N18: =SUM(I18:M18) -> 0
A19: 15 | B19: 46218 | F19: =F18+D19-E18 -> 0 | G19: 0 | H19: 0 | I19: =SUM(D19*$R$4) -> 0 | J19: =SUM(E19*$R$5) -> 0 | K19: =SUM(F19*$R$6) -> 0 | L19: =SUM(G19*$R$7) -> 0 | M19: =SUM(H19*$R$8) -> 0 | N19: =SUM(I19:M19) -> 0
A20: 16 | B20: 46219 | F20: =F19+D20-E19 -> 0 | G20: 0 | H20: 0 | I20: =SUM(D20*$R$4) -> 0 | J20: =SUM(E20*$R$5) -> 0 | K20: =SUM(F20*$R$6) -> 0 | L20: =SUM(G20*$R$7) -> 0 | M20: =SUM(H20*$R$8) -> 0 | N20: =SUM(I20:M20) -> 0
... A34: 30 | B34: 46233 | F34: =F33+D34-E33 -> 0 | G34: 0 | H34: 0 | I34: =SUM(D34*$R$4) -> 0 | J34: =SUM(E34*$R$5) -> 0 | K34: =SUM(F34*$R$6) -> 0 | L34: =SUM(G34*$R$7) -> 0 | M34: =SUM(H34*$R$8) -> 0 | N34: =SUM(I34:M34) -> 0
A35: 31 | I35: =SUM(D35*$R$4) -> 0 | J35: =SUM(E35*$R$5) -> 0 | K35: =SUM(F35*$R$6) -> 0 | L35: =SUM(G35*$R$7) -> 0 | M35: =SUM(H35*$R$8) -> 0 | N35: =SUM(I35:M35) -> 0
D36: =SUM(D5:D35) -> 0 | E36: =SUM(E5:E35) -> 0 | F36: =SUM(F5:F35) -> 0 | G36: =SUM(G5:G35) -> 0 | H36: =SUM(H5:H35) -> 0 | I36: =SUM(I5:I35) -> 0 | J36: =SUM(J5:J35) -> 0 | K36: =SUM(K5:K35) -> 0 | ... N36: =SUM(N5:N35) -> 0
N37: =N36*1.22 -> 0

Sheet Фармпласт Новосибирск
A1: =N37 -> 0
A2: ="Отчет по хранению товара за " & TEXT(B5,"ММММ ГГГГ") -> Отчет по хранению товара за Июль 2026 | I2: Новосибирск
A3: № | B3: дата | D3: Выгрузка кол-во | E3: Загрузка кол-во | F3: Хранение | G3: переконсолидация (тонн) | H3: Паллетирование | I3: стоимость выгрузки | J3: стоимость загрузки | K3: стоимость хранения | L3: стоимость переконс. | M3: Стоимость паллетирования | N3: итого | Q3: Цены
Q4: Выгрузка | R4: 140
A5: 1 | B5: 46204 | D5: 0 | E5: 0 | F5: 0 | G5: 0 | H5: 0 | I5: =SUM(D5*$R$4) -> 0 | J5: =SUM(E5*$R$5) -> 0 | K5: =SUM(F5*$R$6) -> 0 | L5: =SUM(G5*$R$7) -> 0 | M5: =SUM(H5*$R$8) -> 0 | N5: =SUM(I5:M5) -> 0 | Q5: Загрузка | R5: 140
A6: 2 | B6: 46205 | D6: 0 | E6: 0 | F6: =F5+D6-E5 -> 0 | G6: 0 | H6: 0 | I6: =SUM(D6*$R$4) -> 0 | J6: =SUM(E6*$R$5) -> 0 | K6: =SUM(F6*$R$6) -> 0 | L6: =SUM(G6*$R$7) -> 0 | M6: =SUM(H6*$R$8) -> 0 | N6: =SUM(I6:M6) -> 0 | Q6: Хранение | R6: 26
A7: 3 | B7: 46206 | D7: 0 | E7: 0 | F7: =F6+D7-E6 -> 0 | G7: 0 | H7: 0 | I7: =SUM(D7*$R$4) -> 0 | J7: =SUM(E7*$R$5) -> 0 | K7: =SUM(F7*$R$6) -> 0 | L7: =SUM(G7*$R$7) -> 0 | M7: =SUM(H7*$R$8) -> 0 | N7: =SUM(I7:M7) -> 0 | Q7: Переконсолидация | R7: 1200
A8: 4 | B8: 46207 | D8: 0 | E8: 0 | F8: =F7+D8-E7 -> 0 | G8: 0 | H8: 0 | I8: =SUM(D8*$R$4) -> 0 | J8: =SUM(E8*$R$5) -> 0 | K8: =SUM(F8*$R$6) -> 0 | L8: =SUM(G8*$R$7) -> 0 | M8: =SUM(H8*$R$8) -> 0 | N8: =SUM(I8:M8) -> 0 | Q8: Паллетирование | R8: 170
A9: 5 | B9: 46208 | D9: 0 | E9: 0 | F9: =F8+D9-E8 -> 0 | G9: 0 | H9: 0 | I9: =SUM(D9*$R$4) -> 0 | J9: =SUM(E9*$R$5) -> 0 | K9: =SUM(F9*$R$6) -> 0 | L9: =SUM(G9*$R$7) -> 0 | M9: =SUM(H9*$R$8) -> 0 | N9: =SUM(I9:M9) -> 0
A10: 6 | B10: 46209 | D10: 0 | E10: 0 | F10: =F9+D10-E9 -> 0 | G10: 0 | H10: 0 | I10: =SUM(D10*$R$4) -> 0 | J10: =SUM(E10*$R$5) -> 0 | K10: =SUM(F10*$R$6) -> 0 | L10: =SUM(G10*$R$7) -> 0 | M10: =SUM(H10*$R$8) -> 0 | N10: =SUM(I10:M10) -> 0
A11: 7 | B11: 46210 | D11: 0 | E11: 0 | F11: =F10+D11-E10 -> 0 | G11: 0 | H11: 0 | I11: =SUM(D11*$R$4) -> 0 | J11: =SUM(E11*$R$5) -> 0 | K11: =SUM(F11*$R$6) -> 0 | L11: =SUM(G11*$R$7) -> 0 | M11: =SUM(H11*$R$8) -> 0 | N11: =SUM(I11:M11) -> 0
A12: 8 | B12: 46211 | D12: 0 | E12: 0 | F12: =F11+D12-E11 -> 0 | G12: 0 | H12: 0 | I12: =SUM(D12*$R$4) -> 0 | J12: =SUM(E12*$R$5) -> 0 | K12: =SUM(F12*$R$6) -> 0 | L12: =SUM(G12*$R$7) -> 0 | M12: =SUM(H12*$R$8) -> 0 | N12: =SUM(I12:M12) -> 0
A13: 9 | B13: 46212 | D13: 0 | E13: 0 | F13: =F12+D13-E12 -> 0 | G13: 0 | H13: 0 | I13: =SUM(D13*$R$4) -> 0 | J13: =SUM(E13*$R$5) -> 0 | K13: =SUM(F13*$R$6) -> 0 | L13: =SUM(G13*$R$7) -> 0 | M13: =SUM(H13*$R$8) -> 0 | N13: =SUM(I13:M13) -> 0
A14: 10 | B14: 46213 | D14: 0 | E14: 0 | F14: =F13+D14-E13 -> 0 | G14: 0 | H14: 0 | I14: =SUM(D14*$R$4) -> 0 | J14: =SUM(E14*$R$5) -> 0 | K14: =SUM(F14*$R$6) -> 0 | L14: =SUM(G14*$R$7) -> 0 | M14: =SUM(H14*$R$8) -> 0 | N14: =SUM(I14:M14) -> 0
A15: 11 | B15: 46214 | D15: 0 | E15: 0 | F15: =F14+D15-E14 -> 0 | G15: 0 | H15: 0 | I15: =SUM(D15*$R$4) -> 0 | J15: =SUM(E15*$R$5) -> 0 | K15: =SUM(F15*$R$6) -> 0 | L15: =SUM(G15*$R$7) -> 0 | M15: =SUM(H15*$R$8) -> 0 | N15: =SUM(I15:M15) -> 0
A16: 12 | B16: 46215 | D16: 0 | E16: 0 | F16: =F15+D16-E15 -> 0 | G16: 0 | H16: 0 | I16: =SUM(D16*$R$4) -> 0 | J16: =SUM(E16*$R$5) -> 0 | K16: =SUM(F16*$R$6) -> 0 | L16: =SUM(G16*$R$7) -> 0 | M16: =SUM(H16*$R$8) -> 0 | N16: =SUM(I16:M16) -> 0
A17: 13 | B17: 46216 | D17: 0 | E17: 0 | F17: =F16+D17-E16 -> 0 | G17: 0 | H17: 0 | I17: =SUM(D17*$R$4) -> 0 | J17: =SUM(E17*$R$5) -> 0 | K17: =SUM(F17*$R$6) -> 0 | L17: =SUM(G17*$R$7) -> 0 | M17: =SUM(H17*$R$8) -> 0 | N17: =SUM(I17:M17) -> 0
A18: 14 | B18: 46217 | D18: 0 | E18: 0 | F18: =F17+D18-E17 -> 0 | G18: 0 | H18: 0 | I18: =SUM(D18*$R$4) -> 0 | J18: =SUM(E18*$R$5) -> 0 | K18: =SUM(F18*$R$6) -> 0 | L18: =SUM(G18*$R$7) -> 0 | M18: =SUM(H18*$R$8) -> 0 | N18: =SUM(I18:M18) -> 0
A19: 15 | B19: 46218 | D19: 0 | E19: 0 | F19: =F18+D19-E18 -> 0 | G19: 0 | H19: 0 | I19: =SUM(D19*$R$4) -> 0 | J19: =SUM(E19*$R$5) -> 0 | K19: =SUM(F19*$R$6) -> 0 | L19: =SUM(G19*$R$7) -> 0 | M19: =SUM(H19*$R$8) -> 0 | N19: =SUM(I19:M19) -> 0
A20: 16 | B20: 46219 | D20: 0 | E20: 0 | F20: =F19+D20-E19 -> 0 | G20: 0 | H20: 0 | I20: =SUM(D20*$R$4) -> 0 | J20: =SUM(E20*$R$5) -> 0 | K20: =SUM(F20*$R$6) -> 0 | L20: =SUM(G20*$R$7) -> 0 | M20: =SUM(H20*$R$8) -> 0 | N20: =SUM(I20:M20) -> 0
... A34: 30 | B34: 46233 | D34: 0 | E34: 0 | F34: =F33+D34-E33 -> 0 | G34: 0 | H34: 0 | I34: =SUM(D34*$R$4) -> 0 | J34: =SUM(E34*$R$5) -> 0 | K34: =SUM(F34*$R$6) -> 0 | L34: =SUM(G34*$R$7) -> 0 | M34: =SUM(H34*$R$8) -> 0 | N34: =SUM(I34:M34) -> 0
A35: 31 | I35: =SUM(D35*$R$4) -> 0 | J35: =SUM(E35*$R$5) -> 0 | K35: =SUM(F35*$R$6) -> 0 | L35: =SUM(G35*$R$7) -> 0 | M35: =SUM(H35*$R$8) -> 0 | N35: =SUM(I35:M35) -> 0
D36: =SUM(D5:D35) -> 0 | E36: =SUM(E5:E35) -> 0 | F36: =SUM(F5:F35) -> 0 | G36: =SUM(G5:G35) -> 0 | H36: =SUM(H5:H35) -> 0 | I36: =SUM(I5:I35) -> 0 | J36: =SUM(J5:J35) -> 0 | K36: =SUM(K5:K35) -> 0 | ... N36: =SUM(N5:N35) -> 0
N37: =N36*1.22 -> 0

Sheet Фармпласт Екатеринбург
A1: =N37 -> 0
A2: ="Отчет по хранению товара за " & TEXT(B5,"ММММ ГГГГ") -> Отчет по хранению товара за Июль 2026 | I2: Екатеринбург
A3: № | B3: дата | D3: Выгрузка кол-во | E3: Загрузка кол-во | F3: Хранение | G3: переконсолидация (тонн) | H3: Паллетирование | I3: стоимость выгрузки | J3: стоимость загрузки | K3: стоимость хранения | L3: стоимость переконс. | M3: Стоимость паллетирования | N3: итого | Q3: Цены
Q4: Выгрузка | R4: 140
A5: 1 | B5: 46204 | F5: 0 | G5: 0 | H5: 0 | I5: =SUM(D5*$R$4) -> 0 | J5: =SUM(E5*$R$5) -> 0 | K5: =SUM(F5*$R$6) -> 0 | L5: =SUM(G5*$R$7) -> 0 | M5: =SUM(H5*$R$8) -> 0 | N5: =SUM(I5:M5) -> 0 | Q5: Загрузка | R5: 140
A6: 2 | B6: 46205 | F6: =F5+D6 -> 0 | G6: 0 | H6: 0 | I6: =SUM(D6*$R$4) -> 0 | J6: =SUM(E6*$R$5) -> 0 | K6: =SUM(F6*$R$6) -> 0 | L6: =SUM(G6*$R$7) -> 0 | M6: =SUM(H6*$R$8) -> 0 | N6: =SUM(I6:M6) -> 0 | Q6: Хранение | R6: 20
A7: 3 | B7: 46206 | F7: =F6+D7-E6 -> 0 | G7: 0 | H7: 0 | I7: =SUM(D7*$R$4) -> 0 | J7: =SUM(E7*$R$5) -> 0 | K7: =SUM(F7*$R$6) -> 0 | L7: =SUM(G7*$R$7) -> 0 | M7: =SUM(H7*$R$8) -> 0 | N7: =SUM(I7:M7) -> 0 | Q7: Переконсолидация | R7: 950
A8: 4 | B8: 46207 | F8: =F7+D8-E7 -> 0 | G8: 0 | H8: 0 | I8: =SUM(D8*$R$4) -> 0 | J8: =SUM(E8*$R$5) -> 0 | K8: =SUM(F8*$R$6) -> 0 | L8: =SUM(G8*$R$7) -> 0 | M8: =SUM(H8*$R$8) -> 0 | N8: =SUM(I8:M8) -> 0 | Q8: Паллетирование | R8: 120
A9: 5 | B9: 46208 | F9: =F8+D9-E8 -> 0 | G9: 0 | H9: 0 | I9: =SUM(D9*$R$4) -> 0 | J9: =SUM(E9*$R$5) -> 0 | K9: =SUM(F9*$R$6) -> 0 | L9: =SUM(G9*$R$7) -> 0 | M9: =SUM(H9*$R$8) -> 0 | N9: =SUM(I9:M9) -> 0
A10: 6 | B10: 46209 | F10: =F9+D10-E9 -> 0 | G10: 0 | H10: 0 | I10: =SUM(D10*$R$4) -> 0 | J10: =SUM(E10*$R$5) -> 0 | K10: =SUM(F10*$R$6) -> 0 | L10: =SUM(G10*$R$7) -> 0 | M10: =SUM(H10*$R$8) -> 0 | N10: =SUM(I10:M10) -> 0
A11: 7 | B11: 46210 | F11: =F10+D11-E10 -> 0 | G11: 0 | H11: 0 | I11: =SUM(D11*$R$4) -> 0 | J11: =SUM(E11*$R$5) -> 0 | K11: =SUM(F11*$R$6) -> 0 | L11: =SUM(G11*$R$7) -> 0 | M11: =SUM(H11*$R$8) -> 0 | N11: =SUM(I11:M11) -> 0
A12: 8 | B12: 46211 | F12: =F11+D12-E11 -> 0 | G12: 0 | H12: 0 | I12: =SUM(D12*$R$4) -> 0 | J12: =SUM(E12*$R$5) -> 0 | K12: =SUM(F12*$R$6) -> 0 | L12: =SUM(G12*$R$7) -> 0 | M12: =SUM(H12*$R$8) -> 0 | N12: =SUM(I12:M12) -> 0
A13: 9 | B13: 46212 | F13: =F12+D13-E12 -> 0 | G13: 0 | H13: 0 | I13: =SUM(D13*$R$4) -> 0 | J13: =SUM(E13*$R$5) -> 0 | K13: =SUM(F13*$R$6) -> 0 | L13: =SUM(G13*$R$7) -> 0 | M13: =SUM(H13*$R$8) -> 0 | N13: =SUM(I13:M13) -> 0
A14: 10 | B14: 46213 | F14: =F13+D14-E13 -> 0 | G14: 0 | H14: 0 | I14: =SUM(D14*$R$4) -> 0 | J14: =SUM(E14*$R$5) -> 0 | K14: =SUM(F14*$R$6) -> 0 | L14: =SUM(G14*$R$7) -> 0 | M14: =SUM(H14*$R$8) -> 0 | N14: =SUM(I14:M14) -> 0
A15: 11 | B15: 46214 | F15: =F14+D15-E14 -> 0 | G15: 0 | H15: 0 | I15: =SUM(D15*$R$4) -> 0 | J15: =SUM(E15*$R$5) -> 0 | K15: =SUM(F15*$R$6) -> 0 | L15: =SUM(G15*$R$7) -> 0 | M15: =SUM(H15*$R$8) -> 0 | N15: =SUM(I15:M15) -> 0
A16: 12 | B16: 46215 | F16: =F15+D16-E15 -> 0 | G16: 0 | H16: 0 | I16: =SUM(D16*$R$4) -> 0 | J16: =SUM(E16*$R$5) -> 0 | K16: =SUM(F16*$R$6) -> 0 | L16: =SUM(G16*$R$7) -> 0 | M16: =SUM(H16*$R$8) -> 0 | N16: =SUM(I16:M16) -> 0
A17: 13 | B17: 46216 | F17: =F16+D17-E16 -> 0 | G17: 0 | H17: 0 | I17: =SUM(D17*$R$4) -> 0 | J17: =SUM(E17*$R$5) -> 0 | K17: =SUM(F17*$R$6) -> 0 | L17: =SUM(G17*$R$7) -> 0 | M17: =SUM(H17*$R$8) -> 0 | N17: =SUM(I17:M17) -> 0
A18: 14 | B18: 46217 | F18: =F17+D18-E17 -> 0 | G18: 0 | H18: 0 | I18: =SUM(D18*$R$4) -> 0 | J18: =SUM(E18*$R$5) -> 0 | K18: =SUM(F18*$R$6) -> 0 | L18: =SUM(G18*$R$7) -> 0 | M18: =SUM(H18*$R$8) -> 0 | N18: =SUM(I18:M18) -> 0
A19: 15 | B19: 46218 | F19: =F18+D19-E18 -> 0 | G19: 0 | H19: 0 | I19: =SUM(D19*$R$4) -> 0 | J19: =SUM(E19*$R$5) -> 0 | K19: =SUM(F19*$R$6) -> 0 | L19: =SUM(G19*$R$7) -> 0 | M19: =SUM(H19*$R$8) -> 0 | N19: =SUM(I19:M19) -> 0
A20: 16 | B20: 46219 | F20: =F19+D20-E19 -> 0 | G20: 0 | H20: 0 | I20: =SUM(D20*$R$4) -> 0 | J20: =SUM(E20*$R$5) -> 0 | K20: =SUM(F20*$R$6) -> 0 | L20: =SUM(G20*$R$7) -> 0 | M20: =SUM(H20*$R$8) -> 0 | N20: =SUM(I20:M20) -> 0
... A30: 26 | B30: 46229 | F30: =F29+D30-E29 -> 0 | G30: 0 | H30: 0 | I30: =SUM(D30*$R$4) -> 0 | J30: =SUM(E30*$R$5) -> 0 | K30: =SUM(F30*$R$6) -> 0 | L30: =SUM(G30*$R$7) -> 0 | M30: =SUM(H30*$R$8) -> 0 | N30: =SUM(I30:M30) -> 0
A31: 27 | B31: 46230 | F31: 0 | G31: 0 | H31: 0 | I31: =SUM(D31*$R$4) -> 0 | J31: =SUM(E31*$R$5) -> 0 | K31: =SUM(F31*$R$6) -> 0 | L31: =SUM(G31*$R$7) -> 0 | M31: =SUM(H31*$R$8) -> 0 | N31: =SUM(I31:M31) -> 0
A32: 28 | B32: 46231 | F32: =F31+D32-E31 -> 0 | G32: 0 | H32: 0 | I32: =SUM(D32*$R$4) -> 0 | J32: =SUM(E32*$R$5) -> 0 | K32: =SUM(F32*$R$6) -> 0 | L32: =SUM(G32*$R$7) -> 0 | M32: =SUM(H32*$R$8) -> 0 | N32: =SUM(I32:M32) -> 0
A33: 29 | B33: 46232 | F33: =F32+D33-E32 -> 0 | G33: 0 | H33: 0 | I33: =SUM(D33*$R$4) -> 0 | J33: =SUM(E33*$R$5) -> 0 | K33: =SUM(F33*$R$6) -> 0 | L33: =SUM(G33*$R$7) -> 0 | M33: =SUM(H33*$R$8) -> 0 | N33: =SUM(I33:M33) -> 0
A34: 30 | B34: 46233 | F34: =F33+D34-E33 -> 0 | G34: 0 | H34: 0 | I34: =SUM(D34*$R$4) -> 0 | J34: =SUM(E34*$R$5) -> 0 | K34: =SUM(F34*$R$6) -> 0 | L34: =SUM(G34*$R$7) -> 0 | M34: =SUM(H34*$R$8) -> 0 | N34: =SUM(I34:M34) -> 0
A35: 31 | G35: 0 | H35: 0 | I35: =SUM(D35*$R$4) -> 0 | J35: =SUM(E35*$R$5) -> 0 | K35: =SUM(F35*$R$6) -> 0 | L35: =SUM(G35*$R$7) -> 0 | M35: =SUM(H35*$R$8) -> 0 | N35: =SUM(I35:M35) -> 0
D36: =SUM(D5:D35) -> 0 | E36: =SUM(E5:E35) -> 0 | F36: =SUM(F5:F35) -> 0 | G36: =SUM(G5:G35) -> 0 | H36: =SUM(H5:H35) -> 0 | I36: =SUM(I5:I35) -> 0 | J36: =SUM(J5:J35) -> 0 | K36: =SUM(K5:K35) -> 0 | ... N36: =SUM(N5:N35) -> 0
N37: =N36*1.22 -> 0

Sheet Зеленодольск экспорт
A3: =IF(DAY(TODAY())>27,"Акт № от " & TEXT(TODAY(),"ДД ММММ ГГГГ"),"Акт № от " & TEXT(TODAY()-DAY(TODAY()),"ДД ММММ ГГГГ")) & " г. Зеленодольск" -> Акт № от 31 Июль 2026 г. Зеленодольск
A4: =IF(DAY(TODAY()) > 27, "выполненных работ (оказанных услуг) за " & TEXT(TODAY(),"ММММ ГГГГ"),"выполненных работ (оказанных услуг) за " & TEXT(TODAY()-DAY(TODAY()),"ММММ ГГГГ")) -> выполненных работ (оказанных услуг) за Июль 2026
A5: по Договору хранения № СХ.47103 от «10» апреля 2025 г.
A7: =IF(DAY(TODAY()) > 27,"Во исполнение Договора в период с " & TEXT(TODAY()-DAY(TODAY()-DAY(TODAY())),"ДД ММММ ГГГГ") & " г. По " & TEXT(TODAY(),"ДД ММММ ГГГГ") & " г. ХРАНИТЕЛЬ оказал ПОКЛАЖЕДАТЕЛЮ следующие услуги (работы):"," Во исполнение Договора в период с " & TEXT(TODAY()-DAY(TODAY())-DAY(TODAY()-DAY(TODAY()))+1,"ДД ММММ ГГГГ") & " г. По " & TEXT(TODAY()-DAY(TODAY()),"ДД ММММ ГГГГ") & " г. ХРАНИТЕЛЬ оказал ПОКЛАЖЕДАТЕЛЮ следующие услуги (работы):") -> Во исполнение Договора в период с 01 Июль 2026 г. По 31 Июль 2026 г. ХРАНИТЕЛЬ оказал ПОКЛАЖЕДАТЕЛЮ следующие услуги (работы):
A9: № | B9: Наименование услуг (работ) | C9: Ед. изм. | D9: Количество | E9: Цена | F9: Сумма без НДС | G9: Сумма с НДС
A10: 1 | B10: оформление документов | C10: шт. | D10: 2 | E10: 2000 | F10: =SUM(D10*E10) -> 4000 | G10: =F10*1.22 -> 4880
A11: 2 | B11: Оформление сертификата | C11: шт. | F11: =SUM(D11*E11) -> 0 | G11: =F11*1.2 -> 0
F12: =SUM(F10:F11) -> 4000 | G12: =SUM(G10:G11) -> 4880
A13: Итого: | B13: четыре тысячи рублей ноль копеек
A14: Без налога (НДС): | B14: =B13 -> четыре тысячи рублей ноль копеек
A15: Всего (с учетом НДС) | B15: четыре тысячи восемьсот восемьдесят рублей ноль копеек
A16: Вышеперечисленные услуги (работы) выполнены полностью.
A17: ПОКЛАЖЕДАТЕЛЬ претензий по объему, качеству и срокам оказания услуг претензий не имеет.
A20: ООО "ДТМ" | D20: ПАО "СИБУР Холдинг"
A22: ____________________Расстегаев Д.О. | D22: ____________________

Sheet Литейные решения
A1: =R36 -> 102164
B2: Отчет по хранению товара за Июнь
A3: № | B3: дата | D3: Выгрузка кол-во паллет | E3: Загрузка кол-во паллет | F3: Ручная загрузка | G3: Ручная выгрузка | H3: Хранение | I3: предоставление паллеты | J3: Фильмаж (паллет) | K3: стоимость выгрузки | L3: стоимость загрузки | M3: Стоимость ручной загрузки | N3: Стоимость ручной выгрузки | O3: стоимость хранения | P3: Стоимость предоставления паллета | Q3: стоимость услуги фильмаж | R3: итого
H4: (кол-во паллет)
A5: 1 | B5: 46204 | H5: 130 | K5: =SUM(D5*171) -> 0 | L5: =SUM(E5*171) -> 0 | M5: =F5*1018 -> 0 | N5: =G5*1018 -> 0 | O5: =SUM(H5*22) -> 2860 | P5: =I5*509 -> 0 | Q5: =SUM(J5)*610 -> 0 | R5: =SUM(K5:Q5) -> 2860
A6: 2 | B6: 46205 | H6: =H5+D6-E5 -> 130 | K6: =SUM(D6*171) -> 0 | L6: =SUM(E6*171) -> 0 | M6: =F6*1018 -> 0 | N6: =G6*1018 -> 0 | O6: =SUM(H6*22) -> 2860 | P6: =I6*509 -> 0 | Q6: =SUM(J6)*610 -> 0 | R6: =SUM(K6:Q6) -> 2860
A7: 3 | B7: 46206 | H7: =H6+D7-E6 -> 130 | K7: =SUM(D7*171) -> 0 | L7: =SUM(E7*171) -> 0 | M7: =F7*1018 -> 0 | N7: =G7*1018 -> 0 | O7: =SUM(H7*22) -> 2860 | P7: =I7*509 -> 0 | Q7: =SUM(J7)*610 -> 0 | R7: =SUM(K7:Q7) -> 2860
A8: 4 | B8: 46207 | H8: =H7+D8-E7 -> 130 | K8: =SUM(D8*171) -> 0 | L8: =SUM(E8*171) -> 0 | M8: =F8*1018 -> 0 | N8: =G8*1018 -> 0 | O8: =SUM(H8*22) -> 2860 | P8: =I8*509 -> 0 | Q8: =SUM(J8)*610 -> 0 | R8: =SUM(K8:Q8) -> 2860
A9: 5 | B9: 46208 | H9: =H8+D9-E8 -> 130 | K9: =SUM(D9*171) -> 0 | L9: =SUM(E9*171) -> 0 | M9: =F9*1018 -> 0 | N9: =G9*1018 -> 0 | O9: =SUM(H9*22) -> 2860 | P9: =I9*509 -> 0 | Q9: =SUM(J9)*610 -> 0 | R9: =SUM(K9:Q9) -> 2860
A10: 6 | B10: 46209 | H10: =H9+D10-E9 -> 130 | K10: =SUM(D10*171) -> 0 | L10: =SUM(E10*171) -> 0 | M10: =F10*1018 -> 0 | N10: =G10*1018 -> 0 | O10: =SUM(H10*22) -> 2860 | P10: =I10*509 -> 0 | Q10: =SUM(J10)*610 -> 0 | R10: =SUM(K10:Q10) -> 2860
A11: 7 | B11: 46210 | H11: =H10+D11-E10 -> 130 | K11: =SUM(D11*171) -> 0 | L11: =SUM(E11*171) -> 0 | M11: =F11*1018 -> 0 | N11: =G11*1018 -> 0 | O11: =SUM(H11*22) -> 2860 | P11: =I11*509 -> 0 | Q11: =SUM(J11)*610 -> 0 | R11: =SUM(K11:Q11) -> 2860
A12: 8 | B12: 46211 | H12: =H11+D12-E11 -> 130 | K12: =SUM(D12*171) -> 0 | L12: =SUM(E12*171) -> 0 | M12: =F12*1018 -> 0 | N12: =G12*1018 -> 0 | O12: =SUM(H12*22) -> 2860 | P12: =I12*509 -> 0 | Q12: =SUM(J12)*610 -> 0 | R12: =SUM(K12:Q12) -> 2860
A13: 9 | B13: 46212 | H13: =H12+D13-E12 -> 130 | K13: =SUM(D13*171) -> 0 | L13: =SUM(E13*171) -> 0 | M13: =F13*1018 -> 0 | N13: =G13*1018 -> 0 | O13: =SUM(H13*22) -> 2860 | P13: =I13*509 -> 0 | Q13: =SUM(J13)*610 -> 0 | R13: =SUM(K13:Q13) -> 2860
A14: 10 | B14: 46213 | H14: =H13+D14-E13 -> 130 | K14: =SUM(D14*171) -> 0 | L14: =SUM(E14*171) -> 0 | M14: =F14*1018 -> 0 | N14: =G14*1018 -> 0 | O14: =SUM(H14*22) -> 2860 | P14: =I14*509 -> 0 | Q14: =SUM(J14)*610 -> 0 | R14: =SUM(K14:Q14) -> 2860
A15: 11 | B15: 46214 | H15: =H14+D15-E14 -> 130 | K15: =SUM(D15*171) -> 0 | L15: =SUM(E15*171) -> 0 | M15: =F15*1018 -> 0 | N15: =G15*1018 -> 0 | O15: =SUM(H15*22) -> 2860 | P15: =I15*509 -> 0 | Q15: =SUM(J15)*610 -> 0 | R15: =SUM(K15:Q15) -> 2860
A16: 12 | B16: 46215 | H16: =H15+D16-E15 -> 130 | K16: =SUM(D16*171) -> 0 | L16: =SUM(E16*171) -> 0 | M16: =F16*1018 -> 0 | N16: =G16*1018 -> 0 | O16: =SUM(H16*22) -> 2860 | P16: =I16*509 -> 0 | Q16: =SUM(J16)*610 -> 0 | R16: =SUM(K16:Q16) -> 2860
A17: 13 | B17: 46216 | E17: 12 | H17: =H16+D17-E16 -> 130 | K17: =SUM(D17*171) -> 0 | L17: =SUM(E17*171) -> 2052 | M17: =F17*1018 -> 0 | N17: =G17*1018 -> 0 | O17: =SUM(H17*22) -> 2860 | P17: =I17*509 -> 0 | Q17: =SUM(J17)*610 -> 0 | R17: =SUM(K17:Q17) -> 4912
A18: 14 | B18: 46217 | E18: 5 | H18: =H17+D18-E17 -> 118 | K18: =SUM(D18*171) -> 0 | L18: =SUM(E18*171) -> 855 | M18: =F18*1018 -> 0 | N18: =G18*1018 -> 0 | O18: =SUM(H18*22) -> 2596 | P18: =I18*509 -> 0 | Q18: =SUM(J18)*610 -> 0 | R18: =SUM(K18:Q18) -> 3451
A19: 15 | B19: 46218 | H19: =H18+D19-E18 -> 113 | K19: =SUM(D19*171) -> 0 | L19: =SUM(E19*171) -> 0 | M19: =F19*1018 -> 0 | N19: =G19*1018 -> 0 | O19: =SUM(H19*22) -> 2486 | P19: =I19*509 -> 0 | Q19: =SUM(J19)*610 -> 0 | R19: =SUM(K19:Q19) -> 2486
A20: 16 | B20: 46219 | H20: =H19+D20-E19 -> 113 | K20: =SUM(D20*171) -> 0 | L20: =SUM(E20*171) -> 0 | M20: =F20*1018 -> 0 | N20: =G20*1018 -> 0 | O20: =SUM(H20*22) -> 2486 | P20: =I20*509 -> 0 | Q20: =SUM(J20)*610 -> 0 | R20: =SUM(K20:Q20) -> 2486
A21: 17 | B21: 46220 | H21: =H20+D21-E20 -> 113 | K21: =SUM(D21*171) -> 0 | L21: =SUM(E21*171) -> 0 | M21: =F21*1018 -> 0 | N21: =G21*1018 -> 0 | O21: =SUM(H21*22) -> 2486 | P21: =I21*509 -> 0 | Q21: =SUM(J21)*610 -> 0 | R21: =SUM(K21:Q21) -> 2486
A22: 18 | B22: 46221 | H22: =H21+D22-E21 -> 113 | K22: =SUM(D22*171) -> 0 | L22: =SUM(E22*171) -> 0 | M22: =F22*1018 -> 0 | N22: =G22*1018 -> 0 | O22: =SUM(H22*22) -> 2486 | P22: =I22*509 -> 0 | Q22: =SUM(J22)*610 -> 0 | R22: =SUM(K22:Q22) -> 2486
A23: 19 | B23: 46222 | H23: =H22+D23-E22 -> 113 | K23: =SUM(D23*171) -> 0 | L23: =SUM(E23*171) -> 0 | M23: =F23*1018 -> 0 | N23: =G23*1018 -> 0 | O23: =SUM(H23*22) -> 2486 | P23: =I23*509 -> 0 | Q23: =SUM(J23)*610 -> 0 | R23: =SUM(K23:Q23) -> 2486
A24: 20 | B24: 46223 | D24: 41 | H24: =H23+D24-E23 -> 154 | K24: =SUM(D24*171) -> 7011 | L24: =SUM(E24*171) -> 0 | M24: =F24*1018 -> 0 | N24: =G24*1018 -> 0 | O24: =SUM(H24*22) -> 3388 | P24: =I24*509 -> 0 | Q24: =SUM(J24)*610 -> 0 | R24: =SUM(K24:Q24) -> 10399
A25: 21 | B25: 46224 | E25: 1 | H25: =H24+D25-E24 -> 154 | K25: =SUM(D25*171) -> 0 | L25: =SUM(E25*171) -> 171 | M25: =F25*1018 -> 0 | N25: =G25*1018 -> 0 | O25: =SUM(H25*22) -> 3388 | P25: =I25*509 -> 0 | Q25: =SUM(J25)*610 -> 0 | R25: =SUM(K25:Q25) -> 3559
A26: 22 | B26: 46225 | E26: 21 | H26: =H25+D26-E25 -> 153 | K26: =SUM(D26*171) -> 0 | L26: =SUM(E26*171) -> 3591 | M26: =F26*1018 -> 0 | N26: =G26*1018 -> 0 | O26: =SUM(H26*22) -> 3366 | P26: =I26*509 -> 0 | Q26: =SUM(J26)*610 -> 0 | R26: =SUM(K26:Q26) -> 6957
A27: 23 | B27: 46226 | H27: =H26+D27-E26 -> 132 | K27: =SUM(D27*171) -> 0 | L27: =SUM(E27*171) -> 0 | M27: =F27*1018 -> 0 | N27: =G27*1018 -> 0 | O27: =SUM(H27*22) -> 2904 | P27: =I27*509 -> 0 | Q27: =SUM(J27)*610 -> 0 | R27: =SUM(K27:Q27) -> 2904
A28: 24 | B28: 46227 | H28: =H27+D28-E27 -> 132 | K28: =SUM(D28*171) -> 0 | L28: =SUM(E28*171) -> 0 | M28: =F28*1018 -> 0 | N28: =G28*1018 -> 0 | O28: =SUM(H28*22) -> 2904 | P28: =I28*509 -> 0 | Q28: =SUM(J28)*610 -> 0 | R28: =SUM(K28:Q28) -> 2904
A29: 25 | B29: 46228 | H29: =H28+D29-E28 -> 132 | K29: =SUM(D29*171) -> 0 | L29: =SUM(E29*171) -> 0 | M29: =F29*1018 -> 0 | N29: =G29*1018 -> 0 | O29: =SUM(H29*22) -> 2904 | P29: =I29*509 -> 0 | Q29: =SUM(J29)*610 -> 0 | R29: =SUM(K29:Q29) -> 2904
A30: 26 | B30: 46229 | H30: =H29+D30-E29 -> 132 | K30: =SUM(D30*171) -> 0 | L30: =SUM(E30*171) -> 0 | M30: =F30*1018 -> 0 | N30: =G30*1018 -> 0 | O30: =SUM(H30*22) -> 2904 | P30: =I30*509 -> 0 | Q30: =SUM(J30)*610 -> 0 | R30: =SUM(K30:Q30) -> 2904
A31: 27 | B31: 46230 | H31: =H30+D31-E30 -> 132 | K31: =SUM(D31*171) -> 0 | L31: =SUM(E31*171) -> 0 | M31: =F31*1018 -> 0 | N31: =G31*1018 -> 0 | O31: =SUM(H31*22) -> 2904 | P31: =I31*509 -> 0 | Q31: =SUM(J31)*610 -> 0 | R31: =SUM(K31:Q31) -> 2904
A32: 28 | B32: 46231 | H32: =H31+D32-E31 -> 132 | K32: =SUM(D32*171) -> 0 | L32: =SUM(E32*171) -> 0 | M32: =F32*1018 -> 0 | N32: =G32*1018 -> 0 | O32: =SUM(H32*22) -> 2904 | P32: =I32*509 -> 0 | Q32: =SUM(J32)*610 -> 0 | R32: =SUM(K32:Q32) -> 2904
A33: 29 | B33: 46232 | H33: =H32+D33-E32 -> 132 | K33: =SUM(D33*171) -> 0 | L33: =SUM(E33*171) -> 0 | M33: =F33*1018 -> 0 | N33: =G33*1018 -> 0 | O33: =SUM(H33*22) -> 2904 | P33: =I33*509 -> 0 | Q33: =SUM(J33)*610 -> 0 | R33: =SUM(K33:Q33) -> 2904
A34: 30 | B34: 46233 | H34: =H33+D34-E33 -> 132 | K34: =SUM(D34*171) -> 0 | L34: =SUM(E34*171) -> 0 | M34: =F34*1018 -> 0 | N34: =G34*1018 -> 0 | O34: =SUM(H34*22) -> 2904 | P34: =I34*509 -> 0 | Q34: =SUM(J34)*610 -> 0 | R34: =SUM(K34:Q34) -> 2904
A35: 31 | B35: 46234 | H35: =H34+D35-E34 -> 132 | K35: =SUM(D35*171) -> 0 | L35: =SUM(E35*171) -> 0 | M35: =F35*1018 -> 0 | N35: =G35*1018 -> 0 | O35: =SUM(H35*22) -> 2904 | P35: =I35*509 -> 0 | Q35: =SUM(J35)*610 -> 0 | R35: =SUM(K35:Q35) -> 2904
D36: =SUM(D5:D35) -> 41 | E36: =SUM(E5:E35) -> 39 | F36: =SUM(F5:F35) -> 0 | H36: =SUM(H5:H35) -> 4022 | K36: =SUM(K5:K35) -> 7011 | L36: =SUM(L5:L35) -> 6669 | M36: =SUM(M5:M35) -> 0 | N36: =SUM(N5:N35) -> 0 | O36: =SUM(O5:O35) -> 88484 | P36: =SUM(P5:P35) -> 0 | Q36: =SUM(Q5:Q35) -> 0 | R36: =SUM(R5:R35) -> 102164

Sheet ЛС-Техномет
A1: =R36 -> 1605.6
B2: Отчет по хранению товара за Июнь
A3: № | B3: дата | D3: Выгрузка кол-во паллет | E3: Загрузка кол-во паллет | F3: Ручная загрузка | G3: Ручная выгрузка | H3: Хранение | I3: предоставление паллеты | J3: Фильмаж (паллет) | K3: стоимость выгрузки | L3: стоимость загрузки | M3: Стоимость ручной загрузки | N3: Стоимость ручной выгрузки | O3: стоимость хранения | P3: Стоимость предоставления паллета | Q3: стоимость услуги фильмаж | R3: итого
H4: (кол-во паллет)
A5: 1 | B5: 46204 | H5: 4 | K5: =SUM(D5*168) -> 0 | L5: =SUM(E5*168) -> 0 | M5: =F5*1000 -> 0 | N5: =G5*1000 -> 0 | O5: =SUM(H5*21.6) -> 86.4 | P5: =I5*500 -> 0 | Q5: =SUM(J5)*600 -> 0 | R5: =SUM(K5:Q5) -> 86.4
A6: 2 | B6: 46205 | H6: =H5+D6-E5 -> 4 | K6: =SUM(D6*168) -> 0 | L6: =SUM(E6*168) -> 0 | M6: =F6*1000 -> 0 | N6: =G6*1000 -> 0 | O6: =SUM(H6*21.6) -> 86.4 | P6: =I6*500 -> 0 | Q6: =SUM(J6)*600 -> 0 | R6: =SUM(K6:Q6) -> 86.4
A7: 3 | B7: 46206 | H7: =H6+D7-E6 -> 4 | K7: =SUM(D7*168) -> 0 | L7: =SUM(E7*168) -> 0 | M7: =F7*1000 -> 0 | N7: =G7*1000 -> 0 | O7: =SUM(H7*21.6) -> 86.4 | P7: =I7*500 -> 0 | Q7: =SUM(J7)*600 -> 0 | R7: =SUM(K7:Q7) -> 86.4
A8: 4 | B8: 46207 | H8: =H7+D8-E7 -> 4 | K8: =SUM(D8*168) -> 0 | L8: =SUM(E8*168) -> 0 | M8: =F8*1000 -> 0 | N8: =G8*1000 -> 0 | O8: =SUM(H8*21.6) -> 86.4 | P8: =I8*500 -> 0 | Q8: =SUM(J8)*600 -> 0 | R8: =SUM(K8:Q8) -> 86.4
A9: 5 | B9: 46208 | H9: =H8+D9-E8 -> 4 | K9: =SUM(D9*168) -> 0 | L9: =SUM(E9*168) -> 0 | M9: =F9*1000 -> 0 | N9: =G9*1000 -> 0 | O9: =SUM(H9*21.6) -> 86.4 | P9: =I9*500 -> 0 | Q9: =SUM(J9)*600 -> 0 | R9: =SUM(K9:Q9) -> 86.4
A10: 6 | B10: 46209 | H10: =H9+D10-E9 -> 4 | K10: =SUM(D10*168) -> 0 | L10: =SUM(E10*168) -> 0 | M10: =F10*1000 -> 0 | N10: =G10*1000 -> 0 | O10: =SUM(H10*21.6) -> 86.4 | P10: =I10*500 -> 0 | Q10: =SUM(J10)*600 -> 0 | R10: =SUM(K10:Q10) -> 86.4
A11: 7 | B11: 46210 | E11: 3 | H11: =H10+D11-E10 -> 4 | K11: =SUM(D11*168) -> 0 | L11: =SUM(E11*168) -> 504 | M11: =F11*1000 -> 0 | N11: =G11*1000 -> 0 | O11: =SUM(H11*21.6) -> 86.4 | P11: =I11*500 -> 0 | Q11: =SUM(J11)*600 -> 0 | R11: =SUM(K11:Q11) -> 590.4
A12: 8 | B12: 46211 | H12: =H11+D12-E11 -> 1 | K12: =SUM(D12*168) -> 0 | L12: =SUM(E12*168) -> 0 | M12: =F12*1000 -> 0 | N12: =G12*1000 -> 0 | O12: =SUM(H12*21.6) -> 21.6 | P12: =I12*500 -> 0 | Q12: =SUM(J12)*600 -> 0 | R12: =SUM(K12:Q12) -> 21.6
A13: 9 | B13: 46212 | H13: =H12+D13-E12 -> 1 | K13: =SUM(D13*168) -> 0 | L13: =SUM(E13*168) -> 0 | M13: =F13*1000 -> 0 | N13: =G13*1000 -> 0 | O13: =SUM(H13*21.6) -> 21.6 | P13: =I13*500 -> 0 | Q13: =SUM(J13)*600 -> 0 | R13: =SUM(K13:Q13) -> 21.6
A14: 10 | B14: 46213 | H14: =H13+D14-E13 -> 1 | K14: =SUM(D14*168) -> 0 | L14: =SUM(E14*168) -> 0 | M14: =F14*1000 -> 0 | N14: =G14*1000 -> 0 | O14: =SUM(H14*21.6) -> 21.6 | P14: =I14*500 -> 0 | Q14: =SUM(J14)*600 -> 0 | R14: =SUM(K14:Q14) -> 21.6
A15: 11 | B15: 46214 | H15: =H14+D15-E14 -> 1 | K15: =SUM(D15*168) -> 0 | L15: =SUM(E15*168) -> 0 | M15: =F15*1000 -> 0 | N15: =G15*1000 -> 0 | O15: =SUM(H15*21.6) -> 21.6 | P15: =I15*500 -> 0 | Q15: =SUM(J15)*600 -> 0 | R15: =SUM(K15:Q15) -> 21.6
A16: 12 | B16: 46215 | H16: =H15+D16-E15 -> 1 | K16: =SUM(D16*168) -> 0 | L16: =SUM(E16*168) -> 0 | M16: =F16*1000 -> 0 | N16: =G16*1000 -> 0 | O16: =SUM(H16*21.6) -> 21.6 | P16: =I16*500 -> 0 | Q16: =SUM(J16)*600 -> 0 | R16: =SUM(K16:Q16) -> 21.6
A17: 13 | B17: 46216 | H17: =H16+D17-E16 -> 1 | K17: =SUM(D17*168) -> 0 | L17: =SUM(E17*168) -> 0 | M17: =F17*1000 -> 0 | N17: =G17*1000 -> 0 | O17: =SUM(H17*21.6) -> 21.6 | P17: =I17*500 -> 0 | Q17: =SUM(J17)*600 -> 0 | R17: =SUM(K17:Q17) -> 21.6
A18: 14 | B18: 46217 | H18: =H17+D18-E17 -> 1 | K18: =SUM(D18*168) -> 0 | L18: =SUM(E18*168) -> 0 | M18: =F18*1000 -> 0 | N18: =G18*1000 -> 0 | O18: =SUM(H18*21.6) -> 21.6 | P18: =I18*500 -> 0 | Q18: =SUM(J18)*600 -> 0 | R18: =SUM(K18:Q18) -> 21.6
A19: 15 | B19: 46218 | H19: =H18+D19-E18 -> 1 | K19: =SUM(D19*168) -> 0 | L19: =SUM(E19*168) -> 0 | M19: =F19*1000 -> 0 | N19: =G19*1000 -> 0 | O19: =SUM(H19*21.6) -> 21.6 | P19: =I19*500 -> 0 | Q19: =SUM(J19)*600 -> 0 | R19: =SUM(K19:Q19) -> 21.6
A20: 16 | B20: 46219 | H20: =H19+D20-E19 -> 1 | K20: =SUM(D20*168) -> 0 | L20: =SUM(E20*168) -> 0 | M20: =F20*1000 -> 0 | N20: =G20*1000 -> 0 | O20: =SUM(H20*21.6) -> 21.6 | P20: =I20*500 -> 0 | Q20: =SUM(J20)*600 -> 0 | R20: =SUM(K20:Q20) -> 21.6
A21: 17 | B21: 46220 | H21: =H20+D21-E20 -> 1 | K21: =SUM(D21*168) -> 0 | L21: =SUM(E21*168) -> 0 | M21: =F21*1000 -> 0 | N21: =G21*1000 -> 0 | O21: =SUM(H21*21.6) -> 21.6 | P21: =I21*500 -> 0 | Q21: =SUM(J21)*600 -> 0 | R21: =SUM(K21:Q21) -> 21.6
A22: 18 | B22: 46221 | H22: =H21+D22-E21 -> 1 | K22: =SUM(D22*168) -> 0 | L22: =SUM(E22*168) -> 0 | M22: =F22*1000 -> 0 | N22: =G22*1000 -> 0 | O22: =SUM(H22*21.6) -> 21.6 | P22: =I22*500 -> 0 | Q22: =SUM(J22)*600 -> 0 | R22: =SUM(K22:Q22) -> 21.6
A23: 19 | B23: 46222 | H23: =H22+D23-E22 -> 1 | K23: =SUM(D23*168) -> 0 | L23: =SUM(E23*168) -> 0 | M23: =F23*1000 -> 0 | N23: =G23*1000 -> 0 | O23: =SUM(H23*21.6) -> 21.6 | P23: =I23*500 -> 0 | Q23: =SUM(J23)*600 -> 0 | R23: =SUM(K23:Q23) -> 21.6
... A34: 30 | B34: 46233 | H34: =H33+D34-E33 -> 1 | K34: =SUM(D34*168) -> 0 | L34: =SUM(E34*168) -> 0 | M34: =F34*1000 -> 0 | N34: =G34*1000 -> 0 | O34: =SUM(H34*21.6) -> 21.6 | P34: =I34*500 -> 0 | Q34: =SUM(J34)*600 -> 0 | R34: =SUM(K34:Q34) -> 21.6
K35: =SUM(D35*168) -> 0 | L35: =SUM(E35*168) -> 0 | M35: =F35*1000 -> 0 | N35: =G35*1000 -> 0 | O35: =SUM(H35*21.6) -> 0 | P35: =I35*500 -> 0 | Q35: =SUM(J35)*600 -> 0 | R35: =SUM(K35:Q35) -> 0
D36: =SUM(D5:D35) -> 0 | E36: =SUM(E5:E35) -> 3 | F36: =SUM(F5:F35) -> 0 | H36: =SUM(H5:H35) -> 51 | K36: =SUM(K5:K35) -> 0 | L36: =SUM(L5:L35) -> 504 | M36: =SUM(M5:M35) -> 0 | N36: =SUM(N5:N35) -> 0 | O36: =SUM(O5:O35) -> 1101.6 | P36: =SUM(P5:P35) -> 0 | Q36: =SUM(Q5:Q35) -> 0 | R36: =SUM(R5:R35) -> 1605.6

Sheet Сандекс
A1: =S39 -> 17102.4
A4: Отчет "Сандекс" Июнь 2025 | L4: Стоимость
A5: дата | C5: Выгрузка паллет | D5: Выгрузка короб | E5: Загрузка паллет | F5: Загрузка короб | G5: Наборка короб | J5: Палетирование | K5: Хранение | L5: Выгрузка палллет | M5: Выгрузка короб | N5: Загрузка паллет | O5: Загрузка короб | P5: Наборка | Q5: Паллетирование | R5: Хранение | S5: итого
K6: 26
A7: 46204 | J7: 0 | K7: =K6+C7 -> 26 | L7: =C7*168 -> 0 | M7: =D7*4 -> 0 | N7: =E7*168 -> 0 | O7: =F7*4 -> 0 | P7: =G7*4 -> 0 | Q7: =J7*600 -> 0 | R7: =K7*21.6 -> 561.6 | S7: =SUM(L7:R7) -> 561.6
A8: 46205 | J8: 0 | K8: =K7+C8-E7 -> 26 | L8: =C8*168 -> 0 | M8: =D8*4 -> 0 | N8: =E8*168 -> 0 | O8: =F8*4 -> 0 | P8: =G8*4 -> 0 | Q8: =J8*600 -> 0 | R8: =K8*21.6 -> 561.6 | S8: =SUM(L8:R8) -> 561.6
A9: 46206 | J9: 0 | K9: =K8+C9-E8 -> 26 | L9: =C9*168 -> 0 | M9: =D9*4 -> 0 | N9: =E9*168 -> 0 | O9: =F9*4 -> 0 | P9: =G9*4 -> 0 | Q9: =J9*600 -> 0 | R9: =K9*21.6 -> 561.6 | S9: =SUM(L9:R9) -> 561.6
A10: 46207 | J10: 0 | K10: =K9+C10-E9 -> 26 | L10: =C10*168 -> 0 | M10: =D10*4 -> 0 | N10: =E10*168 -> 0 | O10: =F10*4 -> 0 | P10: =G10*4 -> 0 | Q10: =J10*600 -> 0 | R10: =K10*21.6 -> 561.6 | S10: =SUM(L10:R10) -> 561.6
A11: 46208 | J11: 0 | K11: =K10+C11-E10 -> 26 | L11: =C11*168 -> 0 | M11: =D11*4 -> 0 | N11: =E11*168 -> 0 | O11: =F11*4 -> 0 | P11: =G11*4 -> 0 | Q11: =J11*600 -> 0 | R11: =K11*21.6 -> 561.6 | S11: =SUM(L11:R11) -> 561.6
A12: 46209 | J12: 0 | K12: =K11+C12-E11 -> 26 | L12: =C12*168 -> 0 | M12: =D12*4 -> 0 | N12: =E12*168 -> 0 | O12: =F12*4 -> 0 | P12: =G12*4 -> 0 | Q12: =J12*600 -> 0 | R12: =K12*21.6 -> 561.6 | S12: =SUM(L12:R12) -> 561.6
A13: 46210 | J13: 0 | K13: =K12+C13-E12 -> 26 | L13: =C13*168 -> 0 | M13: =D13*4 -> 0 | N13: =E13*168 -> 0 | O13: =F13*4 -> 0 | P13: =G13*4 -> 0 | Q13: =J13*600 -> 0 | R13: =K13*21.6 -> 561.6 | S13: =SUM(L13:R13) -> 561.6
A14: 46211 | J14: 0 | K14: =K13+C14-E13 -> 26 | L14: =C14*168 -> 0 | M14: =D14*4 -> 0 | N14: =E14*168 -> 0 | O14: =F14*4 -> 0 | P14: =G14*4 -> 0 | Q14: =J14*600 -> 0 | R14: =K14*21.6 -> 561.6 | S14: =SUM(L14:R14) -> 561.6
A15: 46212 | E15: 1 | J15: 0 | K15: =K14+C15-E14 -> 26 | L15: =C15*168 -> 0 | M15: =D15*4 -> 0 | N15: =E15*168 -> 168 | O15: =F15*4 -> 0 | P15: =G15*4 -> 0 | Q15: =J15*600 -> 0 | R15: =K15*21.6 -> 561.6 | S15: =SUM(L15:R15) -> 729.6
A16: 46213 | J16: 0 | K16: =K15+C16-E15 -> 25 | L16: =C16*168 -> 0 | M16: =D16*4 -> 0 | N16: =E16*168 -> 0 | O16: =F16*4 -> 0 | P16: =G16*4 -> 0 | Q16: =J16*600 -> 0 | R16: =K16*21.6 -> 540 | S16: =SUM(L16:R16) -> 540
A17: 46214 | J17: 0 | K17: =K16+C17-E16 -> 25 | L17: =C17*168 -> 0 | M17: =D17*4 -> 0 | N17: =E17*168 -> 0 | O17: =F17*4 -> 0 | P17: =G17*4 -> 0 | Q17: =J17*600 -> 0 | R17: =K17*21.6 -> 540 | S17: =SUM(L17:R17) -> 540
A18: 46215 | J18: 0 | K18: =K17+C18-E17 -> 25 | L18: =C18*168 -> 0 | M18: =D18*4 -> 0 | N18: =E18*168 -> 0 | O18: =F18*4 -> 0 | P18: =G18*4 -> 0 | Q18: =J18*600 -> 0 | R18: =K18*21.6 -> 540 | S18: =SUM(L18:R18) -> 540
A19: 46216 | J19: 0 | K19: =K18+C19-E18 -> 25 | L19: =C19*168 -> 0 | M19: =D19*4 -> 0 | N19: =E19*168 -> 0 | O19: =F19*4 -> 0 | P19: =G19*4 -> 0 | Q19: =J19*600 -> 0 | R19: =K19*21.6 -> 540 | S19: =SUM(L19:R19) -> 540
A20: 46217 | J20: 0 | K20: =K19+C20-E19 -> 25 | L20: =C20*168 -> 0 | M20: =D20*4 -> 0 | N20: =E20*168 -> 0 | O20: =F20*4 -> 0 | P20: =G20*4 -> 0 | Q20: =J20*600 -> 0 | R20: =K20*21.6 -> 540 | S20: =SUM(L20:R20) -> 540
A21: 46218 | J21: 0 | K21: =K20+C21-E20 -> 25 | L21: =C21*168 -> 0 | M21: =D21*4 -> 0 | N21: =E21*168 -> 0 | O21: =F21*4 -> 0 | P21: =G21*4 -> 0 | Q21: =J21*600 -> 0 | R21: =K21*21.6 -> 540 | S21: =SUM(L21:R21) -> 540
A22: 46219 | J22: 0 | K22: =K21+C22-E21 -> 25 | L22: =C22*168 -> 0 | M22: =D22*4 -> 0 | N22: =E22*168 -> 0 | O22: =F22*4 -> 0 | P22: =G22*4 -> 0 | Q22: =J22*600 -> 0 | R22: =K22*21.6 -> 540 | S22: =SUM(L22:R22) -> 540
A23: 46220 | J23: 0 | K23: =K22+C23-E22 -> 25 | L23: =C23*168 -> 0 | M23: =D23*4 -> 0 | N23: =E23*168 -> 0 | O23: =F23*4 -> 0 | P23: =G23*4 -> 0 | Q23: =J23*600 -> 0 | R23: =K23*21.6 -> 540 | S23: =SUM(L23:R23) -> 540
A24: 46221 | J24: 0 | K24: =K23+C24-E23 -> 25 | L24: =C24*168 -> 0 | M24: =D24*4 -> 0 | N24: =E24*168 -> 0 | O24: =F24*4 -> 0 | P24: =G24*4 -> 0 | Q24: =J24*600 -> 0 | R24: =K24*21.6 -> 540 | S24: =SUM(L24:R24) -> 540
A25: 46222 | J25: 0 | K25: =K24+C25-E24 -> 25 | L25: =C25*168 -> 0 | M25: =D25*4 -> 0 | N25: =E25*168 -> 0 | O25: =F25*4 -> 0 | P25: =G25*4 -> 0 | Q25: =J25*600 -> 0 | R25: =K25*21.6 -> 540 | S25: =SUM(L25:R25) -> 540
A26: 46223 | J26: 0 | K26: =K25+C26-E25 -> 25 | L26: =C26*168 -> 0 | M26: =D26*4 -> 0 | N26: =E26*168 -> 0 | O26: =F26*4 -> 0 | P26: =G26*4 -> 0 | Q26: =J26*600 -> 0 | R26: =K26*21.6 -> 540 | S26: =SUM(L26:R26) -> 540
A27: 46224 | J27: 0 | K27: =K26+C27-E26 -> 25 | L27: =C27*168 -> 0 | M27: =D27*4 -> 0 | N27: =E27*168 -> 0 | O27: =F27*4 -> 0 | P27: =G27*4 -> 0 | Q27: =J27*600 -> 0 | R27: =K27*21.6 -> 540 | S27: =SUM(L27:R27) -> 540
... A34: 46231 | J34: 0 | K34: =K33+C34-E33 -> 25 | L34: =C34*168 -> 0 | M34: =D34*4 -> 0 | N34: =E34*168 -> 0 | O34: =F34*4 -> 0 | P34: =G34*4 -> 0 | Q34: =J34*600 -> 0 | R34: =K34*21.6 -> 540 | S34: =SUM(L34:R34) -> 540
A35: 46232 | K35: =K34+C35-E34 -> 25 | L35: =C35*168 -> 0 | M35: =D35*4 -> 0 | N35: =E35*168 -> 0 | O35: =F35*4 -> 0 | P35: =G35*4 -> 0 | Q35: =J35*600 -> 0 | R35: =K35*21.6 -> 540 | S35: =SUM(L35:R35) -> 540
A36: 46233 | K36: =K35+C36-E35 -> 25 | L36: =C36*168 -> 0 | M36: =D36*4 -> 0 | N36: =E36*168 -> 0 | O36: =F36*4 -> 0 | P36: =G36*4 -> 0 | Q36: =J36*600 -> 0 | R36: =K36*21.6 -> 540 | S36: =SUM(L36:R36) -> 540
K37: =K36+C37-E36 -> 25 | L37: =C37*168 -> 0 | M37: =D37*4 -> 0 | N37: =E37*168 -> 0 | O37: =F37*4 -> 0 | P37: =G37*4 -> 0 | Q37: =J37*600 -> 0 | R37: =K37*21.6 -> 540 | S37: =SUM(L37:R37) -> 540
A38: Итого | C38: =SUM(C7:C37) -> 0 | D38: =SUM(D7:D37) -> 0 | E38: =SUM(E7:E37) -> 1 | F38: =SUM(F7:F37) -> 0 | G38: =SUM(G7:G37) -> 0 | H38: =SUM(H7:H37) -> 0 | I38: =SUM(I7:I37) -> 0 | J38: =SUM(J7:J37) -> 0 | ... S38: =SUM(S7:S37) -> 17102.4
R39: Итого | S39: =S38 -> 17102.4

Sheet СтройТех
A1: =K36 -> 55733
A2: Отчет по хранению товара СтройТех за Июнь
A3: № | B3: дата | D3: Выгрузка кол-во паллет | E3: ручная загрузка | G3: Хранение | H3: стоимость выгрузки | I3: стоимость загр.. Работ | J3: стоимость хранения | K3: итого | L3: Расход паллет
E4: мультипак | F4: шт,. | G4: (кол-во паллет)
A5: 1 | B5: 46204 | D5: 3 | E5: 27 | G5: 50 | H5: =SUM(D5*60) -> 180 | I5: =SUM(E5*25+F5*7) -> 675 | J5: =SUM(G5*15) -> 750 | K5: =SUM(H5:J5) -> 1605 | L5: 7
A6: 2 | B6: 46205 | G6: =G5+D6-L5 -> 43 | H6: =SUM(D6*60) -> 0 | I6: =SUM(E6*25+F6*7) -> 0 | J6: =SUM(G6*15) -> 645 | K6: =SUM(H6:J6) -> 645 | L6: 0
A7: 3 | B7: 46206 | D7: 20 | F7: 15 | G7: =G6+D7-L6 -> 63 | H7: =SUM(D7*60) -> 1200 | I7: =SUM(E7*25+F7*7) -> 105 | J7: =SUM(G7*15) -> 945 | K7: =SUM(H7:J7) -> 2250 | L7: 0
A8: 4 | B8: 46207 | G8: =G7+D8-L7 -> 63 | H8: =SUM(D8*60) -> 0 | I8: =SUM(E8*25+F8*7) -> 0 | J8: =SUM(G8*15) -> 945 | K8: =SUM(H8:J8) -> 945 | L8: 0
A9: 5 | B9: 46208 | G9: =G8+D9-L8 -> 63 | H9: =SUM(D9*60) -> 0 | I9: =SUM(E9*25+F9*7) -> 0 | J9: =SUM(G9*15) -> 945 | K9: =SUM(H9:J9) -> 945 | L9: 0
A10: 6 | B10: 46209 | E10: 48 | F10: 2 | G10: =G9+D10-L9 -> 63 | H10: =SUM(D10*60) -> 0 | I10: =SUM(E10*25+F10*7) -> 1214 | J10: =SUM(G10*15) -> 945 | K10: =SUM(H10:J10) -> 2159 | L10: 11
A11: 7 | B11: 46210 | D11: 20 | G11: =G10+D11-L10 -> 72 | H11: =SUM(D11*60) -> 1200 | I11: =SUM(E11*25+F11*7) -> 0 | J11: =SUM(G11*15) -> 1080 | K11: =SUM(H11:J11) -> 2280 | L11: 0
A12: 8 | B12: 46211 | D12: 21 | G12: =G11+D12-L11 -> 93 | H12: =SUM(D12*60) -> 1260 | I12: =SUM(E12*25+F12*7) -> 0 | J12: =SUM(G12*15) -> 1395 | K12: =SUM(H12:J12) -> 2655 | L12: 0
A13: 9 | B13: 46212 | D13: 20 | E13: 33 | G13: =G12+D13-L12 -> 113 | H13: =SUM(D13*60) -> 1200 | I13: =SUM(E13*25+F13*7) -> 825 | J13: =SUM(G13*15) -> 1695 | K13: =SUM(H13:J13) -> 3720 | L13: 9
A14: 10 | B14: 46213 | D14: 20 | E14: 28 | G14: =G13+D14-L13 -> 124 | H14: =SUM(D14*60) -> 1200 | I14: =SUM(E14*25+F14*7) -> 700 | J14: =SUM(G14*15) -> 1860 | K14: =SUM(H14:J14) -> 3760 | L14: 7
A15: 11 | B15: 46214 | G15: =G14+D15-L14 -> 117 | H15: =SUM(D15*60) -> 0 | I15: =SUM(E15*25+F15*7) -> 0 | J15: =SUM(G15*15) -> 1755 | K15: =SUM(H15:J15) -> 1755
A16: 12 | B16: 46215 | G16: =G15+D16-L15 -> 117 | H16: =SUM(D16*60) -> 0 | I16: =SUM(E16*25+F16*7) -> 0 | J16: =SUM(G16*15) -> 1755 | K16: =SUM(H16:J16) -> 1755
A17: 13 | B17: 46216 | E17: 45 | F17: 3 | G17: =G16+D17-L16 -> 117 | H17: =SUM(D17*60) -> 0 | I17: =SUM(E17*25+F17*7) -> 1146 | J17: =SUM(G17*15) -> 1755 | K17: =SUM(H17:J17) -> 2901 | L17: 11
A18: 14 | B18: 46217 | G18: =G17+D18-L17 -> 106 | H18: =SUM(D18*60) -> 0 | I18: =SUM(E18*25+F18*7) -> 0 | J18: =SUM(G18*15) -> 1590 | K18: =SUM(H18:J18) -> 1590
A19: 15 | B19: 46218 | G19: =G18+D19-L18 -> 106 | H19: =SUM(D19*60) -> 0 | I19: =SUM(E19*25+F19*7) -> 0 | J19: =SUM(G19*15) -> 1590 | K19: =SUM(H19:J19) -> 1590
A20: 16 | B20: 46219 | G20: =G19+D20-L19 -> 106 | H20: =SUM(D20*60) -> 0 | I20: =SUM(E20*25+F20*7) -> 0 | J20: =SUM(G20*15) -> 1590 | K20: =SUM(H20:J20) -> 1590
A21: 17 | B21: 46220 | G21: =G20+D21-L20 -> 106 | H21: =SUM(D21*60) -> 0 | I21: =SUM(E21*25+F21*7) -> 0 | J21: =SUM(G21*15) -> 1590 | K21: =SUM(H21:J21) -> 1590
A22: 18 | B22: 46221 | G22: =G21+D22-L21 -> 106 | H22: =SUM(D22*60) -> 0 | I22: =SUM(E22*25+F22*7) -> 0 | J22: =SUM(G22*15) -> 1590 | K22: =SUM(H22:J22) -> 1590
A23: 19 | B23: 46222 | G23: =G22+D23-L22 -> 106 | H23: =SUM(D23*60) -> 0 | I23: =SUM(E23*25+F23*7) -> 0 | J23: =SUM(G23*15) -> 1590 | K23: =SUM(H23:J23) -> 1590
A24: 20 | B24: 46223 | E24: 25 | F24: 15 | G24: =G23+D24-L23 -> 106 | H24: =SUM(D24*60) -> 0 | I24: =SUM(E24*25+F24*7) -> 730 | J24: =SUM(G24*15) -> 1590 | K24: =SUM(H24:J24) -> 2320 | L24: 7
A25: 21 | B25: 46224 | E25: 44 | G25: =G24+D25-L24 -> 99 | H25: =SUM(D25*60) -> 0 | I25: =SUM(E25*25+F25*7) -> 1100 | J25: =SUM(G25*15) -> 1485 | K25: =SUM(H25:J25) -> 2585 | L25: 10
A26: 22 | B26: 46225 | E26: 20 | G26: =G25+D26-L25 -> 89 | H26: =SUM(D26*60) -> 0 | I26: =SUM(E26*25+F26*7) -> 500 | J26: =SUM(G26*15) -> 1335 | K26: =SUM(H26:J26) -> 1835 | L26: 5
A27: 23 | B27: 46226 | G27: =G26+D27-L26 -> 84 | H27: =SUM(D27*60) -> 0 | I27: =SUM(E27*25+F27*7) -> 0 | J27: =SUM(G27*15) -> 1260 | K27: =SUM(H27:J27) -> 1260
A28: 24 | B28: 46227 | E28: 35 | F28: 54 | G28: =G27+D28-L27 -> 84 | H28: =SUM(D28*60) -> 0 | I28: =SUM(E28*25+F28*7) -> 1253 | J28: =SUM(G28*15) -> 1260 | K28: =SUM(H28:J28) -> 2513 | L28: 10
A29: 25 | B29: 46228 | G29: =G28+D29-L28 -> 74 | H29: =SUM(D29*60) -> 0 | I29: =SUM(E29*25+F29*7) -> 0 | J29: =SUM(G29*15) -> 1110 | K29: =SUM(H29:J29) -> 1110
A30: 26 | B30: 46229 | G30: =G29+D30-L29 -> 74 | H30: =SUM(D30*60) -> 0 | I30: =SUM(E30*25+F30*7) -> 0 | J30: =SUM(G30*15) -> 1110 | K30: =SUM(H30:J30) -> 1110
A31: 27 | B31: 46230 | E31: 15 | F31: 15 | G31: =G30+D31-L30 -> 74 | H31: =SUM(D31*60) -> 0 | I31: =SUM(E31*25+F31*7) -> 480 | J31: =SUM(G31*15) -> 1110 | K31: =SUM(H31:J31) -> 1590 | L31: 4
A32: 28 | B32: 46231 | F32: 30 | G32: =G31+D32-L31 -> 70 | H32: =SUM(D32*60) -> 0 | I32: =SUM(E32*25+F32*7) -> 210 | J32: =SUM(G32*15) -> 1050 | K32: =SUM(H32:J32) -> 1260
A33: 29 | B33: 46232 | G33: =G32+D33-L32 -> 70 | H33: =SUM(D33*60) -> 0 | I33: =SUM(E33*25+F33*7) -> 0 | J33: =SUM(G33*15) -> 1050 | K33: =SUM(H33:J33) -> 1050
A34: 30 | B34: 46233 | E34: 4 | G34: =G33+D34-L33 -> 70 | H34: =SUM(D34*60) -> 0 | I34: =SUM(E34*25+F34*7) -> 100 | J34: =SUM(G34*15) -> 1050 | K34: =SUM(H34:J34) -> 1150 | L34: 1
B35: 46234 | G35: =G34+D35-L34 -> 69 | H35: =SUM(D35*60) -> 0 | I35: =SUM(E35*25+F35*7) -> 0 | J35: =SUM(G35*15) -> 1035 | K35: =SUM(H35:J35) -> 1035
G36: =SUM(G5:G35) -> 2697 | H36: =SUM(H5:H35) -> 6240 | I36: =SUM(I5:I35) -> 9038 | J36: =SUM(J5:J35) -> 40455 | K36: =SUM(K5:K35) -> 55733

Sheet Ергарда
A1: =J35 -> 7812 | B1: Отчет по хранению товара Ергарда за Июнь
A2: № | B2: дата | D2: Выгрузка кол-во паллет | E2: Загрузка кол-во паллет | F2: Хранение | G2: стоимость выгрузки | H2: стоимость загрузки | I2: стоимость хранения | J2: итого
F3: (кол-во паллет)
A4: 1 | B4: 46204 | F4: 21 | G4: =SUM(D4*120) -> 0 | H4: =SUM(E4*120) -> 0 | I4: =SUM(F4*12) -> 252 | J4: =SUM(G4:I4) -> 252
A5: 2 | B5: 46205 | F5: 21 | G5: =SUM(D5*120) -> 0 | H5: =SUM(E5*120) -> 0 | I5: =SUM(F5*12) -> 252 | J5: =SUM(G5:I5) -> 252
A6: 3 | B6: 46206 | F6: 21 | G6: =SUM(D6*120) -> 0 | H6: =SUM(E6*120) -> 0 | I6: =SUM(F6*12) -> 252 | J6: =SUM(G6:I6) -> 252
A7: 4 | B7: 46207 | F7: 21 | G7: =SUM(D7*120) -> 0 | H7: =SUM(E7*120) -> 0 | I7: =SUM(F7*12) -> 252 | J7: =SUM(G7:I7) -> 252
A8: 5 | B8: 46208 | F8: 21 | G8: =SUM(D8*120) -> 0 | H8: =SUM(E8*120) -> 0 | I8: =SUM(F8*12) -> 252 | J8: =SUM(G8:I8) -> 252
A9: 6 | B9: 46209 | F9: 21 | G9: =SUM(D9*120) -> 0 | H9: =SUM(E9*120) -> 0 | I9: =SUM(F9*12) -> 252 | J9: =SUM(G9:I9) -> 252
A10: 7 | B10: 46210 | F10: 21 | G10: =SUM(D10*120) -> 0 | H10: =SUM(E10*120) -> 0 | I10: =SUM(F10*12) -> 252 | J10: =SUM(G10:I10) -> 252
A11: 8 | B11: 46211 | F11: 21 | G11: =SUM(D11*120) -> 0 | H11: =SUM(E11*120) -> 0 | I11: =SUM(F11*12) -> 252 | J11: =SUM(G11:I11) -> 252
A12: 9 | B12: 46212 | F12: 21 | G12: =SUM(D12*120) -> 0 | H12: =SUM(E12*120) -> 0 | I12: =SUM(F12*12) -> 252 | J12: =SUM(G12:I12) -> 252
A13: 10 | B13: 46213 | F13: 21 | G13: =SUM(D13*120) -> 0 | H13: =SUM(E13*120) -> 0 | I13: =SUM(F13*12) -> 252 | J13: =SUM(G13:I13) -> 252
A14: 11 | B14: 46214 | F14: 21 | G14: =SUM(D14*120) -> 0 | H14: =SUM(E14*120) -> 0 | I14: =SUM(F14*12) -> 252 | J14: =SUM(G14:I14) -> 252
A15: 12 | B15: 46215 | F15: 21 | G15: =SUM(D15*120) -> 0 | H15: =SUM(E15*120) -> 0 | I15: =SUM(F15*12) -> 252 | J15: =SUM(G15:I15) -> 252
... A34: 31 | B34: 46234 | F34: 21 | G34: =SUM(D34*120) -> 0 | H34: =SUM(E34*120) -> 0 | I34: =SUM(F34*12) -> 252 | J34: =SUM(G34:I34) -> 252
G35: =SUM(G4:G34) -> 0 | H35: =SUM(H4:H34) -> 0 | I35: =SUM(I4:I34) -> 7812 | J35: =SUM(J4:J34) -> 7812

Sheet Казань_Автосервисная экспорт
A3: =IF(DAY(TODAY())>27,"Акт № от " & TEXT(TODAY(),"ДД ММММ ГГГГ"),"Акт № от " & TEXT(TODAY()-DAY(TODAY()),"ДД ММММ ГГГГ")) & " г. Казань_Автосервисная" -> Акт № от 31 Июль 2026 г. Казань_Автосервисная
A4: =IF(DAY(TODAY()) > 27, "выполненных работ (оказанных услуг) за " & TEXT(TODAY(),"ММММ ГГГГ"),"выполненных работ (оказанных услуг) за " & TEXT(TODAY()-DAY(TODAY()),"ММММ ГГГГ")) -> выполненных работ (оказанных услуг) за Июль 2026
A5: по Договору хранения № СХ.47103 от «10» апреля 2025 г.
A7: =IF(DAY(TODAY()) > 27,"Во исполнение Договора в период с " & TEXT(TODAY()-DAY(TODAY()-DAY(TODAY())),"ДД ММММ ГГГГ") & " г. По " & TEXT(TODAY(),"ДД ММММ ГГГГ") & " г. ХРАНИТЕЛЬ оказал ПОКЛАЖЕДАТЕЛЮ следующие услуги (работы):"," Во исполнение Договора в период с " & TEXT(TODAY()-DAY(TODAY())-DAY(TODAY()-DAY(TODAY()))+1,"ДД ММММ ГГГГ") & " г. По " & TEXT(TODAY()-DAY(TODAY()),"ДД ММММ ГГГГ") & " г. ХРАНИТЕЛЬ оказал ПОКЛАЖЕДАТЕЛЮ следующие услуги (работы):") -> Во исполнение Договора в период с 01 Июль 2026 г. По 31 Июль 2026 г. ХРАНИТЕЛЬ оказал ПОКЛАЖЕДАТЕЛЮ следующие услуги (работы):
A9: № | B9: Наименование услуг (работ) | C9: Ед. изм. | D9: Количество | E9: Цена | F9: Сумма без НДС | G9: Сумма с НДС
A10: 1 | B10: оформление документов | C10: шт. | D10: 20 | E10: 2000 | F10: =SUM(D10*E10) -> 40000 | G10: =F10*1.22 -> 48800
A11: 2 | B11: Оформление сертификата | C11: шт. | F11: =SUM(D11*E11) -> 0 | G11: =F11*1.2 -> 0
F12: =SUM(F10:F11) -> 40000 | G12: =SUM(G10:G11) -> 48800
A13: Итого: | B13: сорок тысяч рублей ноль копеек
A14: Без налога (НДС): | B14: =B13 -> сорок тысяч рублей ноль копеек
A15: Всего (с учетом НДС) | B15: сорок тысяч восемьсот восемьдесят рублей ноль копеек
A16: Вышеперечисленные услуги (работы) выполнены полностью.
A17: ПОКЛАЖЕДАТЕЛЬ претензий по объему, качеству и срокам оказания услуг претензий не имеет.
A20: ООО "ДТМ" | D20: ПАО "СИБУР Холдинг"
A22: ____________________Расстегаев Д.О. | D22: ____________________

Sheet Екатеринбург экспорт
A3: =IF(DAY(TODAY())>27,"Акт № от " & TEXT(TODAY(),"ДД ММММ ГГГГ"),"Акт № от " & TEXT(TODAY()-DAY(TODAY()),"ДД ММММ ГГГГ")) & " г. Екатеринбург" -> Акт № от 31 Июль 2026 г. Екатеринбург
A4: =IF(DAY(TODAY()) > 27, "выполненных работ (оказанных услуг) за " & TEXT(TODAY(),"ММММ ГГГГ"),"выполненных работ (оказанных услуг) за " & TEXT(TODAY()-DAY(TODAY()),"ММММ ГГГГ")) -> выполненных работ (оказанных услуг) за Июль 2026
A5: по Договору хранения № СХ.47103 от «10» апреля 2025 г.
A7: =IF(DAY(TODAY()) > 27,"Во исполнение Договора в период с " & TEXT(TODAY()-DAY(TODAY()-DAY(TODAY())),"ДД ММММ ГГГГ") & " г. По " & TEXT(TODAY(),"ДД ММММ ГГГГ") & " г. ХРАНИТЕЛЬ оказал ПОКЛАЖЕДАТЕЛЮ следующие услуги (работы):"," Во исполнение Договора в период с " & TEXT(TODAY()-DAY(TODAY())-DAY(TODAY()-DAY(TODAY()))+1,"ДД ММММ ГГГГ") & " г. По " & TEXT(TODAY()-DAY(TODAY()),"ДД ММММ ГГГГ") & " г. ХРАНИТЕЛЬ оказал ПОКЛАЖЕДАТЕЛЮ следующие услуги (работы):") -> Во исполнение Договора в период с 01 Июль 2026 г. По 31 Июль 2026 г. ХРАНИТЕЛЬ оказал ПОКЛАЖЕДАТЕЛЮ следующие услуги (работы):
A9: № | B9: Наименование услуг (работ) | C9: Ед. изм. | D9: Количество | E9: Цена | F9: Сумма без НДС | G9: Сумма с НДС
A10: 1 | B10: оформление документов | C10: шт. | D10: 6 | E10: 2000 | F10: =SUM(D10*E10) -> 12000 | G10: =F10*1.22 -> 14640
A11: 2 | B11: Оформление сертификата | C11: шт. | F11: =SUM(D11*E11) -> 0 | G11: =F11*1.2 -> 0
F12: =SUM(F10:F11) -> 12000 | G12: =SUM(G10:G11) -> 14640
A13: Итого: | B13: двенадцать тысяч рублей ноль копеек
A14: Без налога (НДС): | B14: =B13 -> двенадцать тысяч рублей ноль копеек
A15: Всего (с учетом НДС) | B15: четырнадцать тысяч шестьсот сорок рублей ноль копеек
A16: Вышеперечисленные услуги (работы) выполнены полностью.
A17: ПОКЛАЖЕДАТЕЛЬ претензий по объему, качеству и срокам оказания услуг претензий не имеет.
A20: ООО "ДТМ" | D20: ПАО "СИБУР Холдинг"
A22: ____________________Расстегаев Д.О. | D22: ____________________

Sheet Баумана KPI
A2: Отчет по хранению товара за Июль 2026 Баумана KPI
A3: № | B3: дата | D3: Выгрузка кол-во | E3: Загрузка кол-во | F3: Хранение | G3: Резервирование 0 | H3: Мин. Суточный резерв 0 | I3: переконсолидация (тонн) | J3: Паллетирование | K3: Взвешивание | L3: стоимость взвешивания | M3: стоимость выгрузки за 1 месяц | N3: стоимость загрузки за 1 месяц | O3: стоимость хранения за 1 месяц | P3: Доплата за хранение за 1 месяц | Q3: Доплата за ПРР за 1 месяц | R3: стоимость переконс. | S3: Стоимость паллетирования | T3: итого
A5: 1 | B5: 01.07.2026 | D5: 0 | E5: 0 | F5: 4.1 | G5: 0 | H5: 0 | I5: 0 | J5: 0 | K5: 0 | L5: 0 | M5: 0 | N5: 0 | O5: 0 | P5: 0 | Q5: 0 | R5: 0 | S5: 0 | T5: 0
A6: 2 | B6: 02.07.2026 | D6: 0 | E6: 0 | F6: 4.1 | G6: 0 | H6: 0 | I6: 0 | J6: 0 | K6: 0 | L6: 0 | M6: 0 | N6: 0 | O6: 0 | P6: 0 | Q6: 0 | R6: 0 | S6: 0 | T6: 0
A7: 3 | B7: 03.07.2026 | D7: 0 | E7: 0 | F7: 4.1 | G7: 0 | H7: 0 | I7: 0 | J7: 0 | K7: 0 | L7: 0 | M7: 0 | N7: 0 | O7: 0 | P7: 0 | Q7: 0 | R7: 0 | S7: 0 | T7: 0
A8: 4 | B8: 04.07.2026 | D8: 0 | E8: 0 | F8: 4.1 | G8: 0 | H8: 0 | I8: 0 | J8: 0 | K8: 0 | L8: 0 | M8: 0 | N8: 0 | O8: 0 | P8: 0 | Q8: 0 | R8: 0 | S8: 0 | T8: 0
A9: 5 | B9: 05.07.2026 | D9: 0 | E9: 0 | F9: 4.1 | G9: 0 | H9: 0 | I9: 0 | J9: 0 | K9: 0 | L9: 0 | M9: 0 | N9: 0 | O9: 0 | P9: 0 | Q9: 0 | R9: 0 | S9: 0 | T9: 0
A10: 6 | B10: 06.07.2026 | D10: 0 | E10: 0 | F10: 4.1 | G10: 0 | H10: 0 | I10: 0 | J10: 0 | K10: 0 | L10: 0 | M10: 0 | N10: 0 | O10: 0 | P10: 0 | Q10: 0 | R10: 0 | S10: 0 | T10: 0
A11: 7 | B11: 07.07.2026 | D11: 0 | E11: 0 | F11: 4.1 | G11: 0 | H11: 0 | I11: 0 | J11: 0 | K11: 0 | L11: 0 | M11: 0 | N11: 0 | O11: 0 | P11: 0 | Q11: 0 | R11: 0 | S11: 0 | T11: 0
A12: 8 | B12: 08.07.2026 | D12: 0 | E12: 0 | F12: 4.1 | G12: 0 | H12: 0 | I12: 0 | J12: 0 | K12: 0 | L12: 0 | M12: 0 | N12: 0 | O12: 0 | P12: 0 | Q12: 0 | R12: 0 | S12: 0 | T12: 0
A13: 9 | B13: 09.07.2026 | D13: 0 | E13: 0 | F13: 4.1 | G13: 0 | H13: 0 | I13: 0 | J13: 0 | K13: 0 | L13: 0 | M13: 0 | N13: 0 | O13: 0 | P13: 0 | Q13: 0 | R13: 0 | S13: 0 | T13: 0
A14: 10 | B14: 10.07.2026 | D14: 0 | E14: 0 | F14: 4.1 | G14: 0 | H14: 0 | I14: 0 | J14: 0 | K14: 0 | L14: 0 | M14: 0 | N14: 0 | O14: 0 | P14: 0 | Q14: 0 | R14: 0 | S14: 0 | T14: 0
A15: 11 | B15: 11.07.2026 | D15: 0 | E15: 0 | F15: 4.1 | G15: 0 | H15: 0 | I15: 0 | J15: 0 | K15: 0 | L15: 0 | M15: 0 | N15: 0 | O15: 0 | P15: 0 | Q15: 0 | R15: 0 | S15: 0 | T15: 0
A16: 12 | B16: 12.07.2026 | D16: 0 | E16: 0 | F16: 4.1 | G16: 0 | H16: 0 | I16: 0 | J16: 0 | K16: 0 | L16: 0 | M16: 0 | N16: 0 | O16: 0 | P16: 0 | Q16: 0 | R16: 0 | S16: 0 | T16: 0
... A35: 31 | B35: 31.07.2026 | D35: 0 | E35: 0 | F35: 4.1 | G35: 0 | H35: 0 | I35: 0 | J35: 0 | K35: 0 | L35: 0 | M35: 0 | N35: 0 | O35: 0 | P35: 0 | Q35: 0 | R35: 0 | S35: 0 | T35: 0
D36: 0 | E36: 0 | F36: 127.1 | G36: 0 | H36: 0 | I36: 0 | J36: 0 | K36: 0 | L36: 0 | M36: 0 | N36: 0 | O36: 1244.28 | P36: 0 | Q36: 0 | R36: 0 | S36: 0 | T36: 1244.28
T37: 1518.02

Sheet Баумана Полимеры
A2: Отчет по хранению товара за Июль 2026 Баумана Полимеры
A3: № | B3: дата | D3: Выгрузка кол-во | E3: Загрузка кол-во | F3: Хранение | G3: Резервирование 0 | H3: Мин. Суточный резерв 0 | I3: переконсолидация (тонн) | J3: Паллетирование | K3: Взвешивание | L3: стоимость взвешивания | M3: стоимость выгрузки за 1 месяц | N3: стоимость загрузки за 1 месяц | O3: стоимость хранения за 1 месяц | P3: Доплата за хранение за 1 месяц | Q3: Доплата за ПРР за 1 месяц | R3: стоимость переконс. | S3: Стоимость паллетирования | T3: итого
A5: 1 | B5: 01.07.2026 | D5: 22.5 | E5: 165.125 | F5: 9418.454 | G5: 0 | H5: 0 | I5: 0 | J5: 0 | K5: 0 | L5: 0 | M5: 0 | N5: 0 | O5: 0 | P5: 0 | Q5: 0 | R5: 0 | S5: 0 | T5: 0
A6: 2 | B6: 02.07.2026 | D6: 22.5 | E6: 67 | F6: 9373.954 | G6: 0 | H6: 0 | I6: 0 | J6: 0 | K6: 0 | L6: 0 | M6: 0 | N6: 0 | O6: 0 | P6: 0 | Q6: 0 | R6: 0 | S6: 0 | T6: 0
A7: 3 | B7: 03.07.2026 | D7: 0 | E7: 111.5 | F7: 9262.454 | G7: 0 | H7: 0 | I7: 0 | J7: 0 | K7: 0 | L7: 0 | M7: 0 | N7: 0 | O7: 0 | P7: 0 | Q7: 0 | R7: 0 | S7: 0 | T7: 0
A8: 4 | B8: 04.07.2026 | D8: 45 | E8: 111.5 | F8: 9195.954 | G8: 0 | H8: 0 | I8: 0 | J8: 0 | K8: 0 | L8: 0 | M8: 0 | N8: 0 | O8: 0 | P8: 0 | Q8: 0 | R8: 0 | S8: 0 | T8: 0
A9: 5 | B9: 05.07.2026 | D9: 45 | E9: 0 | F9: 9240.954 | G9: 0 | H9: 0 | I9: 0 | J9: 0 | K9: 0 | L9: 0 | M9: 0 | N9: 0 | O9: 0 | P9: 0 | Q9: 0 | R9: 0 | S9: 0 | T9: 0
A10: 6 | B10: 06.07.2026 | D10: 135 | E10: 89 | F10: 9286.954 | G10: 0 | H10: 0 | I10: 0 | J10: 0 | K10: 0 | L10: 0 | M10: 0 | N10: 0 | O10: 0 | P10: 0 | Q10: 0 | R10: 0 | S10: 0 | T10: 0
A11: 7 | B11: 07.07.2026 | D11: 112.5 | E11: 67.875 | F11: 9331.579 | G11: 0 | H11: 0 | I11: 0 | J11: 0 | K11: 0 | L11: 0 | M11: 0 | N11: 0 | O11: 0 | P11: 0 | Q11: 0 | R11: 0 | S11: 0 | T11: 0
A12: 8 | B12: 08.07.2026 | D12: 90 | E12: 47.25 | F12: 9374.329 | G12: 0 | H12: 0 | I12: 0 | J12: 0 | K12: 0 | L12: 0 | M12: 0 | N12: 0 | O12: 0 | P12: 0 | Q12: 0 | R12: 0 | S12: 0 | T12: 0
A13: 9 | B13: 09.07.2026 | D13: 157.475 | E13: 125.8 | F13: 9406.004 | G13: 0 | H13: 0 | I13: 4.45 | J13: 4.45 | K13: 0 | L13: 0 | M13: 0 | N13: 0 | O13: 0 | P13: 0 | Q13: 0 | R13: 1112.5 | S13: 623 | T13: 1735.5
A14: 10 | B14: 10.07.2026 | D14: 44.975 | E14: 135.7 | F14: 9315.279 | G14: 0 | H14: 0 | I14: 2.975 | J14: 2.975 | K14: 0 | L14: 0 | M14: 0 | N14: 0 | O14: 0 | P14: 0 | Q14: 0 | R14: 743.75 | S14: 416.5 | T14: 1160.25
A15: 11 | B15: 11.07.2026 | D15: 202.5 | E15: 37.875 | F15: 9479.904 | G15: 0 | H15: 0 | I15: 1.5 | J15: 1.5 | K15: 0 | L15: 0 | M15: 0 | N15: 0 | O15: 0 | P15: 0 | Q15: 0 | R15: 375 | S15: 210 | T15: 585
A16: 12 | B16: 12.07.2026 | D16: 180 | E16: 44.5 | F16: 9615.404 | G16: 0 | H16: 0 | I16: 0 | J16: 0 | K16: 0 | L16: 0 | M16: 0 | N16: 0 | O16: 0 | P16: 0 | Q16: 0 | R16: 0 | S16: 0 | T16: 0
... A35: 31 | B35: 31.07.2026 | D35: 90 | E35: 404.375 | F35: 9566.229 | G35: 0 | H35: 0 | I35: 0 | J35: 0 | K35: 0 | L35: 0 | M35: 0 | N35: 0 | O35: 0 | P35: 0 | Q35: 0 | R35: 0 | S35: 0 | T35: 0
D36: 3775.4 | E36: 3770.25 | F36: 304832.65 | G36: 0 | H36: 0 | I36: 35.875 | J36: 35.875 | K36: 0 | L36: 0 | M36: 898486.81 | N36: 926186.67 | O36: 2984245.4 | P36: 1463384.9 | Q36: 0 | R36: 8968.75 | S36: 5022.5 | T36: 6286295
T37: 7669280

Sheet Баумана Полиом
A2: Отчет по хранению товара за Июль 2026 Баумана Полиом
A3: № | B3: дата | D3: Выгрузка кол-во | E3: Загрузка кол-во | F3: Хранение | G3: Резервирование 0 | H3: Мин. Суточный резерв 0 | I3: переконсолидация (тонн) | J3: Паллетирование | K3: Взвешивание | L3: стоимость взвешивания | M3: стоимость выгрузки за 1 месяц | N3: стоимость загрузки за 1 месяц | O3: стоимость хранения за 1 месяц | P3: Доплата за хранение за 1 месяц | Q3: Доплата за ПРР за 1 месяц | R3: стоимость переконс. | S3: Стоимость паллетирования | T3: итого
A5: 1 | B5: 01.07.2026 | D5: 0 | E5: 0 | F5: 89.35 | G5: 0 | H5: 0 | I5: 0 | J5: 0 | K5: 0 | L5: 0 | M5: 0 | N5: 0 | O5: 0 | P5: 0 | Q5: 0 | R5: 0 | S5: 0 | T5: 0
A6: 2 | B6: 02.07.2026 | D6: 0 | E6: 0 | F6: 89.35 | G6: 0 | H6: 0 | I6: 0 | J6: 0 | K6: 0 | L6: 0 | M6: 0 | N6: 0 | O6: 0 | P6: 0 | Q6: 0 | R6: 0 | S6: 0 | T6: 0
A7: 3 | B7: 03.07.2026 | D7: 0 | E7: 0 | F7: 89.35 | G7: 0 | H7: 0 | I7: 0 | J7: 0 | K7: 0 | L7: 0 | M7: 0 | N7: 0 | O7: 0 | P7: 0 | Q7: 0 | R7: 0 | S7: 0 | T7: 0
A8: 4 | B8: 04.07.2026 | D8: 0 | E8: 0 | F8: 89.35 | G8: 0 | H8: 0 | I8: 0 | J8: 0 | K8: 0 | L8: 0 | M8: 0 | N8: 0 | O8: 0 | P8: 0 | Q8: 0 | R8: 0 | S8: 0 | T8: 0
A9: 5 | B9: 05.07.2026 | D9: 0 | E9: 0 | F9: 89.35 | G9: 0 | H9: 0 | I9: 0 | J9: 0 | K9: 0 | L9: 0 | M9: 0 | N9: 0 | O9: 0 | P9: 0 | Q9: 0 | R9: 0 | S9: 0 | T9: 0
A10: 6 | B10: 06.07.2026 | D10: 0 | E10: 0 | F10: 89.35 | G10: 0 | H10: 0 | I10: 0 | J10: 0 | K10: 0 | L10: 0 | M10: 0 | N10: 0 | O10: 0 | P10: 0 | Q10: 0 | R10: 0 | S10: 0 | T10: 0
A11: 7 | B11: 07.07.2026 | D11: 0 | E11: 0 | F11: 89.35 | G11: 0 | H11: 0 | I11: 0 | J11: 0 | K11: 0 | L11: 0 | M11: 0 | N11: 0 | O11: 0 | P11: 0 | Q11: 0 | R11: 0 | S11: 0 | T11: 0
A12: 8 | B12: 08.07.2026 | D12: 0 | E12: 0 | F12: 89.35 | G12: 0 | H12: 0 | I12: 0 | J12: 0 | K12: 0 | L12: 0 | M12: 0 | N12: 0 | O12: 0 | P12: 0 | Q12: 0 | R12: 0 | S12: 0 | T12: 0
A13: 9 | B13: 09.07.2026 | D13: 0 | E13: 5.5 | F13: 83.85 | G13: 0 | H13: 0 | I13: 0 | J13: 0 | K13: 0 | L13: 0 | M13: 0 | N13: 0 | O13: 0 | P13: 0 | Q13: 0 | R13: 0 | S13: 0 | T13: 0
A14: 10 | B14: 10.07.2026 | D14: 0 | E14: 0 | F14: 83.85 | G14: 0 | H14: 0 | I14: 0 | J14: 0 | K14: 0 | L14: 0 | M14: 0 | N14: 0 | O14: 0 | P14: 0 | Q14: 0 | R14: 0 | S14: 0 | T14: 0
A15: 11 | B15: 11.07.2026 | D15: 0 | E15: 0 | F15: 83.85 | G15: 0 | H15: 0 | I15: 0 | J15: 0 | K15: 0 | L15: 0 | M15: 0 | N15: 0 | O15: 0 | P15: 0 | Q15: 0 | R15: 0 | S15: 0 | T15: 0
A16: 12 | B16: 12.07.2026 | D16: 0 | E16: 0 | F16: 83.85 | G16: 0 | H16: 0 | I16: 0 | J16: 0 | K16: 0 | L16: 0 | M16: 0 | N16: 0 | O16: 0 | P16: 0 | Q16: 0 | R16: 0 | S16: 0 | T16: 0
... A35: 31 | B35: 31.07.2026 | D35: 88 | E35: 0 | F35: 215.85 | G35: 0 | H35: 0 | I35: 0 | J35: 0 | K35: 0 | L35: 0 | M35: 0 | N35: 0 | O35: 0 | P35: 0 | Q35: 0 | R35: 0 | S35: 0 | T35: 0
D36: 440 | E36: 313.5 | F36: 5723.35 | G36: 0 | H36: 0 | I36: 0 | J36: 0 | K36: 0 | L36: 0 | M36: 104713.19 | N36: 77013.33 | O36: 56030.35 | P36: 0 | Q36: 0 | R36: 0 | S36: 0 | T36: 237756.87
T37: 290063.38

Sheet Екатеринбург KPI
A2: Отчет по хранению товара за Июль 2026 Екатеринбург KPI
A3: № | B3: дата | D3: Выгрузка кол-во | E3: Загрузка кол-во | F3: Хранение | G3: Резервирование 0 | H3: Мин. Суточный резерв 0 | I3: переконсолидация (тонн) | J3: Паллетирование | K3: Взвешивание | L3: стоимость взвешивания | M3: стоимость выгрузки за 1 месяц | N3: стоимость загрузки за 1 месяц | O3: стоимость хранения за 1 месяц | P3: Доплата за хранение за 1 месяц | Q3: Доплата за ПРР за 1 месяц | R3: стоимость переконс. | S3: Стоимость паллетирования | T3: итого
A5: 1 | B5: 01.07.2026 | D5: 0 | E5: 0 | F5: 221.549 | G5: 0 | H5: 0 | I5: 0 | J5: 0 | K5: 0 | L5: 0 | M5: 0 | N5: 0 | O5: 0 | P5: 0 | Q5: 0 | R5: 0 | S5: 0 | T5: 0
A6: 2 | B6: 02.07.2026 | D6: 0 | E6: 0 | F6: 221.549 | G6: 0 | H6: 0 | I6: 0 | J6: 0 | K6: 0 | L6: 0 | M6: 0 | N6: 0 | O6: 0 | P6: 0 | Q6: 0 | R6: 0 | S6: 0 | T6: 0
A7: 3 | B7: 03.07.2026 | D7: 0 | E7: 0 | F7: 221.549 | G7: 0 | H7: 0 | I7: 0 | J7: 0 | K7: 0 | L7: 0 | M7: 0 | N7: 0 | O7: 0 | P7: 0 | Q7: 0 | R7: 0 | S7: 0 | T7: 0
A8: 4 | B8: 04.07.2026 | D8: 0 | E8: 0 | F8: 221.549 | G8: 0 | H8: 0 | I8: 0 | J8: 0 | K8: 0 | L8: 0 | M8: 0 | N8: 0 | O8: 0 | P8: 0 | Q8: 0 | R8: 0 | S8: 0 | T8: 0
A9: 5 | B9: 05.07.2026 | D9: 0 | E9: 0 | F9: 221.549 | G9: 0 | H9: 0 | I9: 0 | J9: 0 | K9: 0 | L9: 0 | M9: 0 | N9: 0 | O9: 0 | P9: 0 | Q9: 0 | R9: 0 | S9: 0 | T9: 0
A10: 6 | B10: 06.07.2026 | D10: 0 | E10: 0 | F10: 221.549 | G10: 0 | H10: 0 | I10: 0 | J10: 0 | K10: 0 | L10: 0 | M10: 0 | N10: 0 | O10: 0 | P10: 0 | Q10: 0 | R10: 0 | S10: 0 | T10: 0
A11: 7 | B11: 07.07.2026 | D11: 0 | E11: 0 | F11: 221.549 | G11: 0 | H11: 0 | I11: 0 | J11: 0 | K11: 0 | L11: 0 | M11: 0 | N11: 0 | O11: 0 | P11: 0 | Q11: 0 | R11: 0 | S11: 0 | T11: 0
A12: 8 | B12: 08.07.2026 | D12: 0 | E12: 0 | F12: 221.549 | G12: 0 | H12: 0 | I12: 0 | J12: 0 | K12: 0 | L12: 0 | M12: 0 | N12: 0 | O12: 0 | P12: 0 | Q12: 0 | R12: 0 | S12: 0 | T12: 0
A13: 9 | B13: 09.07.2026 | D13: 0 | E13: 0 | F13: 221.549 | G13: 0 | H13: 0 | I13: 0 | J13: 0 | K13: 0 | L13: 0 | M13: 0 | N13: 0 | O13: 0 | P13: 0 | Q13: 0 | R13: 0 | S13: 0 | T13: 0
A14: 10 | B14: 10.07.2026 | D14: 0 | E14: 0 | F14: 221.549 | G14: 0 | H14: 0 | I14: 0 | J14: 0 | K14: 0 | L14: 0 | M14: 0 | N14: 0 | O14: 0 | P14: 0 | Q14: 0 | R14: 0 | S14: 0 | T14: 0
A15: 11 | B15: 11.07.2026 | D15: 0 | E15: 0 | F15: 221.549 | G15: 0 | H15: 0 | I15: 0 | J15: 0 | K15: 0 | L15: 0 | M15: 0 | N15: 0 | O15: 0 | P15: 0 | Q15: 0 | R15: 0 | S15: 0 | T15: 0
A16: 12 | B16: 12.07.2026 | D16: 0 | E16: 0 | F16: 221.549 | G16: 0 | H16: 0 | I16: 0 | J16: 0 | K16: 0 | L16: 0 | M16: 0 | N16: 0 | O16: 0 | P16: 0 | Q16: 0 | R16: 0 | S16: 0 | T16: 0
... A35: 31 | B35: 31.07.2026 | D35: 0 | E35: 0 | F35: 41.799 | G35: 0 | H35: 0 | I35: 0 | J35: 0 | K35: 0 | L35: 0 | M35: 0 | N35: 0 | O35: 0 | P35: 0 | Q35: 0 | R35: 0 | S35: 0 | T35: 0
D36: 0 | E36: 179.75 | F36: 5695.719 | G36: 0 | H36: 0 | I36: 0 | J36: 0 | K36: 0 | L36: 0 | M36: 0 | N36: 17766.21 | O36: 216406.84 | P36: 0 | Q36: 0 | R36: 0 | S36: 0 | T36: 234173.05
T37: 285691.12

Sheet Екатеринбург НПЭГ
A2: Отчет по хранению товара за Июль 2026 Екатеринбург НПЭГ
A3: № | B3: дата | D3: Выгрузка кол-во | E3: Загрузка кол-во | F3: Хранение | G3: Резервирование 0 | H3: Мин. Суточный резерв 0 | I3: переконсолидация (тонн) | J3: Паллетирование | K3: Взвешивание | L3: стоимость взвешивания | M3: стоимость выгрузки за 1 месяц | N3: стоимость загрузки за 1 месяц | O3: стоимость хранения за 1 месяц | P3: Доплата за хранение за 1 месяц | Q3: Доплата за ПРР за 1 месяц | R3: стоимость переконс. | S3: Стоимость паллетирования | T3: итого
A5: 1 | B5: 01.07.2026 | D5: 0 | E5: 0 | F5: 84.594 | G5: 0 | H5: 0 | I5: 0 | J5: 0 | K5: 0 | L5: 0 | M5: 0 | N5: 0 | O5: 0 | P5: 0 | Q5: 0 | R5: 0 | S5: 0 | T5: 0
A6: 2 | B6: 02.07.2026 | D6: 0 | E6: 0 | F6: 84.594 | G6: 0 | H6: 0 | I6: 0 | J6: 0 | K6: 0 | L6: 0 | M6: 0 | N6: 0 | O6: 0 | P6: 0 | Q6: 0 | R6: 0 | S6: 0 | T6: 0
A7: 3 | B7: 03.07.2026 | D7: 0 | E7: 0 | F7: 84.594 | G7: 0 | H7: 0 | I7: 0 | J7: 0 | K7: 0 | L7: 0 | M7: 0 | N7: 0 | O7: 0 | P7: 0 | Q7: 0 | R7: 0 | S7: 0 | T7: 0
A8: 4 | B8: 04.07.2026 | D8: 0 | E8: 0 | F8: 84.594 | G8: 0 | H8: 0 | I8: 0 | J8: 0 | K8: 0 | L8: 0 | M8: 0 | N8: 0 | O8: 0 | P8: 0 | Q8: 0 | R8: 0 | S8: 0 | T8: 0
A9: 5 | B9: 05.07.2026 | D9: 0 | E9: 0 | F9: 84.594 | G9: 0 | H9: 0 | I9: 0 | J9: 0 | K9: 0 | L9: 0 | M9: 0 | N9: 0 | O9: 0 | P9: 0 | Q9: 0 | R9: 0 | S9: 0 | T9: 0
A10: 6 | B10: 06.07.2026 | D10: 0 | E10: 0 | F10: 84.594 | G10: 0 | H10: 0 | I10: 0 | J10: 0 | K10: 0 | L10: 0 | M10: 0 | N10: 0 | O10: 0 | P10: 0 | Q10: 0 | R10: 0 | S10: 0 | T10: 0
A11: 7 | B11: 07.07.2026 | D11: 0 | E11: 0 | F11: 84.594 | G11: 0 | H11: 0 | I11: 0 | J11: 0 | K11: 0 | L11: 0 | M11: 0 | N11: 0 | O11: 0 | P11: 0 | Q11: 0 | R11: 0 | S11: 0 | T11: 0
A12: 8 | B12: 08.07.2026 | D12: 0 | E12: 0 | F12: 84.594 | G12: 0 | H12: 0 | I12: 0 | J12: 0 | K12: 0 | L12: 0 | M12: 0 | N12: 0 | O12: 0 | P12: 0 | Q12: 0 | R12: 0 | S12: 0 | T12: 0
A13: 9 | B13: 09.07.2026 | D13: 0 | E13: 0 | F13: 84.594 | G13: 0 | H13: 0 | I13: 0 | J13: 0 | K13: 0 | L13: 0 | M13: 0 | N13: 0 | O13: 0 | P13: 0 | Q13: 0 | R13: 0 | S13: 0 | T13: 0
A14: 10 | B14: 10.07.2026 | D14: 0 | E14: 0 | F14: 84.594 | G14: 0 | H14: 0 | I14: 0 | J14: 0 | K14: 0 | L14: 0 | M14: 0 | N14: 0 | O14: 0 | P14: 0 | Q14: 0 | R14: 0 | S14: 0 | T14: 0
A15: 11 | B15: 11.07.2026 | D15: 0 | E15: 0 | F15: 84.594 | G15: 0 | H15: 0 | I15: 0 | J15: 0 | K15: 0 | L15: 0 | M15: 0 | N15: 0 | O15: 0 | P15: 0 | Q15: 0 | R15: 0 | S15: 0 | T15: 0
A16: 12 | B16: 12.07.2026 | D16: 0 | E16: 0 | F16: 84.594 | G16: 0 | H16: 0 | I16: 0 | J16: 0 | K16: 0 | L16: 0 | M16: 0 | N16: 0 | O16: 0 | P16: 0 | Q16: 0 | R16: 0 | S16: 0 | T16: 0
... A35: 31 | B35: 31.07.2026 | D35: 0 | E35: 0 | F35: 84.594 | G35: 0 | H35: 0 | I35: 0 | J35: 0 | K35: 0 | L35: 0 | M35: 0 | N35: 0 | O35: 0 | P35: 0 | Q35: 0 | R35: 0 | S35: 0 | T35: 0
D36: 0 | E36: 0 | F36: 2622.414 | G36: 0 | H36: 0 | I36: 0 | J36: 0 | K36: 0 | L36: 0 | M36: 0 | N36: 0 | O36: 99637.7 | P36: 0 | Q36: 0 | R36: 0 | S36: 0 | T36: 99637.7
T37: 121557.99

Sheet Екатеринбург Полимеры
A2: Отчет по хранению товара за Июль 2026 Екатеринбург Полимеры
A3: № | B3: дата | D3: Выгрузка кол-во | E3: Загрузка кол-во | F3: Хранение | G3: Резервирование 0 | H3: Мин. Суточный резерв 0 | I3: переконсолидация (тонн) | J3: Паллетирование | K3: Взвешивание | L3: стоимость взвешивания | M3: стоимость выгрузки за 1 месяц | N3: стоимость загрузки за 1 месяц | O3: стоимость хранения за 1 месяц | P3: Доплата за хранение за 1 месяц | Q3: Доплата за ПРР за 1 месяц | R3: стоимость переконс. | S3: Стоимость паллетирования | T3: итого
A5: 1 | B5: 01.07.2026 | D5: 0 | E5: 67.5 | F5: 9267.597 | G5: 0 | H5: 0 | I5: 0 | J5: 0 | K5: 0 | L5: 0 | M5: 0 | N5: 0 | O5: 0 | P5: 0 | Q5: 0 | R5: 0 | S5: 0 | T5: 0
A6: 2 | B6: 02.07.2026 | D6: 0 | E6: 87.975 | F6: 9179.622 | G6: 0 | H6: 0 | I6: 0 | J6: 0 | K6: 0 | L6: 0 | M6: 0 | N6: 0 | O6: 0 | P6: 0 | Q6: 0 | R6: 0 | S6: 0 | T6: 0
A7: 3 | B7: 03.07.2026 | D7: 0 | E7: 112.7 | F7: 9066.922 | G7: 0 | H7: 0 | I7: 0 | J7: 0 | K7: 0 | L7: 0 | M7: 0 | N7: 0 | O7: 0 | P7: 0 | Q7: 0 | R7: 0 | S7: 0 | T7: 0
A8: 4 | B8: 04.07.2026 | D8: 0 | E8: 48.75 | F8: 9018.172 | G8: 0 | H8: 0 | I8: 0 | J8: 0 | K8: 0 | L8: 0 | M8: 0 | N8: 0 | O8: 0 | P8: 0 | Q8: 0 | R8: 0 | S8: 0 | T8: 0
A9: 5 | B9: 05.07.2026 | D9: 0 | E9: 45 | F9: 8973.172 | G9: 0 | H9: 0 | I9: 0 | J9: 0 | K9: 0 | L9: 0 | M9: 0 | N9: 0 | O9: 0 | P9: 0 | Q9: 0 | R9: 0 | S9: 0 | T9: 0
A10: 6 | B10: 06.07.2026 | D10: 0 | E10: 44.5 | F10: 8928.672 | G10: 0 | H10: 0 | I10: 0 | J10: 0 | K10: 0 | L10: 0 | M10: 0 | N10: 0 | O10: 0 | P10: 0 | Q10: 0 | R10: 0 | S10: 0 | T10: 0
A11: 7 | B11: 07.07.2026 | D11: 0 | E11: 58.75 | F11: 8869.922 | G11: 0 | H11: 0 | I11: 0 | J11: 0 | K11: 0 | L11: 0 | M11: 0 | N11: 0 | O11: 0 | P11: 0 | Q11: 0 | R11: 0 | S11: 0 | T11: 0
A12: 8 | B12: 08.07.2026 | D12: 0 | E12: 45 | F12: 8824.922 | G12: 0 | H12: 0 | I12: 0 | J12: 0 | K12: 0 | L12: 0 | M12: 0 | N12: 0 | O12: 0 | P12: 0 | Q12: 0 | R12: 0 | S12: 0 | T12: 0
A13: 9 | B13: 09.07.2026 | D13: 0 | E13: 24.75 | F13: 8800.172 | G13: 0 | H13: 0 | I13: 0 | J13: 0 | K13: 0 | L13: 0 | M13: 0 | N13: 0 | O13: 0 | P13: 0 | Q13: 0 | R13: 0 | S13: 0 | T13: 0
A14: 10 | B14: 10.07.2026 | D14: 0 | E14: 47.25 | F14: 8752.922 | G14: 0 | H14: 0 | I14: 0 | J14: 0 | K14: 0 | L14: 0 | M14: 0 | N14: 0 | O14: 0 | P14: 0 | Q14: 0 | R14: 0 | S14: 0 | T14: 0
A15: 11 | B15: 11.07.2026 | D15: 0 | E15: 90 | F15: 8662.922 | G15: 0 | H15: 0 | I15: 0 | J15: 0 | K15: 0 | L15: 0 | M15: 0 | N15: 0 | O15: 0 | P15: 0 | Q15: 0 | R15: 0 | S15: 0 | T15: 0
A16: 12 | B16: 12.07.2026 | D16: 0 | E16: 22.5 | F16: 8640.422 | G16: 0 | H16: 0 | I16: 0 | J16: 0 | K16: 0 | L16: 0 | M16: 0 | N16: 0 | O16: 0 | P16: 0 | Q16: 0 | R16: 0 | S16: 0 | T16: 0
... A35: 31 | B35: 31.07.2026 | D35: 0 | E35: 102.521 | F35: 474.311 | G35: 0 | H35: 0 | I35: 0 | J35: 0 | K35: 0 | L35: 0 | M35: 0 | N35: 0 | O35: 0 | P35: 0 | Q35: 0 | R35: 0 | S35: 0 | T35: 0
D36: 5.726 | E36: 8866.512 | F36: 189900.67 | G36: 0 | H36: 0 | I36: 6.71 | J36: 6.71 | K36: 6.71 | L36: 1006.5 | M36: 786040.7 | N36: 876352.03 | O36: 7215209.2 | P36: 0 | Q36: 0 | R36: 6710 | S36: 1342 | T36: 8886660.4
T37: 10841726

Sheet Екатеринбург Полиом
A2: Отчет по хранению товара за Июль 2026 Екатеринбург Полиом
A3: № | B3: дата | D3: Выгрузка кол-во | E3: Загрузка кол-во | F3: Хранение | G3: Резервирование 0 | H3: Мин. Суточный резерв 0 | I3: переконсолидация (тонн) | J3: Паллетирование | K3: Взвешивание | L3: стоимость взвешивания | M3: стоимость выгрузки за 1 месяц | N3: стоимость загрузки за 1 месяц | O3: стоимость хранения за 1 месяц | P3: Доплата за хранение за 1 месяц | Q3: Доплата за ПРР за 1 месяц | R3: стоимость переконс. | S3: Стоимость паллетирования | T3: итого
A5: 1 | B5: 01.07.2026 | D5: 0 | E5: 0 | F5: 283.667 | G5: 0 | H5: 0 | I5: 0 | J5: 0 | K5: 0 | L5: 0 | M5: 0 | N5: 0 | O5: 0 | P5: 0 | Q5: 0 | R5: 0 | S5: 0 | T5: 0
A6: 2 | B6: 02.07.2026 | D6: 0 | E6: 0 | F6: 283.667 | G6: 0 | H6: 0 | I6: 0 | J6: 0 | K6: 0 | L6: 0 | M6: 0 | N6: 0 | O6: 0 | P6: 0 | Q6: 0 | R6: 0 | S6: 0 | T6: 0
A7: 3 | B7: 03.07.2026 | D7: 0 | E7: 0 | F7: 283.667 | G7: 0 | H7: 0 | I7: 0 | J7: 0 | K7: 0 | L7: 0 | M7: 0 | N7: 0 | O7: 0 | P7: 0 | Q7: 0 | R7: 0 | S7: 0 | T7: 0
A8: 4 | B8: 04.07.2026 | D8: 0 | E8: 0 | F8: 283.667 | G8: 0 | H8: 0 | I8: 0 | J8: 0 | K8: 0 | L8: 0 | M8: 0 | N8: 0 | O8: 0 | P8: 0 | Q8: 0 | R8: 0 | S8: 0 | T8: 0
A9: 5 | B9: 05.07.2026 | D9: 0 | E9: 21.975 | F9: 261.692 | G9: 0 | H9: 0 | I9: 0 | J9: 0 | K9: 0 | L9: 0 | M9: 0 | N9: 0 | O9: 0 | P9: 0 | Q9: 0 | R9: 0 | S9: 0 | T9: 0
A10: 6 | B10: 06.07.2026 | D10: 0 | E10: 0 | F10: 261.692 | G10: 0 | H10: 0 | I10: 0 | J10: 0 | K10: 0 | L10: 0 | M10: 0 | N10: 0 | O10: 0 | P10: 0 | Q10: 0 | R10: 0 | S10: 0 | T10: 0
